Workbook

Sheet For Hire 2008-09
A1: Rank | B1: Rank | C1: Company | D1: Revenue | E1: Net income | F1: Employee | G1: Tractors | H1: Truck &Van | I1: Trailers | J1: aircraft | K1: container | L1: chassis | N1: SCAC_Self
A2: 2009 | B2: 2008 | D2: thousand
A3: Rank | C3: Company | D3: Revenue | E3: NetIncome | F3: NumberEmployees | G3: NumberTractors | H3: NumberTruckVans | I3: NumberTrailers | J3: Aircraft | K3: Container | L3: Chassis | M3: AssetYear | N3: SCAC_Self
A4: 1 | B4: 1 | C4: UPS Inc | D4: 45297000 | E4: 2152000 | F4: 408000 | G4: 12268 | H4: 66425 | I4: 22015 | J4: 253 | M4: 2010 | N4: UPSF
A5: 2 | B5: 2 | C5: FedEx Corp | D5: 34734000 | E5: 1184000 | F5: 280000 | G5: 22800 | H5: 60900 | I5: 0 | J5: 664 | M5: 2010 | N5: FDTB
A6: 3 | B6: 3 | C6: DHL USA | D6: 6586872 | G6: 46 | H6: 2683 | I6: 28 | M6: 2010 | N6: DMAL
A7: 4 | B7: 4 | C7: YRC Worldwide Inc. | D7: 5282778 | E7: -622019 | F7: 36000 | G7: 18600 | H7: 400 | I7: 65600 | M7: 2010 | N7: RDWY
A8: 5 | B8: 5 | C8: Ryder System | D8: 4887254 | E8: 61945 | F8: 22900 | G8: 49328 | H8: 72527 | I8: 49660 | M8: 2010 | N8: Ryder
A9: 6 | B9: 6 | C9: Con-way Inc. | D9: 4269239 | E9: -110936 | F9: 27400 | G9: 49328 | H9: 72527 | I9: 49660 | M9: 2010 | N9: CNWY
A10: 7 | B10: 7 | C10: Penske Truck Leasing Co | D10: 4000000 | F10: 18000 | G10: 12060 | H10: 105 | I10: 33028 | M10: 2010 | N10: PSKL
A11: 8 | B11: 8 | C11: J.B. Hunt Transport Services | D11: 3203321 | E11: 136435 | F11: 14171 | G11: 0 | H11: 151350 | I11: 53200 | M11: 2010 | N11: QPMT
A12: 9 | B12: 9 | C12: Schneider National Inc | D12: 2900000 | F12: 18468 | G12: 9169 | H12: 0 | I12: 21951 | K12: 40236 | M12: 2010 | N12: SCNN
A13: 10 | B13: 10 | C13: Swift Transportation | D13: 2571000 | F13: 15500 | G13: 16025 | H13: 0 | I13: 49200 | K13: 4300 | M13: 2010 | N13: SWFT
A14: 11 | B14: 13 | C14: Landstar System | D14: 2008796 | E14: 69950 | F14: 1374 | G14: 8519 | H14: 0 | I14: 13302 | M14: 2010 | N14: LRGR
A15: 12 | B15: 12 | C15: Sirva Inc. | D15: 1698900 | F15: 2600 | G15: 2627 | H15: 1477 | I15: 4362 | M15: 2010 | N15: Sirva | O15: not found
A16: 13 | B16: 14 | C16: Werner Enterprises | D16: 1666470 | E16: 56584 | F16: 11352 | G16: 7250 | H16: 0 | I16: 23880 | M16: 2010 | N16: WENP
A17: 14 | B17: 15 | C17: TransForce Inc. | D17: 1618111 | E17: 9577 | F17: 13900 | G17: 6700 | H17: 0 | I17: 12000 | M17: 2010 | N17: TransForce | O17: not found
A18: 15 | B18: 17 | C18: UniGroup Inc. | D18: 1600000 | F18: 1050 | G18: 6401 | H18: 4343 | I18: 10615 | K18: 735 | M18: 2010 | N18: AERM
A19: 16 | B19: 18 | C19: Arkansas Best Corp. | D19: 1472901 | E19: -127889 | F19: 10347 | G19: 3962 | H19: 73 | I19: 19764 | M19: 2010 | N19: Arkansas | O19: not found
A20: 17 | B20: 19 | C20: U.S. Xpress Enterprises | D20: 1394537 | F20: 10566 | G20: 8536 | H20: 0 | I20: 21458 | M20: 2010 | N20: USXI
A21: 18 | B21: 21 | C21: Estes Express Lines | D21: 1304000 | F21: 12469 | G21: 5547 | H21: 315 | I21: 21994 | M21: 2010 | N21: EXLA
A22: 19 | B22: 22 | C22: Purolator Courier Ltd. | D22: 1256245 | F22: 11300 | G22: 493 | H22: 3833 | I22: 1113 | J22: 18 | M22: 2010 | N22: Purolator | O22: not found
A23: 20 | B23: 20 | C23: Old Dominion Freight Line | D23: 1245005 | E23: 34871 | F23: 9608 | G23: 5390 | H23: 114 | I23: 21185 | M23: 2010 | N23: ODFL
A24: 21 | B24: 23 | C24: Greatwide Logistics Services | D24: 1000000 | F24: 3200 | G24: 4967 | H24: 0 | I24: 5628 | M24: 2010 | N24: ATGL
A25: 22 | B25: 30 | C25: C.R. England Inc. | D25: 919092 | E25: 48521 | F25: 5531 | G25: 3552 | H25: 0 | I25: 5425 | K25: 320 | M25: 2010 | N25: ENGI
A26: 23 | B26: 24 | C26: Crete Carrier Corp. | D26: 850000 | F26: 5750 | G26: 5100 | H26: 0 | I26: 13500 | M26: 2010 | N26: CRCR
A27: 24 | B27: 25 | C27: Saia Inc. | D27: 849141 | E27: -7875 | F27: 7200 | G27: 3390 | H27: 127 | I27: 11089 | M27: 2010 | N27: SAIA
A28: 25 | B28: 32 | C28: Prime Inc | D28: 837382 | E28: 92248 | F28: 3528 | G28: 4418 | H28: 0 | I28: 6149 | M28: 2010 | N28: PDSI
A29: 26 | B29: 35 | C29: NFI Industries | D29: 810000 | F29: 5500 | G29: 2233 | H29: 0 | I29: 7350 | M29: 2010 | N29: NFAQ
A30: 27 | B30: 26 | C30: Averitt Express | D30: 768348 | G30: 3668 | H30: 48 | I30: 12210 | M30: 2010 | N30: AVRT
A31: 28 | B31: 27 | C31: Atlas World Group | D31: 715000 | F31: 350 | G31: 2321 | H31: 1670 | I31: 4218 | M31: 2010 | N31: ALQK
A32: 29 | B32: 33 | C32: Southeastern Freight Lines | D32: 703354 | F32: 6883 | G32: 3136 | H32: 27 | I32: 9387 | M32: 2010 | N32: SEFL
A33: 30 | B33: 31 | C33: Ruan Transportation Management Systems | D33: 680134 | F33: 4553 | G33: 2666 | H33: 18 | I33: 4450 | M33: 2010 | N33: RLCF
A34: 31 | B34: 36 | C34: Lynden Inc. | D34: 680000 | F34: 2267 | G34: 711 | H34: 62 | I34: 2735 | K34: 5605 | M34: 2010 | N34: LTIA
A35: 32 | B35: 28 | C35: CRST International | D35: 679622 | F35: 3740 | G35: 2952 | H35: 0 | I35: 4973 | M35: 2010 | N35: CRFR
A36: 33 | B36: 42 | C36: Kenan Advantage Group | D36: 672113 | F36: 5622 | G36: 3231 | H36: 0 | I36: 3294 | M36: 2010 | N36: AVTK
A37: 34 | B37: 38 | C37: Knight Transportation | D37: 651721 | E37: 50563 | F37: 4500 | G37: 3736 | H37: 0 | I37: 8493 | M37: 2010 | N37: Knight | O37: subsidiaries found
A38: 35 | B38: 40 | C38: Vitran Corp. | D38: 629260 | E38: -3972 | F38: 4832 | G38: 2338 | H38: 0 | I38: 6967 | K38: 519 | L38: 451 | M38: 2010 | N38: VITR
A39: 36 | B39: 34 | C39: Quality Distribution Inc. | D39: 613609 | E39: -180534 | F39: 810 | G39: 2839 | H39: 0 | I39: 6410 | M39: 2010 | N39: QTKI
A40: 37 | B40: 37 | C40: Covenant Transportation Group | D40: 588687 | E40: -25030 | F40: 4819 | G40: 3206 | H40: 0 | I40: 8005 | M40: 2010 | N40: CVTH
A41: 38 | B41: 29 | C41: Anderson Trucking Service | D41: 569692 | F41: 1150 | G41: 1900 | H41: 0 | I41: 5500 | M41: 2010 | N41: ANNN
A42: 39 | B42: 44 | C42: Marten Transport | D42: 505874 | E42: 16267 | F42: 2666 | G42: 2264 | H42: 0 | I42: 3958 | M42: 2010 | N42: MTEN
A43: 40 | B43: 41 | C43: Trimac Group | D43: 505000 | F43: 4200 | G43: 1874 | H43: 0 | I43: 4918 | M43: 2010 | N43: TSUH
A44: 41 | B44: 39 | C44: Universal Truckload Services Inc. | D44: 503230 | E44: 4900 | F44: 630 | G44: 3558 | H44: 0 | I44: 5200 | M44: 2010 | N44: UTVE
A45: 42 | B45: 45 | C45: Celadon Group1 | D45: 490338 | E45: 2500 | F45: 3777 | G45: 3488 | H45: 0 | I45: 9900 | M45: 2010 | N45: CDNK
A46: 43 | B46: 48 | C46: Stevens Transport | D46: 479291 | E46: 64831 | F46: 2450 | G46: 2400 | H46: 0 | I46: 3050 | M46: 2010 | N46: STVV
A47: 44 | B47: 47 | C47: Dart Transit Co. | D47: 474000 | F47: 479 | G47: 2539 | H47: 0 | I47: 7385 | K47: 350 | M47: 2010 | N47: ADTS
A48: 45 | B48: 46 | C48: Interstate Distributor Co | D48: 469622 | F48: 2706 | G48: 1964 | H48: 0 | I48: 7340 | M48: 2010 | N48: IPNS
A49: 46 | B49: 43 | C49: Heartland Express | D49: 459539 | E49: 56949 | F49: 2781 | G49: 3000 | H49: 0 | I49: 8500 | M49: 2010 | N49: NDIJ
A50: 47 | B50: 49 | C50: Roadrunner Transportation Systems | D50: 450351 | E50: -1783 | F50: 1040 | G50: 1300 | H50: 0 | I50: 900 | M50: 2010 | N50: MGAS
A51: 48 | C51: TransX Group | D51: 448666 | F51: 2544 | G51: 1487 | H51: 39 | I51: 3925 | K51: 920 | M51: 2010 | N51: DKXP
A52: 49 | C52: Western Express | D52: 439000 | G52: 2500 | H52: 0 | I52: 6250 | M52: 2010 | N52: WESD
A53: 50 | B53: 57 | C53: Shevell Group | D53: 434000 | F53: 3400 | G53: 2660 | H53: 141 | I53: 5200 | M53: 2010 | N53: Shevell | O53: not found
A54: 51 | B54: 51 | C54: AAA Cooper Transportation | D54: 420000 | F54: 4200 | G54: 2350 | H54: 85 | I54: 6250 | M54: 2010 | N54: AACT
A55: 52 | B55: 54 | C55: Forward Air Corp. | D55: 417410 | E55: 9802 | F55: 2755 | G55: =464*1027/(1027 + 177) -> 395.78738 | H55: =464*177/(1027 + 177) -> 68.212625 | I55: 2310 | M55: 2010 | N55: FAFN
A56: 53 | B56: 52 | C56: Comcar Industries | D56: 401279 | F56: 3294 | G56: 2803 | H56: 0 | I56: 5575 | M56: 2010 | N56: Comcar | O56: subsidiaries found
A57: 54 | B57: 50 | C57: USA Truck | D57: 382368 | E57: -7177 | F57: 3000 | G57: 2344 | H57: 0 | I57: 6904 | M57: 2010 | N57: USAT
A58: 55 | B58: 59 | C58: RoadLink | D58: 374000 | F58: 2400 | G58: 1790 | H58: 0 | I58: 457 | M58: 2010 | N58: RDLK
A59: 56 | B59: 53 | C59: Frozen Food Express Industries | D59: 373051 | E59: -16415 | F59: 2187 | G59: 1943 | H59: 0 | I59: 3786 | M59: 2010 | N59: FRZF
A60: 57 | B60: 60 | C60: Canada Cartage System | D60: 350520 | G60: 2000 | H60: 430 | I60: 2300 | M60: 2010 | N60: CACG
A61: 58 | B61: 55 | C61: Contrans Group | D61: 327374 | E61: 20114 | F61: 1600 | G61: 1100 | H61: 0 | I61: 2200 | M61: 2010 | N61: BCFG
A62: 59 | B62: 56 | C62: Mullen Group | D62: 326071 | F62: 1000 | G62: 980 | H62: 644 | I62: 2771 | K62: 750 | M62: 2010 | N62: MULM
A63: 60 | B63: 61 | C63: Central Refrigerated Service Inc | D63: 322103 | F63: 1430 | G63: 1720 | H63: 0 | I63: 2680 | M63: 2010 | N63: CRFS
A64: 61 | B64: 70 | C64: Dynamex Inc | D64: 301924 | E64: 7866 | F64: 1500 | G64: 97 | H64: 745 | I64: 2404 | M64: 2010 | N64: DYXW
A65: 62 | B65: 62 | C65: P.A.M. Transportation Services Inc | D65: 291910 | E65: -10847 | F65: 2591 | G65: 1731 | H65: 0 | I65: 4630 | M65: 2010 | N65: PAMT
A66: 63 | B66: 66 | C66: Challenger Group3 | D66: 285674 | F66: 2300 | G66: 3081 | H66: 34 | I66: 3563 | K66: 400 | M66: 2010 | N66: CGFR
A67: 64 | B67: 77 | C67: Gordon Trucking Inc. | D67: 285000 | F67: 1900 | G67: 1500 | H67: 0 | I67: 4200 | M67: 2010 | N67: GORK
A68: 65 | B68: 58 | C68: Mercer Transportation | D68: 282166 | F68: 214 | G68: 1700 | H68: 0 | I68: 1850 | M68: 2010 | N68: MCET
A69: 66 | B69: 88 | C69: 3PD Inc. | D69: 271000 | F69: 500 | G69: 539 | H69: 539 | I69: 0 | M69: 2010 | N69: TPIB
A70: 67 | B70: 80 | C70: TransAm Trucking | D70: 267738 | F70: 663 | G70: 1347 | H70: 0 | I70: 2400 | M70: 2010 | N70: TAMI
A71: 68 | B71: 65 | C71: Graebel Cos. | D71: 261000 | E71: -3300 | F71: 1531 | G71: 805 | H71: 472 | I71: 1036 | M71: 2010 | N71: Graebel | O71: not found
A72: 69 | B72: 76 | C72: KLLM Transport Services | D72: 260234 | F72: 1013 | G72: 1550 | H72: 0 | I72: 2100 | M72: 2010 | N72: KLMI
A73: 70 | B73: 64 | C73: Cardinal Logistics Management | D73: 257000 | F73: 1811 | G73: 1201 | H73: 264 | I73: 4297 | M73: 2010 | N73: CHWK
A74: 71 | B74: 69 | C74: The Suddath Cos. | D74: 255221 | E74: 10291 | F74: 940 | G74: 216 | H74: 217 | I74: 412 | K74: 1600 | M74: 2010 | N74: SGLN
A75: 72 | B75: 67 | C75: Pitt Ohio Express | D75: 255198 | E75: 9420 | F75: 2042 | G75: 682 | H75: 436 | I75: 1747 | M75: 2010 | N75: PITD
A76: 73 | B76: 73 | C76: Super Service Holdings | D76: 250000 | G76: 1154 | H76: 0 | I76: 2830 | M76: 2010 | N76: SUSE
A77: 74 | B77: 83 | C77: Mesilla Valley Transportation | D77: 232000 | F77: 1500 | G77: 1020 | H77: 0 | I77: 3900 | M77: 2010 | N77: MSLV
A78: 75 | B78: 78 | C78: Specialized Transportation Inc | D78: 230000 | E78: 12030 | F78: 225 | G78: 643 | H78: 200 | I78: 1100 | M78: 2010 | N78: SZXE
A79: 76 | B79: 81 | C79: Calyx Transportation Group | D79: 228714 | F79: 1800 | G79: 365 | H79: 33 | I79: 1158 | M79: 2010 | N79: Calyx | O79: subsidiaries found
A80: 77 | B80: 74 | C80: Roehl Transport | D80: 228057 | F80: 1955 | G80: 1873 | H80: 4 | I80: 4722 | M80: 2010 | N80: ROEV
A81: 78 | C81: Koch Companies Inc. | D81: 226700 | F81: 1000 | G81: 735 | H81: 0 | I81: 2200 | M81: 2010 | N81: KLOG
A82: 79 | B82: 63 | C82: Bridge Terminal Transport Inc | D82: 224157 | F82: 300 | G82: 1414 | H82: 0 | I82: 0 | L82: 700 | M82: 2010 | N82: BTTM
A83: 80 | B83: 82 | C83: Epes Carriers Inc | D83: 218434 | F83: 1206 | G83: 1091 | H83: 0 | I83: 3920 | M83: 2010 | N83: EPES
A84: 81 | B84: 86 | C84: Dayton Freight Lines Inc | D84: 213500 | F84: 2200 | G84: 996 | H84: 19 | I84: 2205 | M84: 2010 | N84: DAFG
A85: 82 | B85: 84 | C85: Central Freight Lines | D85: 207000 | F85: 3235 | G85: 2351 | H85: 0 | I85: 8464 | M85: 2010 | N85: CFMH
A86: 83 | B86: 85 | C86: Bennett International Group | D86: 206477 | F86: 574 | G86: 615 | H86: 667 | I86: 1178 | M86: 2010 | N86: BGME
A87: 84 | B87: 90 | C87: A. Duie Pyle Cos. | D87: 205000 | F87: 2455 | G87: 800 | H87: 26 | I87: 1451 | M87: 2010 | N87: PYLE
A88: 85 | B88: 79 | C88: Transport America | D88: 203178 | F88: 1205 | G88: 1156 | H88: 0 | I88: 3855 | M88: 2010 | N88: EXTO | O88: Express TA
A89: 86 | B89: 95 | C89: Cowan Systems | D89: 199668 | F89: 920 | G89: 1070 | H89: 0 | I89: 3737 | M89: 2010 | N89: CWAS
A90: 87 | B90: 87 | C90: United Road Services | D90: 198000 | E90: 1700 | F90: 1200 | G90: 1126 | H90: 0 | I90: 908 | M90: 2010 | N90: URDS
A91: 88 | B91: 93 | C91: Navajo Express | D91: 197000 | E91: 6200 | F91: 609 | G91: 751 | H91: 0 | I91: 1677 | M91: 2010 | N91: NAVE
A92: 89 | B92: 71 | C92: Maverick USA | D92: 190658 | F92: 1262 | G92: 1292 | H92: 0 | I92: 1807 | M92: 2010 | N92: MAVK
A93: 90 | C93: Milan Express Co. | D93: 189000 | F93: 1500 | G93: 920 | H93: 13 | I93: 2255 | M93: 2010 | N93: MLXP
A94: 91 | B94: 89 | C94: Superior Bulk Logistics | D94: 188278 | E94: 2050 | F94: 1300 | G94: 1185 | H94: 0 | I94: 1954 | M94: 2010 | N94: SUAH
A95: 92 | B95: 98 | C95: A&R Logistics | D95: 185000 | F95: 988 | G95: 705 | H95: 0 | I95: 1774 | K95: 276 | M95: 2010 | N95: ANRI
A96: 93 | B96: 94 | C96: Consolidated Fastfrate | D96: 184023 | F96: 1600 | G96: 590 | H96: 30 | I96: 900 | K96: 500 | M96: 2010 | N96: Consolidated | O96: not found
A97: 94 | C97: Evans Network of Cos | D97: 181000 | F97: 250 | G97: 1770 | H97: 0 | I97: 400 | M97: 2010 | N97: EVTW
A98: 95 | C98: Velocity Express | D98: 180000 | F98: 1200 | G98: 71 | H98: 518 | I98: 1079 | M98: 2010 | N98: VAIC
A99: 96 | C99: U.S. 1 Industries | D99: 179732 | E99: -2586 | F99: 89 | G99: 1700 | H99: 0 | I99: 0 | M99: 2010 | N99: U.S. 1 | O99: not found
A100: 97 | C100: Paschall Truck Lines | D100: 172717 | F100: 1485 | G100: 1105 | H100: 0 | I100: 2895 | M100: 2010 | N100: PASC
...

Sheet For Hire 2009-10
A1: Rank | B1: Rank | C1: Company | D1: Revenue | E1: Net income | F1: Employee | G1: Tractors | H1: Truck &Van | I1: Trailers | J1: aircraft | K1: container | L1: chassis | N1: SCAC_Self
A2: 2010 | B2: 2009 | D2: thousand
A3: Rank | C3: Company | D3: Revenue | E3: NetIncome | F3: NumberEmployees | G3: NumberTractors | H3: NumberTruckVans | I3: NumberTrailers | J3: Aircraft | K3: Container | L3: Chassis | M3: AssetYear | N3: SCAC_Self
A4: 1 | B4: 1 | C4: UPS Inc | D4: 49600000 | E4: 3500000 | F4: 400600 | G4: =12268/(12268+66425)*99800 -> 15558.517 | H4: =66425/(12268+66425)*99800 -> 84241.483 | I4: 21090 | J4: 216 | M4: 2011 | N4: UPSF
A5: 2 | B5: 2 | C5: FedEx Corp | D5: 38180000 | E5: 1125000 | F5: 285000 | G5: 22803 | H5: 52353 | I5: 80281 | J5: 697 | M5: 2011 | N5: FDTB
A6: 3 | B6: 6 | C6: Con-way Inc. | D6: 4952000 | E6: 78200 | F6: 27900 | G6: 11952 | H6: 105 | I6: 34400 | M6: 2011 | N6: CNWY
A7: 4 | B7: 4 | C7: YRC Worldwide | D7: 4334640 | E7: -230600 | F7: 32000 | G7: 16152 | H7: 0 | I7: 52098 | M7: 2011 | N7: RDWY
A8: 5 | B8: 8 | C8: J.B. Hunt Transport Services | D8: 3793485 | E8: 199617 | F8: 15223 | G8: 9543 | H8: 0 | I8: 20803 | K8: 45666 | M8: 2011 | N8: QPMT
A9: 6 | B9: 9 | C9: Schneider National Inc | D9: 3100000 | F9: 18395 | G9: 11634 | H9: 0 | I9: 32608 | K9: 12600 | M9: 2011 | N9: SCNN
A10: 7 | B10: 10 | C10: Swift Transportation | D10: 2929723 | E10: -125413 | F10: 18000 | G10: 16100 | H10: 0 | I10: 48992 | K10: 4800 | M10: 2011 | N10: SWFT
A11: 8 | B11: 11 | C11: Landstar System | D11: 2400170 | E11: 87514 | F11: 1353 | G11: 8452 | H11: 0 | I11: 13084 | M11: 2011 | N11: LRGR
A12: 9 | B12: 7 | C12: Penske Logistics | D12: 2400000 | F12: 9000 | G12: 2115 | H12: 289 | I12: 2969 | M12: 2011 | N12: PSKL
A13: 10 | B13: 14 | C13: TransForce Inc | D13: 1942746 | E13: 101504 | F13: 11600 | G13: 4906 | H13: 1294 | I13: 10684 | L13: 916 | M13: 2011 | N13: TransForce | O13: not found
A14: 11 | B14: 13 | C14: Werner Enterprises | D14: 1815020 | E14: 80039 | F14: 11916 | G14: 7275 | H14: 0 | I14: 23850 | M14: 2011 | N14: WENP
A15: 12 | B15: 5 | C15: Ryder Supply Chain Solutions | D15: 1734834 | F15: 15017 | G15: 3272 | H15: 707 | I15: 5455 | M15: 2011 | N15: Ryder
A16: 13 | B16: 12 | C16: Sirva Inc. | D16: 1731900 | F16: 2300 | G16: 2510 | H16: 1388 | I16: 8002 | M16: 2011 | N16: Sirva
A17: 14 | B17: 16 | C17: Arkansas Best Corp. | D17: 1657864 | E17: -32693 | F17: 10750 | G17: 3821 | H17: 63 | I17: 19285 | M17: 2011 | N17: Arkansas | O17: not found
A18: 15 | B18: 17 | C18: U.S. Xpress Enterprises | D18: 1585283 | F18: 9250 | G18: 8517 | H18: 0 | I18: 22000 | M18: 2011 | N18: USXI
A19: 16 | B19: 15 | C19: UniGroup Inc. | D19: 1520000 | F19: 800 | G19: 6204 | H19: 4650 | I19: 10400 | K19: 6600 | M19: 2011 | N19: AERM
A20: 17 | B20: 18 | C20: Estes Express Lines | D20: 1502510 | F20: 13412 | G20: 6009 | H20: 371 | I20: 22120 | M20: 2011 | N20: EXLA
A21: 18 | B21: 20 | C21: Old Dominion Freight Line | D21: 1480998 | E21: 117 | F21: 12457 | G21: 5718 | H21: 112 | I21: 20986 | L21: 52 | M21: 2011 | N21: ODFL
A22: 19 | B22: 19 | C22: Purolator Inc. | D22: 1448777 | F22: 11300 | G22: 432 | H22: 3273 | I22: 1149 | M22: 2011 | N22: Purolator | O22: not found
A23: 20 | B23: 21 | C23: Greatwide Logistics Services | D23: 1022027 | F23: 3300 | G23: 4089 | H23: 0 | I23: 5200 | M23: 2011 | N23: ATGL
A24: 21 | B24: 22 | C24: C.R. England Inc. | D24: 934669 | E24: 47716 | F24: 6109 | G24: 3747 | H24: 0 | I24: 5444 | K24: 320 | M24: 2011 | N24: ENGI
A25: 22 | B25: 25 | C25: Prime Inc. | D25: 931787 | E25: 93818 | F25: 3565 | G25: 4392 | H25: 0 | I25: 6828 | M25: 2011 | N25: PDSI
A26: 23 | B26: 24 | C26: Saia Inc. | D26: 902660 | E26: 1957 | F26: 7500 | G26: 3525 | H26: 130 | I26: 10900 | M26: 2011 | N26: NFAQ
A27: 24 | B27: 26 | C27: NFI Industries | D27: 90000 | F27: 5600 | G27: 1907 | H27: 235 | I27: 6851 | K27: 49 | M27: 2011 | N27: SAIA
A28: 25 | B28: 23 | C28: Crete Carrier Corp. | D28: 850311 | F28: 5815 | G28: 5260 | H28: 0 | I28: 13400 | M28: 2011 | N28: CRCR
A29: 26 | B29: 32 | C29: CRST International | D29: 838193 | F29: 6490 | G29: 3427 | H29: 0 | I29: 6031 | M29: 2011 | N29: CRFR
A30: 27 | B30: 29 | C30: Southeastern Freight Lines | D30: 826755 | F30: 7360 | G30: 2778 | H30: 23 | I30: 9189 | M30: 2011 | N30: SEFL
A31: 28 | B31: 27 | C31: Averitt Express | D31: 824000 | G31: 3720 | H31: 46 | I31: 12082 | M31: 2011 | N31: AVRT
A32: 29 | B32: 33 | C32: Kenan Advantage Group | D32: 772447 | F32: 6245 | G32: 4038 | H32: 0 | I32: 5382 | M32: 2011 | N32: AVTK
A33: 30 | B33: 28 | C33: Atlas World Group | D33: 759998 | F33: 636 | G33: 2206 | H33: 1612 | I33: 4063 | K33: 5648 | M33: 2011 | N33: ALQK
A34: 31 | B34: 34 | C34: Knight Transportation | D34: 730709 | E34: 59072 | F34: 4526 | G34: 3866 | H34: 0 | I34: 8960 | L34: 48 | M34: 2011 | N34: Knight | O34: subsidiaries found
A35: 32 | B35: 31 | C35: Lynden Inc. | D35: 720000 | F35: 2198 | G35: 693 | H35: 94 | I35: 2773 | K35: 5578 | L35: 1624 | M35: 2011 | N35: LTIA
A36: 33 | B36: 36 | C36: Quality Distribution Inc. | D36: 686598 | E36: -7406 | F36: 752 | G36: 2901 | H36: 0 | I36: 5738 | M36: 2011 | N36: QTKI
A37: 34 | B37: 35 | C37: Vitran Corp. | D37: 672556 | E37: -40182 | F37: 4895 | G37: 2134 | H37: 0 | I37: 6158 | K37: 513 | L37: 451 | M37: 2011 | N37: VITR
A38: 35 | B38: 30 | C38: Ruan Transportation Management Systems | D38: 669905 | F38: 4603 | G38: 3036 | H38: 25 | I38: 7443 | M38: 2011 | N38: RLCF
A39: 36 | B39: 37 | C39: Covenant Transportation group | D39: 649749 | E39: 3289 | F39: 4740 | G39: 3059 | H39: 0 | I39: 7332 | M39: 2011 | N39: CVTH
A40: 37 | C40: Day & Ross Transportation group | D40: 643583 | F40: 4318 | G40: 2154 | H40: 170 | I40: 3858 | M40: 2011 | N40: DAYR
A41: 38 | B41: 47 | C41: Roadrunner Transportation systems | D41: 632018 | E41: 2826 | F41: 1054 | G41: 1330 | H41: 0 | I41: 800 | M41: 2011 | N41: MGAS
A42: 39 | B42: 38 | C42: Anderson Trucking Service | D42: 611521 | F42: 1050 | G42: 1750 | H42: 0 | I42: 5000 | M42: 2011 | N42: ANNN
A43: 40 | B43: 41 | C43: Universal Truckload Services | D43: 605943 | E43: 12744 | F43: 714 | G43: 2997 | H43: 0 | I43: 3400 | L43: 475 | M43: 2011 | N43: UTVE
A44: 41 | B44: 40 | C44: Trimac Group | D44: 579551 | F44: 3725 | G44: 1879 | H44: 0 | I44: 4856 | M44: 2011 | N44: TSUH
A45: 42 | B45: 42 | C45: Celadon Group2 | D45: 541841 | E45: 10372 | F45: 3802 | G45: 3194 | H45: 0 | I45: 9852 | M45: 2011 | N45: CDNK
A46: 43 | B46: 39 | C46: Marten Transport | D46: 516920 | E46: 19742 | F46: 2678 | G46: 2146 | H46: 0 | I46: 3928 | M46: 2011 | N46: MTEN
A47: 44 | B47: 43 | C47: Stevens Transport | D47: 508930 | E47: 67277 | F47: 2475 | G47: 2500 | H47: 0 | I47: 3150 | M47: 2011 | N47: STVV
A48: 45 | B48: 46 | C48: Heartland Express | D48: 499516 | E48: 62216 | F48: 3000 | G48: 3000 | H48: 0 | I48: 8500 | M48: 2011 | N48: NDIJ
A49: 46 | B49: 52 | C49: Forward Air Corp. | D49: 483939 | E49: 32036 | F49: 2717 | G49: =456*1027/(1027 + 177) -> 388.96346 | H49: =456*177/(1027 + 177) -> 67.036545 | I49: 2375 | M49: 2011 | N49: FAFN
A50: 47 | B50: 57 | C50: Canada Cartage System | D50: 470645 | F50: 3500 | G50: 2500 | H50: 430 | I50: 2300 | M50: 2011 | N50: CACG
A51: 48 | B51: 51 | C51: Canada Cartage System | D51: 468868 | F51: 4500 | G51: 1961 | H51: 59 | I51: 6461 | M51: 2011 | N51: CCXP
A52: 49 | C52: United Vision Logistics | D52: 461100 | F52: 381 | G52: 2550 | H52: 0 | I52: 0 | M52: 2011 | N52: DYNS
A53: 50 | B53: 54 | C53: USA Truck | D53: 460161 | E53: -3308 | G53: 2621 | H53: 0 | I53: 6716 | M53: 2011 | N53: USAT
A54: 51 | B54: 44 | C54: Dart Transit Co. | D54: 458000 | F54: 378 | G54: 2481 | H54: 0 | I54: 8252 | K54: 350 | M54: 2011 | N54: ADTS
A55: 52 | B55: 48 | C55: TransX Group | D55: 454148 | F55: 2468 | G55: 1414 | H55: 72 | I55: 4015 | K55: 920 | L55: 458 | M55: 2011 | N55: DKXP
A56: 53 | B56: 50 | C56: Shevell Group | D56: 442000 | F56: 3600 | G56: 2855 | H56: 150 | I56: 5600 | M56: 2011 | N56: Shevell | O56: not found
A57: 54 | B57: 45 | C57: Interstate Distributor Co. | D57: 433174 | F57: 2500 | G57: 1804 | H57: 0 | I57: 7253 | M57: 2011 | N57: IPNS
A58: 55 | B58: 49 | C58: Western Express | D58: 432000 | G58: 2459 | H58: 0 | I58: 6687 | M58: 2011 | N58: WESD
A59: 56 | B59: 59 | C59: Mullen Group1 | D59: 380495 | F59: 1084 | G59: 998 | H59: 118 | I59: 2668 | K59: 636 | M59: 2011 | N59: MULM
A60: 57 | B60: 56 | C60: Frozen Food Express Industries | D60: 368822 | E60: -11930 | F60: 2286 | G60: 1803 | H60: 0 | I60: 3503 | M60: 2011 | N60: FRZF
A61: 58 | B61: 53 | C61: Comcar Industries | D61: 368099 | F61: 3023 | G61: 2713 | H61: 0 | I61: 5354 | M61: 2011 | N61: Comcar | O61: subsidiaries found
A62: 59 | B62: 65 | C62: Mercer Transportation | D62: 363695 | F62: 244 | G62: 1951 | H62: 0 | I62: 2251 | M62: 2011 | N62: MCET
A63: 60 | B63: 58 | C63: Contrans Group | D63: 347918 | E63: 17121 | F63: 943 | G63: 1146 | H63: 0 | I63: 1966 | M63: 2011 | N63: BCFG
A64: 61 | B64: 60 | C64: Central Refrigerated Service | D64: 346472 | F64: 1700 | G64: 1750 | H64: 0 | I64: 2700 | M64: 2011 | N64: CRFS
A65: 62 | B65: 62 | C65: P.A.M. Transportation Services | D65: 331994 | E65: -655 | F65: 2658 | G65: 1768 | H65: 0 | I65: 4632 | M65: 2011 | N65: PAMT
A66: 63 | B66: 63 | C66: Challenger Group1 | D66: 321876 | F66: 2300 | G66: 1505 | H66: 34 | I66: 3563 | K66: 400 | L66: 300 | M66: 2011 | N66: CGFR
A67: 64 | B67: 64 | C67: Gordon Trucking Inc | D67: 320000 | F67: 2000 | G67: 1640 | H67: 0 | I67: 4800 | M67: 2011 | N67: GORK
A68: 65 | B68: 72 | C68: Pitt Ohio | D68: 312454 | E68: 11658 | F68: 2502 | G68: 997 | H68: 385 | I68: 3096 | M68: 2011 | N68: PITD
A69: 66 | B69: 74 | C69: Mesilla Valley Transportation | D69: 298000 | F69: 1500 | G69: 1180 | H69: 0 | I69: 4100 | M69: 2011 | N69: MSLV
A70: 67 | B70: 55 | C70: RoadLink | D70: 297000 | F70: 2100 | G70: 1285 | H70: 0 | I70: 325 | L70: 25 | M70: 2011 | N70: RDLK
A71: 68 | C71: Bison Transport Inc. | D71: 291121 | F71: 1700 | G71: 1050 | H71: 0 | I71: 3000 | K71: 160 | M71: 2011 | N71: BIOS
A72: 69 | B72: 87 | C72: United Road Services | D72: 285000 | F72: 1250 | G72: 1130 | H72: 0 | I72: 910 | M72: 2011 | N72: URDS
A73: 70 | B73: 71 | C73: The Suddath Cos. | D73: 281515 | E73: 14570 | F73: 1350 | G73: 327 | H73: 251 | I73: 551 | K73: 2004 | M73: 2011 | N73: SGLN
A74: 71 | B74: 69 | C74: KLLM Transport Services | D74: 280904 | F74: 880 | G74: 1300 | H74: 0 | I74: 2100 | M74: 2011 | N74: KLMI
A75: 72 | B75: 100 | C75: Jack Cooper Transport Co. | D75: 275000 | F75: 1500 | G75: 1800 | H75: 0 | I75: 1800 | M75: 2011 | N75: COOJ
A76: 73 | B76: 70 | C76: Cardinal Logistics management | D76: 274100 | F76: 2030 | G76: 1458 | H76: 171 | I76: 4824 | M76: 2011 | N76: CHWK
A77: 74 | B77: 77 | C77: Roehl Transport | D77: 272536 | F77: 2185 | G77: 1810 | H77: 4 | I77: 4690 | M77: 2011 | N77: ROEV
A78: 75 | B78: 67 | C78: TransAm Trucking | D78: 269660 | F78: 683 | G78: 1347 | H78: 0 | I78: 2100 | M78: 2011 | N78: TAMI
A79: 76 | B79: 68 | C79: Graebel Cos. | D79: 266000 | E79: -1866 | F79: 1363 | G79: 463 | H79: 400 | I79: 864 | M79: 2011 | N79: Graebel | O79: not found
A80: 77 | B80: 81 | C80: Dayton Freight Lines | D80: 257000 | F80: 2500 | G80: 1065 | H80: 25 | I80: 2300 | M80: 2011 | N80: DAFG
A81: 78 | B81: 80 | C81: Epes Carriers | D81: 247898 | F81: 1206 | G81: 1105 | H81: 0 | I81: 3922 | M81: 2011 | N81: EPES
A82: 79 | B82: 94 | C82: Evans Network of Cos. | D82: 245673 | E82: 6787 | F82: 250 | G82: 1760 | H82: 0 | I82: 500 | M82: 2011 | N82: EVTW
A83: 80 | B83: 84 | C83: A. Duie Pyle Cos. | D83: 234000 | F83: 1956 | G83: 893 | H83: 23 | I83: 1799 | K83: 217 | M83: 2011 | N83: PYLE
A84: 81 | B84: 76 | C84: Calyx Transportation Group | D84: 232128 | F84: 1802 | G84: 357 | H84: 42 | I84: 1917 | M84: 2011 | N84: Calyx | O84: subsidiaries found
A85: 82 | B85: 75 | C85: Specialized Transportation Inc. | D85: 230700 | E85: 9200 | F85: 230 | G85: 580 | H85: 123 | I85: 890 | M85: 2011 | N85: SZXE
A86: 83 | B86: 86 | C86: Cowan Systems | D86: 230321 | F86: 1066 | G86: 1195 | H86: 0 | I86: 2750 | M86: 2011 | N86: CWAS
A87: 84 | C87: Towne Air Freight | D87: 226000 | F87: 1250 | G87: 1001 | H87: 50 | I87: 1400 | M87: 2011 | N87: TOWE
A88: 85 | B88: 88 | C88: Navajo Express | D88: 225000 | G88: 751 | H88: 0 | I88: 1677 | M88: 2011 | N88: NAVE
A89: 86 | B89: 83 | C89: Bennett International Group | D89: 221208 | F89: 574 | G89: 650 | H89: 667 | I89: 1155 | M89: 2011 | N89: BGME
A90: 87 | B90: 97 | C90: Paschall Truck Lines | D90: 200845 | F90: 1474 | G90: 1137 | H90: 0 | I90: 2704 | M90: 2011 | N90: PASC
A91: 88 | B91: 85 | C91: Transport America | D91: 219721 | F91: 1551 | G91: 1150 | H91: 0 | I91: 3650 | M91: 2011 | N91: EXTO
A92: 89 | C92: Acme Truck Lines | D92: 214975 | F92: 2600 | G92: 1037 | H92: 1010 | I92: 1400 | M92: 2011 | N92: ATEQ
A93: 90 | B93: 78 | C93: Koch Companies | D93: 214789 | E93: 4800 | F93: 1000 | G93: 725 | H93: 0 | I93: 2400 | M93: 2011 | N93: KLOG
A94: 91 | B94: 92 | C94: A&R Logistics | D94: 212000 | F94: 960 | G94: 730 | H94: 1 | I94: 1800 | K94: 275 | L94: 50 | M94: 2011 | N94: ANRI
A95: 92 | B95: 82 | C95: Central Freight Lines | D95: 211067 | F95: 2341 | G95: 1092 | H95: 11 | I95: 2700 | M95: 2011 | N95: CFMH
A96: 93 | B96: 96 | C96: U.S. 1 Industries | D96: 210751 | E96: 1773 | F96: 89 | G96: 1700 | H96: 0 | I96: 0 | M96: 2011 | N96: U.S. 1 | O96: not found
A97: 94 | B97: 73 | C97: Super Service Holdings | D97: 209220 | F97: 1560 | G97: 1267 | H97: 0 | I97: 2600 | M97: 2011 | N97: SUSE
A98: 95 | B98: 91 | C98: Superior Bulk Logistics | D98: 207060 | E98: 5566 | F98: 1321 | G98: 1082 | H98: 0 | I98: 1898 | M98: 2011 | N98: SUAH
A99: 96 | B99: 89 | C99: Maverick USA | D99: 200108 | F99: 1377 | G99: 1113 | H99: 0 | I99: 1761 | M99: 2011 | N99: MAVK
A100: 97 | C100: Panther Expedited Services | D100: 196414 | F100: 394 | G100: 316 | H100: 722 | I100: 0 | M100: 2011 | N100: PTWT
...

Sheet For Hire 2011-12
A1: Rank | B1: Rank | C1: Company | D1: Revenue | E1: Net income | F1: Employee | G1: Tractors | H1: Truck &Van | I1: Trailers | J1: aircraft | K1: container | L1: chassis | N1: SCAC_Self
A2: 2012 | B2: 2011 | D2: thousand
A3: Rank | C3: Company | D3: Revenue | E3: NetIncome | F3: NumberEmployees | G3: NumberTractors | H3: NumberTruckVans | I3: NumberTrailers | J3: Aircraft | K3: Container | L3: Chassis | M3: AssetYear | N3: SCAC_Self
A4: 1 | B4: 1 | C4: UPS Inc | D4: 54127000 | E4: 807000 | F4: 399000 | G4: =102851*12268/(12268+66425) -> 16034.159 | H4: =102851*66425/(12268+66425) -> 86816.841 | I4: 83730 | J4: 230 | M4: 2013 | N4: UPSF
A5: 2 | B5: 2 | C5: FedEx Corp | D5: 43898000 | E5: 1808000 | F5: 300000 | G5: 24261 | H5: 57335 | I5: 86707 | J5: 660 | M5: 2013 | N5: FDTB
A6: 3 | B6: 3 | C6: Con-way Inc | D6: 5580247 | E6: 104546 | F6: 29987 | G6: 11800 | H6: 0 | I6: 40000 | M6: 2013 | N6: CNWY
A7: 4 | B7: 5 | C7: J.B. Hunt Transport Services | D7: 5054980 | E7: 310354 | F7: 16475 | G7: 9686 | H7: 684 | I7: 22699 | J7: 0 | K7: 58745 | L7: 55409 | M7: 2013 | N7: QPMT
A8: 5 | B8: 4 | C8: YRC Worldwide | D8: 4850500 | E8: -136500 | F8: 32000 | G8: 14572 | H8: 0 | I8: 47694 | M8: 2013 | N8: RDWY
A9: 6 | B9: 6 | C9: Schneider National Inc | D9: 3500000 | F9: 16700 | G9: 11540 | H9: 23 | I9: 29800 | J9: 0 | K9: 14300 | M9: 2013 | N9: SCNN
A10: 7 | B10: 7 | C10: Swift Transportation | D10: 3493182 | E10: 114589 | F10: 16671 | G10: 15231 | M10: 2013 | N10: SWFT
A11: 8 | B11: 8 | C11: TransForce Inc. | D11: 3141513 | E11: 154238 | F11: 14240 | G11: 11380 | H11: 0 | I11: 11700 | M11: 2013 | N11: TransForce | O11: not found
A12: 9 | B12: 9 | C12: Landstar System | D12: 2793420 | E12: 129781 | F12: 1369 | G12: 8265 | H12: 258 | I12: 12967 | M12: 2013 | N12: LRGR
A13: 10 | B13: 10 | C13: Ryder Supply Chain Solutions | D13: 2280586 | E13: 1945 | F13: 13711 | G13: 3729 | H13: 692 | I13: 6282 | M13: 2013 | N13: Ryder
A14: 11 | B14: 14 | C14: Old Dominion Freight Line | D14: 2110483 | E14: 169452 | F14: 14334 | G14: 6099 | H14: 106 | I14: 24181 | L14: 68 | M14: 2013 | N14: ODFL
A15: 12 | B15: 13 | C15: Arkansas Best Corp. | D15: 2065999 | E15: -7732 | F15: 11250 | G15: 3835 | H15: 65 | I15: 20079 | M15: 2013 | N15: Arkansas | O15: not found
A16: 13 | B16: 11 | C16: Werner Enterprises | D16: 2036386 | E16: 103034 | F16: 10736 | G16: 6505 | H16: 645 | I16: 23380 | M16: 2013 | N16: WENP
A17: 14 | B17: 12 | C17: Sirva Inc. | D17: 1973000 | G17: 2465 | H17: 1454 | I17: 4074 | M17: 2013 | N17: Sirva | O17: not found
A18: 15 | B18: 15 | C18: Estes Express Lines | D18: 1857598 | F18: 13849 | G18: 6536 | H18: 523 | I18: 24135 | M18: 2013 | N18: EXLA
A19: 16 | B19: 16 | C19: U.S. Xpress Enterprises | D19: 1756464 | F19: 11983 | G19: 7550 | H19: 0 | I19: 21000 | M19: 2013 | N19: USXI
A20: 17 | B20: 17 | C20: Purolator Inc. | D20: 1632291 | F20: 12000 | G20: 487 | H20: 3256 | I20: 1296 | J20: 23 | M20: 2013 | N20: Purolator | O20: not found
A21: 18 | B21: 18 | C21: UniGroup Inc. | D21: 1613124 | F21: 980 | G21: 6260 | H21: 4415 | I21: 9950 | K21: 14300 | M21: 2013 | N21: AERM
A22: 19 | B22: 20 | C22: C.R. England Inc. | D22: 1416806 | F22: 6759 | G22: 5238 | H22: 0 | I22: 7259 | K22: 700 | M22: 2013 | N22: ENGI
A23: 20 | B23: 19 | C23: CRST International | D23: 1257995 | F23: 5128 | G23: 4511 | H23: 0 | I23: 7570 | M23: 2013 | N23: CRFR
A24: 21 | B24: 23 | C24: Prime Inc. | D24: 1152569 | E24: 147281 | F24: 4450 | G24: 4985 | H24: 0 | I24: 8781 | M24: 2013 | N24: PDSI
A25: 22 | B25: 22 | C25: Saia Inc. | D25: 1100000 | F25: 8000 | G25: 3662 | H25: 80 | I25: 10407 | M25: 2013 | N25: SAIA
A26: 23 | B26: 26 | C26: Kenan Advantage Group | D26: 1091031 | F26: 6873 | G26: 4767 | H26: 0 | I26: 6229 | M26: 2013 | N26: AVTK
A27: 24 | B27: 32 | C27: Roadrunner Transportation Systems | D27: 1073354 | E27: 37530 | F27: 2491 | G27: 3222 | H27: 0 | I27: 2609 | M27: 2013 | N27: MGAS
A28: 25 | B28: 24 | C28: NFI Industries | D28: 1041230 | F28: 6000 | G28: 2155 | H28: 0 | I28: 7000 | K28: 120 | M28: 2013 | N28: NFAQ
A29: 26 | B29: 39 | C29: Universal Truckload Services Inc | D29: 1037006 | E29: 47688 | F29: 4809 | G29: 4125 | H29: 0 | I29: 6308 | K29: 800 | L29: 844 | M29: 2013 | N29: UTVE
A30: 27 | B30: 27 | C30: Southeastern Freight Lines | D30: 1012908 | F30: 7852 | G30: 3291 | H30: 23 | I30: 9820 | M30: 2013 | N30: SEFL
A31: 28 | B31: 28 | C31: Crete Carrier Corp | D31: 998727 | F31: 5627 | G31: 5500 | H31: 0 | I31: 13494 | M31: 2013 | N31: CRCR
A32: 29 | B32: 29 | C32: Averitt Express | D32: 961560 | G32: 3939 | H32: 43 | I32: 11606 | M32: 2013 | N32: AVRT
A33: 30 | B33: 25 | C33: Penske Logistics | D33: 951000 | F33: 8151 | G33: 1615 | H33: 219 | I33: 2883 | M33: 2013 | N33: PSKL
A34: 31 | B34: 30 | C34: Knight Transportation | D34: 936036 | E34: 64117 | F34: 4600 | G34: 4134 | H34: 0 | I34: 9564 | M34: 2013 | N34: Knight | O34: not found
A35: 32 | B35: 36 | C35: Anderson Trucking Service | D35: 927406 | F35: 1250 | G35: 2209 | H35: 0 | I35: 5400 | M35: 2013 | N35: ANNN
A36: 33 | B36: 31 | C36: Lynden Inc. | D36: 885000 | F36: 2391 | G36: 689 | H36: 55 | I36: 1190 | K36: 5926 | L36: 1644 | M36: 2013 | N36: LTIA
A37: 34 | C37: Cardinal Logistics Management Corp. | D37: 850000 | F37: 5100 | G37: 4066 | H37: 201 | I37: 9930 | M37: 2013 | N37: CHWK
A38: 35 | B38: 38 | C38: Quality Distribution Inc | D38: 842118 | E38: 50076 | F38: 1371 | G38: 2775 | H38: 0 | I38: 6514 | M38: 2013 | N38: QTKI
A39: 36 | B39: 35 | C39: Day & Ross Transportation1 Group | D39: 830642 | F39: 2138 | G39: 1630 | H39: 486 | I39: 3944 | M39: 2013 | N39: DAYR
A40: 37 | B40: 33 | C40: Atlas World Group | D40: 815518 | E40: 5910 | F40: 405 | G40: 2178 | H40: 1562 | I40: 3391 | M40: 2013 | N40: ALQK
A41: 38 | B41: 37 | C41: Ruan Transportation Management Systems | D41: 774892 | F41: 5139 | G41: 3319 | H41: 35 | I41: 5858 | M41: 2013 | N41: RLCF
A42: 39 | B42: 42 | C42: Trimac Group | D42: 722288 | F42: 3750 | G42: 2132 | H42: 0 | I42: 4871 | M42: 2013 | N42: TSUH
A43: 40 | B43: 34 | C43: Vitran Corp | D43: 702914 | E43: -35975 | F43: 6366 | G43: 2603 | H43: 243 | I43: 7221 | K43: 512 | L43: 448 | M43: 2013 | N43: VITR
A44: 41 | B44: 40 | C44: Covenant Transportation | D44: 674254 | E44: 6065 | F44: 5124 | G44: 2884 | H44: 0 | I44: 6904 | M44: 2013 | N44: CVTH
A45: 42 | B45: 41 | C45: Marten Transport | D45: 638456 | E45: 27267 | F45: 2946 | G45: 2252 | H45: 0 | I45: 4170 | K45: 200 | M45: 2013 | N45: MTEN
A46: 43 | B46: 43 | C46: Stevens Transport | D46: 612365 | E46: 85270 | F46: 2725 | G46: 2610 | H46: 0 | I46: 3485 | M46: 2013 | N46: STVV
A47: 44 | B47: 44 | C47: Celadon Group1 | D47: 612202 | E47: 30265 | F47: 4100 | G47: 3801 | H47: 48 | I47: 8782 | M47: 2013 | N47: CDNK
A48: 45 | B48: 46 | C48: Forward Air Corp. | D48: 584446 | E48: 52668 | F48: 3169 | G48: 3801 | H48: 166 | I48: 2746 | L48: 50 | M48: 2013 | N48: FAFN
A49: 46 | B49: 48 | C49: AAA Cooper Transportation | D49: 553408 | F49: 4500 | G49: 1342 | H49: 65 | I49: 6000 | M49: 2013 | N49: AACT
A50: 47 | B50: 47 | C50: Heartland Express | D50: 545745 | E50: 61541 | F50: 2993 | G50: 2826 | H50: 0 | I50: 7800 | M50: 2013 | N50: NDIJ
A51: 48 | B51: 45 | C51: Canada catage system | D51: 543820 | F51: 3700 | G51: 2188 | H51: 350 | I51: 2165 | M51: 2013 | N51: CACG
A52: 49 | B52: 51 | C52: Mullen Group | D52: 535814 | F52: 1685 | G52: 1131 | H52: 339 | I52: 3008 | K52: 527 | M52: 2013 | N52: MULM
A53: 50 | B53: 50 | C53: TransX Group | D53: 534214 | F53: 2560 | K53: 900 | L53: 450 | M53: 2013 | N53: DKXP
A54: 51 | B54: 63 | C54: Contrans Group | D54: 522429 | E54: 28298 | G54: 1520 | H54: 0 | I54: 4200 | M54: 2013 | N54: BCFG
A55: 52 | B55: 49 | C55: USA Truck | D55: 512428 | E55: -17671 | F55: 2990 | G55: 2246 | H55: 0 | I55: 6091 | M55: 2013 | N55: USAT
A56: 53 | B56: 55 | C56: Jack Cooper Transport Co. | D56: 500000 | F56: 2500 | G56: 2030 | H56: 0 | I56: 0 | M56: 2013 | N56: COOJ
A57: 54 | B57: 54 | C57: Mercer Transportation | D57: 492297 | F57: 298 | G57: 2191 | H57: 0 | I57: 0 | M57: 2013 | N57: MCET
A58: 55 | B58: 53 | C58: Dart Transit Co. | D58: 457000 | F58: 348 | G58: 2087 | H58: 0 | I58: 7126 | K58: 340 | M58: 2013 | N58: ADTS
A59: 56 | B59: 58 | C59: Central Refrigerated Service | D59: 452805 | F59: 1687 | G59: 1915 | H59: 0 | I59: 3100 | M59: 2013 | N59: CRFS
A60: 57 | B60: 56 | C60: Shevell Group | D60: 446000 | F60: 3400 | G60: 2155 | H60: 120 | I60: 4700 | M60: 2013 | N60: Shevell | O60: not found
A61: 58 | B61: 21 | C61: Greatwide Logistics Services | D61: 444737 | M61: 2013 | N61: ATGL
A62: 59 | B62: 57 | C62: Western Express | D62: 433018 | F62: 2500 | G62: 2390 | H62: 0 | I62: 5000 | M62: 2013 | N62: WESD
A63: 60 | B63: 64 | C63: The Suddath Cos | D63: 429324 | F63: 1900 | G63: 336 | H63: 205 | I63: 558 | K63: 1400 | M63: 2013 | N63: SGLN
A64: 61 | B64: 62 | C64: Gordon Trucking Inc | D64: 426000 | F64: 2500 | G64: 1925 | H64: 0 | I64: 6700 | M64: 2013 | N64: GORK
A65: 62 | C65: Groupe Robert | D65: 420168 | F65: 3300 | G65: 1100 | H65: 0 | I65: 2142 | K65: 440 | M65: 2013 | N65: BUTN
A66: 63 | B66: 65 | C66: Bison Transport | D66: 391156 | F66: 2395 | G66: 1310 | H66: 15 | I66: 3454 | K66: 124 | L66: 51 | M66: 2013 | N66: BIOS
A67: 64 | B67: 68 | C67: Pitt Ohio | D67: 388200 | F67: 2713 | G67: 10041 | H67: 449 | I67: 3015 | M67: 2013 | N67: PITD
A68: 65 | B68: 67 | C68: P.A.M. Transportation services | D68: 380633 | E68: 2179 | F68: 3031 | G68: 1800 | H68: 0 | I68: 4943 | M68: 2013 | N68: PAMT
A69: 66 | B69: 61 | C69: Frozen Food Express industries | D69: 377715 | E69: -15056 | F69: 2183 | G69: 1807 | H69: 0 | I69: 3252 | M69: 2013 | N69: FRZF
A70: 67 | B70: 72 | C70: Mesilla Valley Transportation | D70: 376800 | F70: 1700 | G70: 1235 | H70: 0 | I70: 4600 | M70: 2013 | N70: MSLV
A71: 68 | B71: 71 | C71: Roehl Transport | D71: 374620 | F71: 2506 | G71: 1980 | H71: 5 | I71: 5004 | M71: 2013 | N71: ROEV
A72: 69 | B72: 79 | C72: Comtrak Logistics | D72: 373827 | F72: 658 | G72: 2541 | H72: 0 | I72: 450 | L72: 82 | M72: 2013 | N72: CMKI
A73: 70 | B73: 59 | C73: Comcar Industries | D73: 3737239 | F73: 3004 | G73: 2305 | H73: 0 | I73: 4784 | M73: 2013 | N73: Comcar | O73: not found
A74: 71 | B74: 74 | C74: Acme Truck Line Inc. | D74: 372739 | F74: 3150 | G74: 1322 | H74: 386 | I74: 0 | M74: 2013 | N74: ATEQ
A75: 72 | B75: 60 | C75: Transport America | D75: 363546 | F75: 2270 | G75: 1680 | H75: 30 | I75: 4570 | L75: 125 | M75: 2013 | N75: EXTO
A76: 73 | B76: 76 | C76: Dayton Freight Lines | D76: 363400 | F76: 2906 | G76: 1167 | H76: 39 | I76: 2750 | M76: 2013 | N76: DAFG
A77: 74 | B77: 69 | C77: KLLM Transport Services | D77: 363000 | G77: 1685 | H77: 0 | I77: 2213 | M77: 2013 | N77: KLMI
A78: 75 | B78: 75 | C78: Graebel Cos. | D78: 341856 | E78: 4462 | F78: 2377 | G78: 618 | H78: 340 | I78: 972 | M78: 2013 | N78: Graebel | O78: not found
A79: 76 | B79: 73 | C79: Challenger Group1 | D79: 340351 | F79: 2300 | G79: 1505 | H79: 0 | I79: 3613 | L79: 300 | M79: 2013 | N79: CGFR
A80: 77 | B80: 66 | C80: Interstate Distributor Co | D80: 338500 | F80: 1800 | G80: 1605 | H80: 0 | I80: 5450 | M80: 2013 | N80: IPNS
A81: 78 | B81: 77 | C81: United Road Services | D81: 325000 | F81: 1100 | G81: 1100 | H81: 0 | I81: 900 | M81: 2013 | N81: URDS
A82: 79 | B82: 78 | C82: TransAm Trucking | D82: 321000 | F82: 669 | G82: 1347 | H82: 0 | I82: 2100 | M82: 2013 | N82: TAMI
A83: 80 | B83: 80 | C83: Cowan Systems | D83: 315325 | F83: 1362 | G83: 1455 | H83: 0 | I83: 3724 | M83: 2013 | N83: CWAS
A84: 81 | C84: California Cartage Co. | D84: 311000 | G84: 1000 | H84: 0 | I84: 0 | K84: 125 | L84: 125 | M84: 2013 | N84: CCXP
A85: 82 | B85: 81 | C85: Epes Carriers | D85: 302593 | E85: 18404 | F85: 1424 | G85: 1116 | H85: 27 | I85: 4422 | M85: 2013 | N85: EPES
A86: 83 | B86: 87 | C86: OnTrac Inc. | D86: 286911 | E86: 4846 | F86: 1656 | G86: 0 | H86: 0 | I86: 250 | M86: 2013 | N86: EMSY
A87: 84 | B87: 88 | C87: Maverick USA | D87: 286851 | F87: 1782 | G87: 1432 | H87: 0 | I87: 1665 | M87: 2013 | N87: MAVK
A88: 85 | B88: 82 | C88: A. Duie Pyle Cos. | D88: 286000 | F88: 2149 | G88: 740 | H88: 23 | I88: 2050 | M88: 2013 | N88: PYLE
A89: 86 | B89: 89 | C89: Cassens Transport | D89: 283775 | F89: 1280 | G89: 615 | I89: 615 | M89: 2013 | N89: CASF
A90: 87 | B90: 83 | C90: Evans Network of Cos | D90: 275000 | F90: 260 | G90: 1850 | H90: 0 | I90: 525 | M90: 2013 | N90: EVTW
A91: 88 | B91: 85 | C91: Bennett International Group | D91: 266349 | F91: 643 | G91: 680 | H91: 560 | I91: 1152 | M91: 2013 | N91: BGME
A92: 89 | C92: John Christner Trucking LLC | D92: 264774 | E92: 13328 | F92: 967 | G92: 817 | H92: 0 | I92: 1098 | M92: 2013 | N92: CJHT
A93: 90 | C93: Fastfrate Holdings | D93: 263079 | F93: 1600 | G93: 636 | H93: 24 | I93: 1668 | L93: 366 | M93: 2013 | N93: Consolidated | O93: not found
A94: 91 | B94: 90 | C94: Koch Companies | D94: 262000 | E94: 7500 | F94: 925 | G94: 725 | H94: 0 | I94: 2100 | M94: 2013 | N94: KLOG
A95: 92 | B95: 86 | C95: Towne Air Freight | D95: 258825 | G95: 1150 | H95: 0 | I95: 0 | M95: 2013 | N95: TOWE
A96: 93 | B96: 84 | C96: Wheaton Van Lines | D96: 250000 | F96: 150 | G96: 661 | H96: 496 | I96: 779 | M96: 2013 | N96: WHTN
A97: 94 | B97: 92 | C97: The Waggoners Trucking | D97: 247031 | F97: 1087 | G97: 809 | H97: 0 | I97: 900 | M97: 2013 | N97: WAGP
A98: 95 | B98: 98 | C98: A&R Logistics | D98: 235000 | F98: 1100 | G98: 825 | H98: 0 | I98: 0 | K98: 750 | L98: 100 | M98: 2013 | N98: ANRI
A99: 96 | B99: 93 | C99: Superior Bulk Logistics | D99: 234700 | F99: 1359 | G99: 1078 | H99: 0 | I99: 1967 | M99: 2013 | N99: SUAH
A100: 97 | B100: 95 | C100: Groendyke Transport Inc. | D100: 228855 | F100: 1382 | G100: 1048 | H100: 0 | I100: 1723 | M100: 2013 | N100: Groendyke | O100: not found
...

Sheet For Hire 2010-11
A1: Rank | B1: Rank | C1: Company | D1: Revenue | E1: Net income | F1: Employee | G1: Tractors | H1: Truck &Van | I1: Trailers | J1: aircraft | K1: container | L1: chassis | N1: SCAC_Self
A2: 2011 | B2: 2010 | D2: thousand
A3: Rank | C3: Company | D3: Revenue | E3: NetIncome | F3: NumberEmployees | G3: NumberTractors | H3: NumberTruckVans | I3: NumberTrailers | J3: Aircraft | K3: Container | L3: Chassis | M3: AssetYear | N3: SCAC_Self
A4: 1 | B4: 1 | C4: UPS Inc | D4: 53105000 | E4: 3804000 | F4: 398300 | G4: =101121*12268/(12268+66425) -> 15764.457 | H4: =101121*66425/(12268+66425) -> 85356.543 | I4: 78974 | J4: 230 | M4: 2012 | N4: UPSF
A5: 2 | B5: 2 | C5: FedEx Corp | D5: 42224000 | E5: 1369000 | F5: 300000 | G5: 23692 | H5: 53839 | I5: 84817 | J5: 688 | M5: 2012 | N5: FDTB
A6: 3 | B6: 3 | C6: Con-way Inc | D6: 5289953 | E6: 88443 | F6: 27800 | G6: 11900 | H6: 0 | I6: 34400 | M6: 2012 | N6: CNWY
A7: 4 | B7: 4 | C7: YRC Worldwide | D7: 4868844 | E7: -354517 | F7: 32000 | G7: 15602 | H7: 0 | I7: 51636 | M7: 2012 | N7: RDWY
A8: 5 | B8: 5 | C8: J.B. Hunt Transport Services | D8: 4527000 | E8: 257006 | F8: 15631 | G8: 10287 | H8: 0 | I8: 54506 | K8: 54506 | M8: 2012 | N8: QPMT
A9: 6 | B9: 6 | C9: Schneider National Inc | D9: 3400000 | F9: 17400 | G9: 11700 | H9: 80 | I9: 32000 | K9: 13600 | M9: 2012 | N9: SCNN
A10: 7 | B10: 7 | C10: Swift Transportation | D10: 3333908 | E10: 90550 | F10: 17400 | G10: 15902 | H10: 0 | I10: 50555 | K10: 6210 | M10: 2012 | N10: SWFT
A11: 8 | B11: 10 | C11: TransForce Inc. | D11: 2719907 | E11: 103336 | F11: 14680 | G11: 4906 | H11: 1294 | I11: 10684 | L11: 916 | M11: 2012 | N11: TransForce | O11: not found
A12: 9 | B12: 8 | C12: Landstar System | D12: 2649082 | E12: 113007 | F12: 1351 | G12: 8121 | H12: 250 | I12: 13320 | M12: 2012 | N12: LRGR
A13: 10 | B13: 12 | C13: Ryder Supply Chain Solutions | D13: 2211000 | F13: 12387 | G13: 3503 | H13: 918 | I13: 5526 | M13: 2012 | N13: Ryder | O13: subsidiaries found
A14: 11 | B14: 11 | C14: Werner Enterprises | D14: 2002850 | E14: 103757 | F14: 11033 | G14: 7280 | H14: 0 | I14: 23045 | M14: 2012 | N14: WENP
A15: 12 | B15: 13 | C15: Sirva Inc. | D15: 1957000 | F15: 2700 | G15: 2435 | H15: 1429 | I15: 4104 | M15: 2012 | N15: Sirva | O15: not found
A16: 13 | B16: 14 | C16: Arkansas Best Corp. | D16: 1907609 | E16: 6159 | F16: 10800 | G16: 3989 | H16: 67 | I16: 20209 | M16: 2012 | N16: Arkansas | O16: not found
A17: 14 | B17: 18 | C17: Old Dominion Freight Line | D17: 1882541 | E17: 139470 | F17: 13696 | G17: 5830 | H17: 109 | I17: 22695 | L17: 69 | M17: 2012 | N17: ODFL
A18: 15 | B18: 17 | C18: Estes Express Lines | D18: 170000 | F18: 13605 | G18: 6131 | H18: 433 | I18: 22760 | M18: 2012 | N18: EXLA
A19: 16 | B19: 15 | C19: U.S. Xpress Enterprises | D19: 1695548 | F19: 9666 | G19: 7500 | H19: 150 | I19: 21000 | M19: 2012 | N19: USXI
A20: 17 | B20: 19 | C20: Purolator Inc. | D20: 1633241 | F20: 12000 | G20: 432 | H20: 3342 | I20: 1150 | J20: 22 | M20: 2012 | N20: Purolator | O20: not found
A21: 18 | B21: 16 | C21: UniGroup Inc. | D21: 1580000 | F21: 900 | G21: 5904 | H21: 4810 | I21: 10100 | K21: 8000 | M21: 2012 | N21: AERM
A22: 19 | B22: 26 | C22: CRST International | D22: 1277348 | F22: 5200 | G22: 4413 | H22: 0 | I22: 7569 | M22: 2012 | N22: CRFR
A23: 20 | B23: 21 | C23: C.R. England Inc. | D23: 1079716 | E23: 73038 | F23: 4005 | G23: 4331 | H23: 0 | I23: 6854 | K23: 301 | M23: 2012 | N23: ENGI
A24: 21 | B24: 20 | C24: Greatwide Logistics Services | D24: 1045957 | F24: 3500 | G24: 4252 | H24: 0 | I24: 5355 | M24: 2012 | N24: ATGL
A25: 22 | B25: 23 | C25: Saia Inc. | D25: 1030224 | E25: 11373 | F25: 7900 | G25: 4125 | H25: 130 | I25: 11000 | M25: 2012 | N25: SAIA
A26: 23 | B26: 22 | C26: Prime Inc. | D26: 1017482 | E26: 128399 | F26: 3629 | G26: 4886 | H26: 0 | I26: 7262 | M26: 2012 | N26: PDSI
A27: 24 | B27: 24 | C27: NFI Industries | D27: 1010000 | F27: 6000 | G27: 2044 | H27: 30 | I27: 6840 | K27: 70 | M27: 2012 | N27: NFAQ
A28: 25 | B28: 9 | C28: Penske Logistics | D28: 990000 | F28: 8000 | G28: 2180 | H28: 330 | I28: 2878 | M28: 2012 | N28: PSKL
A29: 26 | B29: 29 | C29: Kenan Advantage Group | D29: 987800 | F29: 6560 | G29: 4380 | H29: 0 | I29: 5771 | M29: 2012 | N29: AVTK
A30: 27 | B30: 27 | C30: Southeastern Freight Lines | D30: 942912 | F30: 7552 | G30: 3368 | H30: 23 | I30: 11496 | M30: 2012 | N30: SEFL
A31: 28 | B31: 25 | C31: Crete Carrier Corp. | D31: 942000 | F31: 5933 | G31: 5266 | H31: 0 | I31: 13330 | M31: 2012 | N31: CRCR
A32: 29 | B32: 28 | C32: Averitt Express | D32: 922000 | G32: 3753 | H32: 44 | I32: 11955 | M32: 2012 | N32: AVRT
A33: 30 | B33: 31 | C33: Knight Transportation | D33: 866199 | E33: 60248 | F33: 4854 | G33: 3976 | H33: 0 | I33: 8986 | L33: 66 | M33: 2012 | N33: Knight | O33: subsidiaries found
A34: 31 | B34: 32 | C34: Lynden Inc. | D34: 850000 | F34: 2298 | G34: 729 | H34: 113 | I34: 2931 | K34: 5704 | L34: 1643 | M34: 2012 | N34: LTIA
A35: 32 | B35: 38 | C35: Roadrunner Transportation Systems | D35: 843627 | E35: 25871 | F35: 1848 | G35: 2320 | H35: 0 | I35: 1225 | M35: 2012 | N35: MGAS
A36: 33 | B36: 30 | C36: Atlas World Group | D36: 808935 | E36: 3532 | F36: 642 | G36: 2153 | H36: 1576 | I36: 4014 | K36: 5648 | M36: 2012 | N36: ALQK
A37: 34 | B37: 34 | C37: Vitran Corp. | D37: 805598 | E37: -14013 | F37: 6282 | G37: 2664 | H37: 194 | I37: 7386 | K37: 517 | L37: 448 | M37: 2012 | N37: VITR
A38: 35 | B38: 37 | C38: Day & Ross Transportation Group1 | D38: 785022 | F38: 4292 | G38: 2124 | H38: 145 | I38: 4026 | M38: 2012 | N38: DAYR
A39: 36 | B39: 39 | C39: Anderson Trucking Service | D39: 762143 | F39: 1150 | G39: 2054 | H39: 0 | I39: 5300 | M39: 2012 | N39: ANNN
A40: 37 | B40: 35 | C40: Ruan Transportation Management Systems | D40: 750915 | F40: 5155 | G40: 3334 | H40: 45 | I40: 5667 | M40: 2012 | N40: RLCF
A41: 38 | B41: 33 | C41: Quality Distribution Inc | D41: 745951 | E41: 23431 | F41: 851 | G41: 2940 | H41: 0 | I41: 5493 | M41: 2012 | N41: QTKI
A42: 39 | B42: 40 | C42: Universal Truckload Services Inc | D42: 699771 | E42: 15813 | F42: 675 | G42: 3240 | H42: 0 | I42: 0 | M42: 2012 | N42: UTVE
A43: 40 | B43: 36 | C43: Covenant Transportation Group | D43: 652627 | E43: -14267 | F43: 4807 | G43: 3194 | H43: 0 | I43: 7361 | M43: 2012 | N43: CVTH
A44: 41 | B44: 43 | C44: Marten Transport | D44: 603679 | E44: 24285 | F44: 2787 | G44: 2281 | H44: 0 | I44: 4124 | K44: 200 | M44: 2012 | N44: MTEN
A45: 42 | B45: 41 | C45: Trimac Group | D45: 589000 | F45: 3725 | G45: 1879 | H45: 0 | I45: 4856 | M45: 2012 | N45: TSUH
A46: 43 | B46: 44 | C46: Stevens Transport | D46: 569901 | E46: 76996 | F46: 2650 | G46: 2600 | H46: 0 | I46: 3310 | M46: 2012 | N46: STVV
A47: 44 | B47: 42 | C47: Celadon Group1 | D47: 556695 | E47: 14731 | F47: 3478 | G47: 2785 | H47: 0 | I47: 8206 | M47: 2012 | N47: CDNK
A48: 45 | B48: 47 | C48: Canada Cartage System | D48: 539830 | F48: 3600 | G48: 1940 | H48: 415 | I48: 2300 | L48: 35 | M48: 2012 | N48: CACG
A49: 46 | B49: 46 | C49: Forward Air Corp | D49: 536402 | E49: 47199 | F49: 3161 | G49: 1027 | H49: 177 | I49: 2536 | M49: 2012 | N49: FAFN
A50: 47 | B50: 45 | C50: Heartland Express | D50: 528623 | E50: 69932 | F50: 2862 | G50: 2886 | H50: 0 | I50: 7800 | M50: 2012 | N50: NDIJ
A51: 48 | B51: 48 | C51: AAA Cooper Transportation | D51: 522000 | F51: 4350 | G51: 5115 | H51: 80 | I51: 6526 | M51: 2012 | N51: AACT
A52: 49 | B52: 50 | C52: USA Truck | D52: 519408 | E52: -10777 | F52: 3020 | G52: 2394 | H52: 0 | I52: 6318 | M52: 2012 | N52: USAT
A53: 50 | B53: 52 | C53: TransX Group | D53: 507481 | F53: 2510 | G53: 1510 | H53: 0 | I53: 4100 | K53: 925 | L53: 450 | M53: 2012 | N53: DKXP
A54: 51 | B54: 56 | C54: Mullen Group | D54: 494646 | F54: 1084 | G54: 998 | H54: 118 | I54: 2668 | K54: 636 | M54: 2012 | N54: MULM
A55: 52 | B55: 49 | C55: United Vision Logistics | D55: 494000 | F55: 361 | G55: 2238 | H55: 0 | I55: 0 | M55: 2012 | N55: DYNS
A56: 53 | B56: 51 | C56: Dart Transit Co | D56: 480000 | F56: 320 | G56: 2225 | H56: 0 | I56: 7950 | K56: 350 | M56: 2012 | N56: ADTS
A57: 54 | B57: 59 | C57: Mercer Transportation | D57: 476633 | F57: 281 | G57: 1037 | I57: 1036 | M57: 2012 | N57: MCET
A58: 55 | B58: 72 | C58: Jack Cooper Transport Co | D58: 450000 | F58: 2000 | G58: 1800 | H58: 0 | I58: 1800 | M58: 2012 | N58: COOJ
A59: 56 | B59: 53 | C59: Shevell Group | D59: 441000 | F59: 3310 | G59: 3470 | H59: 145 | I59: 5250 | M59: 2012 | N59: Shevell | O59: not found
A60: 57 | B60: 55 | C60: Western Express | D60: 433000 | F60: 300 | G60: 2300 | H60: 0 | I60: 5800 | M60: 2012 | N60: WESD
A61: 58 | B61: 61 | C61: Central Refrigerated Service | D61: 419138 | F61: 1650 | G61: 1800 | H61: 0 | I61: 3000 | M61: 2012 | N61: CRFS
A62: 59 | B62: 58 | C62: Comcar Industries | D62: 392687 | F62: 3002 | G62: 2713 | H62: 0 | I62: 5354 | M62: 2012 | N62: Comcar | O62: subsidiaries found
A63: 60 | B63: 88 | C63: Transport America | D63: 392000 | F63: 2520 | G63: 1880 | H63: 0 | I63: 5050 | L63: 125 | M63: 2012 | N63: EXTO
A64: 61 | B64: 57 | C64: Frozen Food Express Industries | D64: 388461 | E64: -36670 | F64: 2125 | G64: 1656 | H64: 0 | I64: 3388 | M64: 2012 | N64: FRZF
A65: 62 | B65: 64 | C65: Gordon Trucking Inc | D65: 383000 | F65: 2400 | G65: 1900 | H65: 0 | I65: 6100 | M65: 2012 | N65: GORK
A66: 63 | B66: 60 | C66: Contrans Group | D66: 382143 | E66: 20709 | F66: 943 | G66: 1146 | H66: 0 | I66: 1966 | M66: 2012 | N66: BCFG
A67: 64 | B67: 70 | C67: The Suddath Cos | D67: 380000 | F67: 1700 | G67: 304 | H67: 283 | I67: 579 | K67: 1500 | M67: 2012 | N67: SGLN
A68: 65 | B68: 68 | C68: Bison Transport Inc | D68: 375253 | F68: 1850 | G68: 1101 | H68: 10 | I68: 3128 | K68: 200 | L68: 51 | M68: 2012 | N68: BIOS
A69: 66 | B69: 54 | C69: Interstate Distributor Co. | D69: 372000 | F69: 2030 | G69: 1655 | H69: 0 | I69: 6200 | M69: 2012 | N69: IPNS
A70: 67 | B70: 62 | C70: P.A.M. Transportation Services | D70: 359243 | E70: -2857 | F70: 2764 | G70: 1868 | H70: 0 | I70: 4785 | M70: 2012 | N70: PAMT
A71: 68 | B71: 65 | C71: Pitt Ohio | D71: 358384 | F71: 2586 | G71: 926 | H71: 360 | I71: 2835 | M71: 2012 | N71: PITD
A72: 69 | B72: 71 | C72: KLLM Transport Services | D72: 351000 | F72: 710 | G72: 1400 | H72: 150 | I72: 2200 | M72: 2012 | N72: KLMI
A73: 70 | C73: Allied Systems Holdings | D73: 3434000 | M73: 2012 | N73: Allied Systems | O73: not found
A74: 71 | B74: 74 | C74: Roehl Transport | D74: 339388 | F74: 2345 | G74: 1943 | H74: 4 | I74: 4875 | M74: 2012 | N74: ROEV
A75: 72 | B75: 66 | C75: Mesilla Valley Transportation | D75: 335000 | F75: 1500 | G75: 1200 | H75: 0 | I75: 4400 | M75: 2012 | N75: MSLV
A76: 73 | B76: 63 | C76: Challenger Group | D76: 334503 | F76: 2300 | G76: 1505 | H76: 0 | I76: 3613 | L76: 300 | M76: 2012 | N76: CGFR
A77: 74 | B77: 89 | C77: Acme Truck Line Inc | D77: 325000 | F77: 3000 | G77: 1910 | H77: 780 | I77: 2200 | M77: 2012 | N77: ATEQ
A78: 75 | B78: 76 | C78: Graebel Cos | D78: 322926 | E78: 3021 | F78: 1603 | G78: 460 | H78: 400 | I78: 864 | M78: 2012 | N78: Graebel | O78: not found
A79: 76 | B79: 77 | C79: Dayton Freight Lines | D79: 321000 | F79: 2838 | G79: 1105 | H79: 31 | I79: 2698 | M79: 2012 | N79: DAFG
A80: 77 | B80: 69 | C80: United Road Services | D80: 307000 | F80: 1122 | G80: 776 | H80: 0 | I80: 184 | M80: 2012 | N80: URDS | O80: 184 owner-operator tractor
A81: 78 | B81: 75 | C81: TransAm Trucking | D81: 305000 | F81: 588 | G81: 1347 | H81: 0 | I81: 2100 | M81: 2012 | N81: TAMI
A82: 79 | C82: Comtrak Logistics | D82: 294747 | E82: 15500 | F82: 343 | G82: 2102 | H82: 0 | I82: 450 | K82: 82 | M82: 2012 | N82: CMKI
A83: 80 | B83: 83 | C83: Cowan Systems | D83: 279044 | F83: 1281 | G83: 1252 | H83: 0 | I83: 3079 | M83: 2012 | N83: CWAS
A84: 81 | B84: 78 | C84: Epes Carriers | D84: 277087 | F84: 1276 | G84: 1087 | H84: 0 | I84: 3804 | M84: 2012 | N84: EPES
A85: 82 | B85: 80 | C85: A. Duie Pyle Cos. | D85: 270000 | F85: 2163 | G85: 754 | H85: 23 | I85: 2000 | M85: 2012 | N85: PYLE
A86: 83 | B86: 79 | C86: Evans Network of Cos. | D86: 268635 | F86: 250 | G86: 1725 | H86: 0 | I86: 525 | M86: 2012 | N86: EVTW
A87: 84 | C87: Wheaton Van Lines | D87: 250000 | F87: 138 | G87: 103 | H87: 47 | I87: 88 | M87: 2012 | N87: WHTN
A88: 85 | B88: 86 | C88: Bennett International Group | D88: 249514 | F88: 638 | G88: 646 | H88: 616 | I88: 1155 | M88: 2012 | N88: BGME
A89: 86 | B89: 84 | C89: Towne Air Freight | D89: 241772 | F89: 1120 | G89: 1020 | H89: 50 | I89: 1500 | M89: 2012 | N89: TOWE
A90: 87 | C90: OnTrac Inc. | D90: 239552 | F90: 1571 | G90: 0 | H90: 0 | I90: 154 | M90: 2012 | N90: EMSY
A91: 88 | B91: 96 | C91: Maverick USA | D91: 239497 | F91: 1497 | G91: 1199 | H91: 0 | I91: 1665 | M91: 2012 | N91: MAVK
A92: 89 | C92: Cassens Transport | D92: 238358 | F92: 1231 | G92: 537 | I92: 536 | M92: 2012 | N92: CASF
A93: 90 | B93: 90 | C93: Koch Companies | D93: 230189 | E93: 2400 | F93: 1000 | G93: 735 | H93: 0 | I93: 2400 | M93: 2012 | N93: KLOG
A94: 91 | B94: 81 | C94: Calyx Transportation Group | D94: 228983 | F94: 600 | G94: 251 | H94: 15 | I94: 1674 | M94: 2012 | N94: Calyx | O94: subsidiaries found
A95: 92 | C95: The Waggoners Trucking | D95: 224722 | F95: 1069 | G95: 1101 | H95: 0 | I95: 1100 | M95: 2012 | N95: WAGP
A96: 93 | B96: 95 | C96: Superior Bulk Logistics | D96: 224000 | E96: 5500 | F96: 1329 | G96: 1098 | H96: 0 | I96: 1835 | M96: 2012 | N96: SUAH
A97: 94 | B97: 87 | C97: Paschall Truck Lines | D97: 218383 | F97: 1464 | G97: 1150 | H97: 0 | I97: 3000 | M97: 2012 | N97: PASC
A98: 95 | B98: 99 | C98: Groendyke Transport Inc | D98: 217780 | F98: 1317 | G98: 953 | H98: 0 | I98: 1800 | M98: 2012 | N98: Groendyke | O98: not found
A99: 96 | B99: 93 | C99: U.S. 1 Industries | D99: 216000 | E99: 91 | F99: 91 | G99: 1702 | H99: 0 | I99: 100 | L99: 20 | M99: 2012 | N99: U.S. 1 | O99: not found
A100: 97 | C100: Transport Investments Inc. | D100: 215359 | F100: 127 | G100: 730 | H100: 0 | I100: 780 | M100: 2012 | N100: Transport Investments | O100: not found
...

Sheet For Hire 2012-13
A1: Rank 2013 | B1: Rank 2012 | C1: Company | D1: Revenue (000) | E1: Net Income (000) | F1: Employees | G1: Tractors | H1: Trucks & Vans | I1: Trailers | J1: Aircraft | K1: Container | L1: Chassis | M1: SCAC_Self
A2: 1 | B2: 1 | C2: =VLOOKUP('For Hire 2012-13'!B2,'For Hire 2011-12'!$A$4:$C$103,3) -> UPS Inc | D2: 55438000 | E2: 4372000 | F2: 395000 | G2: 103000 | J2: 237 | K2: 33000 | M2: UPSF
A3: 2 | B3: 2 | C3: =VLOOKUP('For Hire 2012-13'!B3,'For Hire 2011-12'!$A$4:$C$103,3) -> FedEx Corp | D3: 45100000 | E3: 2046000 | F3: 300000 | G3: 25028 | H3: 62076 | I3: 92982 | J3: 649 | M3: ELGS
A4: 3 | B4: 4 | C4: =VLOOKUP('For Hire 2012-13'!B4,'For Hire 2011-12'!$A$4:$C$103,3) -> J.B. Hunt Transport Services | D4: 5585000 | E4: 342000 | F4: 18467 | G4: =10397+152+686 -> 11235 | H4: =537+208 -> 745 | I4: 26340 | K4: 68302 | L4: 61948 | M4: QPMT
A5: 4 | B5: 3 | C5: =VLOOKUP('For Hire 2012-13'!B5,'For Hire 2011-12'!$A$4:$C$103,3) -> Con-way Inc | D5: 5473356 | E5: 99152 | F5: 29500 | G5: =11600+267 -> 11867 | I5: 32800 | M5: CNWY
A6: 5 | B6: 5 | C6: =VLOOKUP('For Hire 2012-13'!B6,'For Hire 2011-12'!$A$4:$C$103,3) -> YRC Worldwide | D6: 4865400 | E6: 83600 | F6: 2000 | G6: 14500 | I6: 46500 | M6: RDWY
A7: 6 | B7: 7 | C7: =VLOOKUP('For Hire 2012-13'!B7,'For Hire 2011-12'!$A$4:$C$103,3) -> Swift Transportation | D7: 4118195 | E7: 155422 | F7: 16900 | G7: =6081+6685+5195 -> 17961 | I7: 57310 | K7: 8717 | M7: SWFT
A8: 7 | B8: 6 | C8: =VLOOKUP('For Hire 2012-13'!B8,'For Hire 2011-12'!$A$4:$C$103,3) -> Schneider National Inc | D8: 3600000 | F8: 16900 | G8: =9700+2000 -> 11700 | I8: 31000 | K8: 14500 | M8: SCNN
A9: 8 | B9: 69 | C9: =VLOOKUP('For Hire 2012-13'!B9,'For Hire 2011-12'!$A$4:$C$103,3) -> Comtrak Logistics | D9: 3373898 | E9: 69110 | F9: 1982 | G9: =355+2269 -> 2624 | I9: 448 | K9: 25769 | M9: CMKI
A10: 9 | B10: 8 | C10: =VLOOKUP('For Hire 2012-13'!B10,'For Hire 2011-12'!$A$4:$C$103,3) -> TransForce Inc. | D10: 3019367 | E10: 98754 | F10: 14210 | G10: =4300+7630 -> 11930 | I10: 11200 | M10: TransForce
A11: 10 | B11: 9 | C11: =VLOOKUP('For Hire 2012-13'!B11,'For Hire 2011-12'!$A$4:$C$103,3) -> Landstar System | D11: 2644780 | E11: 146009 | F11: 1217 | G11: 8174 | H11: 258 | I11: 12912 | M11: LRGR
A12: 11 | B12: 10 | C12: =VLOOKUP('For Hire 2012-13'!B12,'For Hire 2011-12'!$A$4:$C$103,3) -> Ryder Supply Chain Solutions | D12: 2383063 | F12: 14312 | G12: 4098 | I12: 6042 | M12: Ryder
A13: 12 | B13: 11 | C13: =VLOOKUP('For Hire 2012-13'!B13,'For Hire 2011-12'!$A$4:$C$103,3) -> Old Dominion Freight Line | D13: 2337648 | E13: 206113 | F13: 14073 | G13: 6296 | H13: 105 | I13: 25052 | L13: 27 | M13: ODFL
A14: 13 | B14: 12 | C14: =VLOOKUP('For Hire 2012-13'!B14,'For Hire 2011-12'!$A$4:$C$103,3) -> Arkansas Best Corp. | D14: 2299549 | E14: 15811 | F14: 11420 | G14: 3791 | H14: 56 | I14: 19650 | M14: Arkansas
A15: 14 | B15: 13 | C15: =VLOOKUP('For Hire 2012-13'!B15,'For Hire 2011-12'!$A$4:$C$103,3) -> Werner Enterprises | D15: 2029183 | E15: 86785 | F15: 11642 | G15: =6380+670 -> 7050 | I15: 21980 | K15: 16 | M15: WENP
A16: 15 | B16: 14 | C16: =VLOOKUP('For Hire 2012-13'!B16,'For Hire 2011-12'!$A$4:$C$103,3) -> Sirva Inc. | D16: 1994200 | E16: 9700 | F16: 2700 | G16: =1+1831 -> 1832 | H16: 506 | I16: 6516 | M16: Sirva
A17: 16 | B17: 15 | C17: =VLOOKUP('For Hire 2012-13'!B17,'For Hire 2011-12'!$A$4:$C$103,3) -> Estes Express Lines | D17: 1948535 | F17: 14909 | G17: 6277 | H17: 398 | I17: 24102 | M17: EXLA
A18: 17 | B18: 18 | C18: =VLOOKUP('For Hire 2012-13'!B18,'For Hire 2011-12'!$A$4:$C$103,3) -> UniGroup Inc. | D18: 1700000 | F18: 1050 | G18: =1+6300 -> 6301 | H18: 4500 | I18: 10000 | K18: 16500 | M18: AERM
A19: 18 | B19: 16 | C19: =VLOOKUP('For Hire 2012-13'!B19,'For Hire 2011-12'!$A$4:$C$103,3) -> U.S. Xpress Enterprises | D19: 1600000 | F19: 9700 | G19: =6800+575+621 -> 7996 | I19: 17000 | M19: USXI
A20: 19 | B20: 17 | C20: =VLOOKUP('For Hire 2012-13'!B20,'For Hire 2011-12'!$A$4:$C$103,3) -> Purolator Inc. | D20: 1575391 | F20: 12000 | G20: 493 | H20: 169 | I20: 1292 | M20: Purolator
A21: 20 | B21: 19 | C21: =VLOOKUP('For Hire 2012-13'!B21,'For Hire 2011-12'!$A$4:$C$103,3) -> C.R. England Inc. | D21: 1495597 | F21: 7352 | G21: =3412+819+267 -> 4498 | I21: 6400 | K21: 1200 | M21: ENGI
A22: 21 | B22: 24 | C22: =VLOOKUP('For Hire 2012-13'!B22,'For Hire 2011-12'!$A$4:$C$103,3) -> Roadrunner Transportation Systems | D22: 1361410 | E22: 48996 | F22: 3325 | G22: =740+2983 -> 3723 | I22: 3429 | M22: MGAS
A23: 22 | B23: 21 | C23: =VLOOKUP('For Hire 2012-13'!B23,'For Hire 2011-12'!$A$4:$C$103,3) -> Prime Inc. | D23: 1300998 | E23: 163439 | F23: 4400 | G23: =2021+3168+158 -> 5347 | I23: 9436 | M23: PDSI
A24: 23 | B24: 23 | C24: =VLOOKUP('For Hire 2012-13'!B24,'For Hire 2011-12'!$A$4:$C$103,3) -> Kenan Advantage Group | D24: 1286631 | F24: 7530 | G24: =4449+488+1364 -> 6301 | I24: 9774 | M24: AVTK
A25: 24 | B25: 20 | C25: =VLOOKUP('For Hire 2012-13'!B25,'For Hire 2011-12'!$A$4:$C$103,3) -> CRST International | D25: 1269899 | F25: 4975 | G25: =1870+1208+1412 -> 4490 | H25: 5 | I25: 7552 | M25: CRFR
A26: 25 | B26: 22 | C26: =VLOOKUP('For Hire 2012-13'!B26,'For Hire 2011-12'!$A$4:$C$103,3) -> Saia Inc. | D26: 1139044 | E26: 43627 | F26: 8400 | G26: 3426 | H26: 35 | I26: 10848 | M26: SAIA
A27: 26 | B27: 25 | C27: =VLOOKUP('For Hire 2012-13'!B27,'For Hire 2011-12'!$A$4:$C$103,3) -> NFI Industries | D27: 1090000 | F27: 7600 | G27: =2050+250 -> 2300 | I27: 7400 | K27: 170 | M27: NFAQ
A28: 27 | B28: 27 | C28: =VLOOKUP('For Hire 2012-13'!B28,'For Hire 2011-12'!$A$4:$C$103,3) -> Southeastern Freight Lines | D28: 1065188 | F28: 8030 | G28: =3082+236 -> 3318 | H28: 23 | I28: 11042 | M28: SEFL
A29: 28 | B29: 26 | C29: =VLOOKUP('For Hire 2012-13'!B29,'For Hire 2011-12'!$A$4:$C$103,3) -> Universal Truckload Services Inc | D29: 1033492 | E29: 50572 | F29: 4339 | G29: =734+3403 -> 4137 | I29: 6198 | K29: 800 | L29: 778 | M29: UTVE
A30: 29 | B30: 29 | C30: =VLOOKUP('For Hire 2012-13'!B30,'For Hire 2011-12'!$A$4:$C$103,3) -> Averitt Express | D30: 1020000 | F30: N/A | G30: 4121 | H30: 42 | I30: 12139 | M30: AVRT
A31: 30 | B31: 28 | C31: =VLOOKUP('For Hire 2012-13'!B31,'For Hire 2011-12'!$A$4:$C$103,3) -> Crete Carrier Corp | D31: 1008165 | F31: 5524 | G31: 5300 | I31: 13614 | M31: CRCR
A32: 31 | B32: 31 | C32: =VLOOKUP('For Hire 2012-13'!B32,'For Hire 2011-12'!$A$4:$C$103,3) -> Knight Transportation | D32: 969237 | E32: 69282 | F32: 4600 | G32: =3539+452 -> 3991 | I32: 9181 | M32: Knight
A33: 32 | B33: 30 | C33: =VLOOKUP('For Hire 2012-13'!B33,'For Hire 2011-12'!$A$4:$C$103,3) -> Penske Logistics | D33: 968000 | F33: 10000 | G33: 1598 | H33: 224 | I33: 2816 | M33: PSKL
A34: 33 | B34: 47 | C34: =VLOOKUP('For Hire 2012-13'!B34,'For Hire 2011-12'!$A$4:$C$103,3) -> Heartland Express | D34: 961525 | E34: 90821 | F34: 5220 | G34: 4878 | I34: 14372 | M34: NDIJ
A35: 34 | B35: 35 | C35: =VLOOKUP('For Hire 2012-13'!B35,'For Hire 2011-12'!$A$4:$C$103,3) -> Quality Distribution Inc | D35: 929810 | E35: 42038 | F35: 1145 | G35: =832+1178+889 -> 2899 | I35: 5255 | M35: QTKI
A36: 35 | B36: 33 | C36: =VLOOKUP('For Hire 2012-13'!B36,'For Hire 2011-12'!$A$4:$C$103,3) -> Lynden Inc. | D36: 875000 | F36: 2540 | G36: =483+187 -> 670 | H36: =32+33 -> 65 | I36: 3612 | K36: 12154 | L36: 1558 | M36: LTIA
A37: 36 | B37: 37 | C37: =VLOOKUP('For Hire 2012-13'!B37,'For Hire 2011-12'!$A$4:$C$103,3) -> Atlas World Group | D37: 844827 | E37: 7747 | F37: 700 | G37: =14+2126 -> 2140 | H37: 1551 | I37: 3922 | M37: ALQK
A38: 37 | B38: 53 | C38: =VLOOKUP('For Hire 2012-13'!B38,'For Hire 2011-12'!$A$4:$C$103,3) -> Jack Cooper Transport Co. | D38: 825000 | F38: 4500 | G38: 4000 | M38: COOJ
A39: 38 | B39: 38 | C39: =VLOOKUP('For Hire 2012-13'!B39,'For Hire 2011-12'!$A$4:$C$103,3) -> Ruan Transportation Management Systems | D39: 807507 | F39: 5088 | G39: 3651 | H39: 39 | I39: 6683 | K39: 302 | M39: RLCF
A40: 39 | B40: 36 | C40: =VLOOKUP('For Hire 2012-13'!B40,'For Hire 2011-12'!$A$4:$C$103,3) -> Day & Ross Transportation1 Group | D40: 796476 | F40: 1734 | G40: =110+136+1366 -> 1612 | H40: 339 | I40: 2629 | L40: 69 | M40: DAYR
A41: 40 | B41: 39 | C41: =VLOOKUP('For Hire 2012-13'!B41,'For Hire 2011-12'!$A$4:$C$103,3) -> Trimac Group | D41: 761000 | F41: 3345 | G41: =1127+843 -> 1970 | I41: 4801 | M41: TSUH
A42: 41 | B42: 32 | C42: =VLOOKUP('For Hire 2012-13'!B42,'For Hire 2011-12'!$A$4:$C$103,3) -> Anderson Trucking Service | D42: 750204 | F42: 1300 | G42: =493+703+1009 -> 2205 | I42: 5300 | M42: ANNN
A43: 42 | B43: 74 | C43: =VLOOKUP('For Hire 2012-13'!B43,'For Hire 2011-12'!$A$4:$C$103,3) -> KLLM Transport Services | D43: 743682 | G43: 3250 | I43: 4600 | M43: KLMI
A44: 43 | B44: 41 | C44: =VLOOKUP('For Hire 2012-13'!B44,'For Hire 2011-12'!$A$4:$C$103,3) -> Covenant Transportation | D44: 684549 | E44: 5244 | F44: 4204 | G44: =2456+232 -> 2688 | I44: 6861 | M44: CVTH
A45: 44 | B45: 44 | C45: =VLOOKUP('For Hire 2012-13'!B45,'For Hire 2011-12'!$A$4:$C$103,3) -> Celadon Group1 | D45: 680936 | E45: 23314 | G45: =1941+1213+636 -> 3790 | I45: 8385 | K45: 185 | L45: 64 | M45: CDNK
A46: 45 | B46: 42 | C46: =VLOOKUP('For Hire 2012-13'!B46,'For Hire 2011-12'!$A$4:$C$103,3) -> Marten Transport | D46: 659214 | E46: 30147 | F46: 3045 | G46: =2206+49 -> 2255 | I46: 4105 | M46: MTEN
A47: 46 | B47: 45 | C47: =VLOOKUP('For Hire 2012-13'!B47,'For Hire 2011-12'!$A$4:$C$103,3) -> Forward Air Corp. | D47: 652481 | E47: 54467 | F47: 3537 | G47: =233+1284 -> 1517 | H47: 196 | I47: 3017 | L47: 50 | M47: FAFN
A48: 47 | B48: 43 | C48: =VLOOKUP('For Hire 2012-13'!B48,'For Hire 2011-12'!$A$4:$C$103,3) -> Stevens Transport | D48: 642138 | E48: 86285 | F48: 2835 | G48: =1890+820 -> 2710 | I48: 3615 | M48: STVV
A49: 48 | B49: 46 | C49: =VLOOKUP('For Hire 2012-13'!B49,'For Hire 2011-12'!$A$4:$C$103,3) -> AAA Cooper Transportation | D49: 580372 | F49: 4500 | G49: 2450 | I49: 6000 | M49: AACT
A50: 49 | B50: 51 | C50: =VLOOKUP('For Hire 2012-13'!B50,'For Hire 2011-12'!$A$4:$C$103,3) -> Contrans Group | D50: 555715 | E50: 28577 | G50: 1400 | I50: 2600 | M50: BCFG
A51: 50 | B51: 52 | C51: =VLOOKUP('For Hire 2012-13'!B51,'For Hire 2011-12'!$A$4:$C$103,3) -> USA Truck | D51: 555005 | E51: 9110 | F51: 2750 | G51: =2113+135 -> 2248 | I51: 6054 | M51: USAT
A52: 51 | B52: 48 | C52: =VLOOKUP('For Hire 2012-13'!B52,'For Hire 2011-12'!$A$4:$C$103,3) -> Canada catage system | D52: 541800 | F52: 3800 | G52: =1578+668 -> 2246 | H52: 359 | I52: 2589 | M52: CACG
A53: 52 | B53: 49 | C53: =VLOOKUP('For Hire 2012-13'!B53,'For Hire 2011-12'!$A$4:$C$103,3) -> Mullen Group | D53: 537858 | F53: 2170 | G53: =678+647 -> 1325 | H53: =252+178 -> 430 | I53: 3329 | K53: 555 | L53: 166 | M53: MULM
A54: 53 | B54: 50 | C54: =VLOOKUP('For Hire 2012-13'!B54,'For Hire 2011-12'!$A$4:$C$103,3) -> TransX Group | D54: 533061 | F54: 2630 | G54: =650+890 -> 1540 | I54: 4280 | K54: 940 | L54: 475 | M54: DKXP
A55: 54 | B55: 60 | C55: =VLOOKUP('For Hire 2012-13'!B55,'For Hire 2011-12'!$A$4:$C$103,3) -> The Suddath Cos | D55: 500000 | E55: 7000 | F55: 2000 | G55: =142+188 -> 330 | H55: 265 | I55: 692 | K55: 1492 | M55: SGLN
A56: 55 | B56: 63 | C56: =VLOOKUP('For Hire 2012-13'!B56,'For Hire 2011-12'!$A$4:$C$103,3) -> Bison Transport | D56: 485484 | F56: 2600 | G56: =876+526 -> 1402 | I56: 4000 | K56: 118 | L56: 51 | M56: BIOS
A57: 56 | B57: 54 | C57: =VLOOKUP('For Hire 2012-13'!B57,'For Hire 2011-12'!$A$4:$C$103,3) -> Mercer Transportation | D57: 483162 | F57: 315 | G57: 2183 | M57: MCET
A58: 57 | B58: 59 | C58: =VLOOKUP('For Hire 2012-13'!B58,'For Hire 2011-12'!$A$4:$C$103,3) -> Western Express | D58: 463454 | F58: 2962 | G58: =2415+4 -> 2419 | I58: 5650 | M58: WESD
A59: 58 | B59: 57 | C59: =VLOOKUP('For Hire 2012-13'!B59,'For Hire 2011-12'!$A$4:$C$103,3) -> Shevell Group | D59: 450105 | F59: 3515 | G59: =2100+40 -> 2140 | H59: 115 | I59: 4600 | L59: 10 | M59: Shevell
A60: 59 | B60: NA | C60: Daseke Inc. | D60: 447000 | F60: 1990 | G60: =1575+280+200 -> 2055 | I60: 3800 | L60: 95 | M60: Daseke
A61: 60 | B61: 64 | C61: =VLOOKUP('For Hire 2012-13'!B61,'For Hire 2011-12'!$A$4:$C$103,3) -> Pitt Ohio | D61: 429800 | F61: 2851 | G61: =1040+20+10 -> 1070 | H61: =398+68 -> 466 | I61: 3134 | M61: PITD
A62: 61 | B62: 55 | C62: =VLOOKUP('For Hire 2012-13'!B62,'For Hire 2011-12'!$A$4:$C$103,3) -> Dart Transit Co. | D62: 426320 | F62: 411 | G62: 1886 | I62: 6799 | K62: 342 | M62: ADTS
A63: 62 | B63: 62 | C63: =VLOOKUP('For Hire 2012-13'!B63,'For Hire 2011-12'!$A$4:$C$103,3) -> Groupe Robert | D63: 410719 | G63: =1100+270 -> 1370 | I63: 3000 | M63: BUTN
A64: 63 | B64: 65 | C64: =VLOOKUP('For Hire 2012-13'!B64,'For Hire 2011-12'!$A$4:$C$103,3) -> P.A.M. Transportation services | D64: 402813 | E64: 5915 | F64: 3034 | G64: =1480+357 -> 1837 | I64: 5170 | M64: PAMT
A65: 64 | B65: NA | C65: United Vision Logistics | D65: 400325 | E65: 19512 | F65: 291 | G65: 1505 | H65: 468 | I65: 1668 | M65: DYNS
A66: 65 | B66: 73 | C66: =VLOOKUP('For Hire 2012-13'!B66,'For Hire 2011-12'!$A$4:$C$103,3) -> Dayton Freight Lines | D66: 386000 | F66: 3361 | G66: 1167 | H66: 39 | I66: 2750 | M66: DAFG
A67: 66 | B67: 68 | C67: =VLOOKUP('For Hire 2012-13'!B67,'For Hire 2011-12'!$A$4:$C$103,3) -> Roehl Transport | D67: 384007 | F67: 2290 | G67: =1911+90+57 -> 2058 | H67: 7 | I67: 5148 | M67: ROEV
A68: 67 | B68: 80 | C68: =VLOOKUP('For Hire 2012-13'!B68,'For Hire 2011-12'!$A$4:$C$103,3) -> Cowan Systems | D68: 377428 | F68: 1878 | G68: =1125+623 -> 1748 | I68: 3795 | M68: CWAS
A69: 68 | B69: 67 | C69: =VLOOKUP('For Hire 2012-13'!B69,'For Hire 2011-12'!$A$4:$C$103,3) -> Mesilla Valley Transportation | D69: 376000 | F69: 1700 | G69: 1200 | I69: 4500 | M69: MSLV
A70: 69 | B70: 75 | C70: =VLOOKUP('For Hire 2012-13'!B70,'For Hire 2011-12'!$A$4:$C$103,3) -> Graebel Cos. | D70: 363131 | E70: 158 | F70: 2271 | G70: =136+482 -> 618 | H70: 253 | I70: 963 | L70: 67 | M70: Graebel
A71: 70 | B71: 71 | C71: =VLOOKUP('For Hire 2012-13'!B71,'For Hire 2011-12'!$A$4:$C$103,3) -> Acme Truck Line Inc. | D71: 356157 | F71: 3200 | G71: 2007 | H71: 724 | I71: 2257 | M71: ATEQ
A72: 71 | B72: 72 | C72: =VLOOKUP('For Hire 2012-13'!B72,'For Hire 2011-12'!$A$4:$C$103,3) -> Transport America | D72: 347465 | F72: 1945 | G72: =1350+15+150 -> 1515 | I72: 4450 | M72: EXTO
A73: 72 | B73: 70 | C73: =VLOOKUP('For Hire 2012-13'!B73,'For Hire 2011-12'!$A$4:$C$103,3) -> Comcar Industries | D73: 346403 | F73: 2679 | G73: =1601+385 -> 1986 | I73: 4401 | M73: Comcar
A74: 73 | B74: 77 | C74: =VLOOKUP('For Hire 2012-13'!B74,'For Hire 2011-12'!$A$4:$C$103,3) -> Interstate Distributor Co | D74: 339250 | F74: 1975 | G74: =1330+275 -> 1605 | I74: 5600 | M74: IPNS
A75: 74 | B75: 78 | C75: =VLOOKUP('For Hire 2012-13'!B75,'For Hire 2011-12'!$A$4:$C$103,3) -> United Road Services | D75: 333464 | F75: 2100 | G75: =1325+415 -> 1740 | M75: URDS
A76: 75 | B76: 83 | C76: =VLOOKUP('For Hire 2012-13'!B76,'For Hire 2011-12'!$A$4:$C$103,3) -> OnTrac Inc. | D76: 332331 | F76: 1697 | I76: 445 | M76: EMSY
A77: 76 | B77: 88 | C77: =VLOOKUP('For Hire 2012-13'!B77,'For Hire 2011-12'!$A$4:$C$103,3) -> Bennett International Group | D77: 327857 | F77: 727 | G77: =35+30+1114 -> 1179 | H77: 263 | I77: 1422 | M77: BGME
A78: 77 | B78: 76 | C78: =VLOOKUP('For Hire 2012-13'!B78,'For Hire 2011-12'!$A$4:$C$103,3) -> Challenger Group1 | D78: 325502 | F78: 1800 | G78: =1300+140 -> 1440 | I78: 2900 | L78: 420 | M78: CGFR
A79: 78 | B79: 82 | C79: =VLOOKUP('For Hire 2012-13'!B79,'For Hire 2011-12'!$A$4:$C$103,3) -> Epes Carriers | D79: 320000 | E79: 17700 | F79: 1446 | G79: =937+77+101 -> 1115 | M79: EPES
A80: 79 | B80: 81 | C80: =VLOOKUP('For Hire 2012-13'!B80,'For Hire 2011-12'!$A$4:$C$103,3) -> California Cartage Co. | D80: 318000 | G80: 1000 | M80: CCXP
A81: 80 | B81: 84 | C81: =VLOOKUP('For Hire 2012-13'!B81,'For Hire 2011-12'!$A$4:$C$103,3) -> Maverick USA | D81: 315014 | E81: 18674 | F81: 1777 | G81: =1307+73+25 -> 1405 | I81: 1971 | M81: MAVK
A82: 81 | B82: 87 | C82: =VLOOKUP('For Hire 2012-13'!B82,'For Hire 2011-12'!$A$4:$C$103,3) -> Evans Network of Cos | D82: 310000 | F82: 200 | G82: 2250 | I82: 525 | M82: EVTW
A83: 82 | B83: 85 | C83: =VLOOKUP('For Hire 2012-13'!B83,'For Hire 2011-12'!$A$4:$C$103,3) -> A. Duie Pyle Cos. | D83: 293000 | F83: 2235 | G83: =650+81 -> 731 | H83: 22 | I83: 1702 | M83: PYLE
A84: 83 | B84: 86 | C84: =VLOOKUP('For Hire 2012-13'!B84,'For Hire 2011-12'!$A$4:$C$103,3) -> Cassens Transport | D84: 289794 | F84: 1430 | G84: 1303 | M84: CASF
A85: 84 | B85: 91 | C85: =VLOOKUP('For Hire 2012-13'!B85,'For Hire 2011-12'!$A$4:$C$103,3) -> Koch Companies | D85: 274705 | F85: 955 | G85: =716+80+28 -> 824 | H85: 462 | I85: 4279 | K85: 60 | L85: 462 | M85: KLOG
A86: 85 | B86: 90 | C86: =VLOOKUP('For Hire 2012-13'!B86,'For Hire 2011-12'!$A$4:$C$103,3) -> Fastfrate Holdings | D86: 274633 | G86: =198+130 -> 328 | H86: 15 | I86: 650 | L86: 800 | M86: Consolidated
A87: 86 | B87: 92 | C87: =VLOOKUP('For Hire 2012-13'!B87,'For Hire 2011-12'!$A$4:$C$103,3) -> Towne Air Freight | D87: 265000 | G87: =260+800 -> 1060 | H87: 50 | I87: 1600 | M87: TOWE
A88: 87 | B88: NA | C88: The Dependable Cos. | D88: 257000 | F88: 1590 | G88: =324+238 -> 562 | H88: 40 | I88: 1231 | L88: 300 | M88: DPXI
A89: 88 | B89: 89 | C89: =VLOOKUP('For Hire 2012-13'!B89,'For Hire 2011-12'!$A$4:$C$103,3) -> John Christner Trucking LLC | D89: 256426 | E89: 9417 | F89: 211 | G89: =839+39 -> 878 | I89: 1188 | M89: CJHT
A90: 89 | B90: 96 | C90: =VLOOKUP('For Hire 2012-13'!B90,'For Hire 2011-12'!$A$4:$C$103,3) -> Superior Bulk Logistics | D90: 250700 | E90: 8900 | F90: 1414 | G90: =940+236 -> 1176 | I90: 2037 | M90: SUAH
A91: 90 | B91: NA | C91: Trans-System Inc. | D91: 246002 | F91: 898 | G91: =657+219 -> 876 | I91: 1110 | M91: Transsystem
A92: 91 | B92: 97 | C92: =VLOOKUP('For Hire 2012-13'!B92,'For Hire 2011-12'!$A$4:$C$103,3) -> Groendyke Transport Inc. | D92: 239000 | F92: 1368 | G92: 955 | I92: 1800 | M92: Groendyke
A93: 92 | B93: NA | C93: Arnold Transportation Services | D93: 237000 | F93: 1429 | G93: =1250+149 -> 1399 | I93: 4265 | M93: ANTT
A94: 93 | B94: NA | C94: Calyx Transportation Group | D94: 223323 | F94: 373 | G94: =170+318 -> 488 | H94: 30 | I94: 750 | K94: 200 | L94: 164 | M94: Calyx
A95: 94 | B95: 98 | C95: =VLOOKUP('For Hire 2012-13'!B95,'For Hire 2011-12'!$A$4:$C$103,3) -> Paschall Truck Lines | D95: 222685 | F95: 1450 | G95: =950+180 -> 1130 | I95: 2600 | M95: PASC
A96: 95 | B96: 93 | C96: =VLOOKUP('For Hire 2012-13'!B96,'For Hire 2011-12'!$A$4:$C$103,3) -> Wheaton Van Lines | D96: 221000 | E96: 6414 | F96: 183 | G96: 740 | H96: 261 | I96: 1143 | M96: WHTN
A97: 96 | B97: 95 | C97: =VLOOKUP('For Hire 2012-13'!B97,'For Hire 2011-12'!$A$4:$C$103,3) -> A&R Logistics | D97: 220000 | E97: 30000 | F97: 1000 | G97: =600+125 -> 725 | I97: 50 | K97: 275 | L97: 25 | M97: ANRI
A98: 97 | B98: 99 | C98: =VLOOKUP('For Hire 2012-13'!B98,'For Hire 2011-12'!$A$4:$C$103,3) -> Brown Integrated Logistics | D98: 218779 | F98: 1107 | G98: =545+31+426 -> 1002 | H98: 10 | I98: 4800 | M98: BRWH
A99: 98 | B99: NA | C99: Bridge Terminal Transport | D99: 218245 | F99: 262 | G99: 1285 | M99: BridgeTerminal
A100: 99 | B100: NA | C100: Falcon Transport Co. | D100: 217510 | E100: 8294 | F100: 1744 | G100: =831+22 -> 853 | I100: 1251 | M100: FCNW
...

Sheet For Hire 2013-14
A1: Rank 2014 | B1: Rank 2013 | C1: Company | D1: Revenue (000) | E1: Net Income (000) | F1: Employees | G1: Tractors | H1: Trucks & Vans | I1: Trailers | J1: Aircraft | K1: Container | L1: Chassis | M1: SCAC_Self
A2: 1 | B2: 1 | C2: =VLOOKUP('For Hire 2013-14'!B2,'For Hire 2012-13'!$A$2:$C$101,3) -> UPS Inc | D2: 58232000 | E2: 3032000 | F2: 435000 | G2: 106000 | J2: 237 | K2: 33000 | M2: UPSF
A3: 2 | B3: 2 | C3: =VLOOKUP('For Hire 2013-14'!B3,'For Hire 2012-13'!$A$2:$C$101,3) -> FedEx Corp | D3: 47100000 | E3: 2532000 | F3: 300000 | G3: 26594 | H3: 39211 | I3: 97469 | J3: 673 | M3: ELGS
A4: 3 | B4: 3 | C4: =VLOOKUP('For Hire 2013-14'!B4,'For Hire 2012-13'!$A$2:$C$101,3) -> J.B. Hunt Transport Services | D4: 6165441 | E4: 374792 | F4: 20158 | G4: =1358+11637 -> 12995 | I4: 27731 | K4: 73298 | M4: QPMT
A5: 4 | B5: 4 | C5: =VLOOKUP('For Hire 2013-14'!B5,'For Hire 2012-13'!$A$2:$C$101,3) -> Con-way Inc | D5: 5806069 | E5: 137039 | F5: 30100 | G5: 12100 | I5: 33300 | M5: CNWY
A6: 5 | B6: 5 | C6: =VLOOKUP('For Hire 2013-14'!B6,'For Hire 2012-13'!$A$2:$C$101,3) -> YRC Worldwide | D6: 5068800 | E6: 67700 | F6: 33000 | G6: 6400 | I6: 13000 | M6: RDWY
A7: 6 | B7: 6 | C7: =VLOOKUP('For Hire 2013-14'!B7,'For Hire 2012-13'!$A$2:$C$101,3) -> Swift Transportation | D7: 4298724 | E7: 161151 | F7: 21274 | G7: =6083+7799+4954 -> 18836 | I7: 61652 | K7: 9150 | M7: SWFT
A8: 7 | B8: 7 | C8: =VLOOKUP('For Hire 2013-14'!B8,'For Hire 2012-13'!$A$2:$C$101,3) -> Schneider National Inc | D8: 3900000 | F8: 17450 | G8: =9800+2500 -> 12300 | I8: 32350 | K8: 17500 | M8: SCNN
A9: 8 | B9: 8 | C9: =VLOOKUP('For Hire 2013-14'!B9,'For Hire 2012-13'!$A$2:$C$101,3) -> Comtrak Logistics | D9: 3571126 | E9: 51558 | F9: 2568 | G9: =1218+1759 -> 2977 | I9: 448 | K9: 28341 | M9: CMKI
A10: 9 | B10: 9 | C10: =VLOOKUP('For Hire 2013-14'!B10,'For Hire 2012-13'!$A$2:$C$101,3) -> TransForce Inc. | D10: 3363213 | E10: 138902 | F10: 16050 | G10: =6220+8760 -> 14980 | I10: 18680 | M10: TransForce
A11: 10 | B11: 10 | C11: =VLOOKUP('For Hire 2013-14'!B11,'For Hire 2012-13'!$A$2:$C$101,3) -> Landstar System | D11: 31840790 | E11: 138809 | F11: 1211 | G11: 8662 | H11: 270 | I11: 13732 | M11: LRGR
A12: 11 | B12: 12 | C12: =VLOOKUP('For Hire 2013-14'!B12,'For Hire 2012-13'!$A$2:$C$101,3) -> Old Dominion Freight Line | D12: 2787897 | E12: 267514 | F12: 18804 | G12: 6907 | H12: 116 | I12: 27635 | L12: 376 | M12: ODFL
A13: 12 | B13: 13 | C13: =VLOOKUP('For Hire 2013-14'!B13,'For Hire 2012-13'!$A$2:$C$101,3) -> Arkansas Best Corp. | D13: 2612693 | E13: 46177 | F13: 13238 | G13: 4191 | H13: 56 | I13: 19911 | M13: Arkansas
A14: 13 | B14: 11 | C14: =VLOOKUP('For Hire 2013-14'!B14,'For Hire 2012-13'!$A$2:$C$101,3) -> Ryder Supply Chain Solutions | D14: 2461149 | E14: 122356 | G14: 4098 | I14: 6042 | M14: Ryder
A15: 14 | B15: NA | C15: XPO Logistics | D15: 2356600 | E15: 63600 | F15: 10000 | G15: 6200 | M15: XPOL
A16: 15 | B16: 16 | C16: =VLOOKUP('For Hire 2013-14'!B16,'For Hire 2012-13'!$A$2:$C$101,3) -> Estes Express Lines | D16: 2173000 | F16: 15815 | G16: 6620 | H16: 388 | I16: 24592 | K16: 21 | M16: EXLA
A17: 16 | B17: 14 | C17: =VLOOKUP('For Hire 2013-14'!B17,'For Hire 2012-13'!$A$2:$C$101,3) -> Werner Enterprises | D17: 2139289 | E17: 98650 | F17: 10664 | G17: =6455+650 -> 7105 | I17: 22305 | K17: 1 | M17: WENP
A18: 17 | B18: 21 | C18: =VLOOKUP('For Hire 2013-14'!B18,'For Hire 2012-13'!$A$2:$C$101,3) -> Roadrunner Transportation Systems | D18: 1872816 | E18: 51974 | F18: 4142 | G18: =999+3171 -> 4170 | I18: 5135 | M18: MGAS
A19: 18 | B19: 18 | C19: =VLOOKUP('For Hire 2013-14'!B19,'For Hire 2012-13'!$A$2:$C$101,3) -> U.S. Xpress Enterprises | D19: 1730000 | G19: =6800+970 -> 7770 | I19: 17000 | M19: USXI
A20: 19 | B20: 17 | C20: =VLOOKUP('For Hire 2013-14'!B20,'For Hire 2012-13'!$A$2:$C$101,3) -> UniGroup Inc. | D20: 1700000 | F20: 1150 | G20: =5000+1 -> 5001 | H20: 3700 | I20: 500 | K20: 25000 | M20: AERM
A21: 20 | B21: 23 | C21: =VLOOKUP('For Hire 2013-14'!B21,'For Hire 2012-13'!$A$2:$C$101,3) -> Kenan Advantage Group | D21: 1567453 | F21: 7265 | G21: =4470+399+1586 -> 6455 | I21: 9448 | M21: AVTK
A22: 21 | B22: 22 | C22: =VLOOKUP('For Hire 2013-14'!B22,'For Hire 2012-13'!$A$2:$C$101,3) -> Prime Inc. | D22: 1563413 | E22: 207436 | F22: 4450 | G22: =1782+3966+439 -> 6187 | I22: 10637 | M22: PDSI
A23: 22 | B23: 19 | C23: =VLOOKUP('For Hire 2013-14'!B23,'For Hire 2012-13'!$A$2:$C$101,3) -> Purolator Inc. | D23: 1524071 | F23: 11500 | G23: 489 | H23: =166+3055 -> 3221 | I23: 1286 | M23: Purolator
A24: 23 | B24: 20 | C24: =VLOOKUP('For Hire 2013-14'!B24,'For Hire 2012-13'!$A$2:$C$101,3) -> C.R. England Inc. | D24: 1517290 | F24: 7385 | G24: =3528+427+132 -> 4087 | I24: 5293 | K24: 1642 | M24: ENGI
A25: 24 | B25: 15 | C25: =VLOOKUP('For Hire 2013-14'!B25,'For Hire 2012-13'!$A$2:$C$101,3) -> Sirva Inc. | D25: 1464400 | F25: 2700 | G25: =1+2608 -> 2609 | H25: 1625 | I25: 4263 | M25: Sirva
A26: 25 | B26: 24 | C26: =VLOOKUP('For Hire 2013-14'!B26,'For Hire 2012-13'!$A$2:$C$101,3) -> CRST International | D26: 1351571 | F26: 5129 | G26: =1684+1247+1463 -> 4394 | I26: 7290 | M26: CRFR
A27: 26 | B27: 25 | C27: =VLOOKUP('For Hire 2013-14'!B27,'For Hire 2012-13'!$A$2:$C$101,3) -> Saia Inc. | D27: 1272321 | E27: 51991 | F27: 8900 | G27: 3780 | I27: 11530 | M27: SAIA
A28: 27 | B28: 28 | C28: =VLOOKUP('For Hire 2013-14'!B28,'For Hire 2012-13'!$A$2:$C$101,3) -> Universal Truckload Services Inc | D28: 1191521 | E28: 45370 | F28: 4218 | G28: =1075+3333 -> 4408 | I28: 6291 | K28: 800 | L28: 954 | M28: UTVE
A29: 28 | B29: 27 | C29: =VLOOKUP('For Hire 2013-14'!B29,'For Hire 2012-13'!$A$2:$C$101,3) -> Southeastern Freight Lines | D29: 1171968 | F29: 8299 | G29: =3343+256 -> 3599 | H29: 23 | I29: 11496 | M29: SEFL
A30: 29 | B30: 32 | C30: =VLOOKUP('For Hire 2013-14'!B30,'For Hire 2012-13'!$A$2:$C$101,3) -> Penske Logistics | D30: 1137000 | F30: 13000 | G30: 2054 | H30: 245 | I30: 4918 | M30: PSKL
A31: 30 | B31: 26 | C31: =VLOOKUP('For Hire 2013-14'!B31,'For Hire 2012-13'!$A$2:$C$101,3) -> NFI Industries | D31: 1105000 | F31: 8000 | G31: =2022+242 -> 2264 | I31: 7500 | K31: 170 | M31: NFAQ
A32: 31 | B32: 31 | C32: =VLOOKUP('For Hire 2013-14'!B32,'For Hire 2012-13'!$A$2:$C$101,3) -> Knight Transportation | D32: 1102332 | E32: 102862 | F32: 5526 | G32: =4282+456 -> 4738 | I32: 11487 | M32: Knight
A33: 32 | B33: 30 | C33: =VLOOKUP('For Hire 2013-14'!B33,'For Hire 2012-13'!$A$2:$C$101,3) -> Crete Carrier Corp | D33: 1100000 | F33: 5500 | G33: 5130 | I33: 12883 | M33: CRCR
A34: 33 | B34: 29 | C34: =VLOOKUP('For Hire 2013-14'!B34,'For Hire 2012-13'!$A$2:$C$101,3) -> Averitt Express | D34: 1078000 | G34: 4441 | H34: 45 | I34: 13075 | M34: AVRT
A35: 34 | B35: 46 | C35: =VLOOKUP('For Hire 2013-14'!B35,'For Hire 2012-13'!$A$2:$C$101,3) -> Forward Air Corp. | D35: 1010959 | E35: 61169 | F35: 3600 | G35: =248+1052 -> 1300 | H35: =6+190 -> 196 | I35: 3100 | M35: FAFN
A36: 35 | B36: 35 | C36: =VLOOKUP('For Hire 2013-14'!B36,'For Hire 2012-13'!$A$2:$C$101,3) -> Lynden Inc. | D36: 1000000 | F36: 2652 | G36: =448+158 -> 606 | H36: 17 | I36: 3646 | K36: 8540 | L36: 58 | M36: LTIA
A37: 36 | B37: 34 | C37: =VLOOKUP('For Hire 2013-14'!B37,'For Hire 2012-13'!$A$2:$C$101,3) -> Quality Distribution Inc | D37: 991758 | E37: 20640 | F37: 188 | G37: =922+1343+930 -> 3195 | I37: 3171 | M37: QTKI
A38: 37 | B38: 36 | C38: =VLOOKUP('For Hire 2013-14'!B38,'For Hire 2012-13'!$A$2:$C$101,3) -> Atlas World Group | D38: 878313 | E38: 9542 | F38: 644 | G38: =12+2074 -> 2086 | H38: 784 | I38: 4012 | M38: ALQK
A39: 38 | B39: 41 | C39: =VLOOKUP('For Hire 2013-14'!B39,'For Hire 2012-13'!$A$2:$C$101,3) -> Anderson Trucking Service | D39: 873432 | F39: 1389 | G39: =581+1938 -> 2519 | I39: 6127 | M39: ANNN
A40: 39 | B40: 33 | C40: =VLOOKUP('For Hire 2013-14'!B40,'For Hire 2012-13'!$A$2:$C$101,3) -> Heartland Express | D40: 871355 | E40: 84834 | F40: 4500 | G40: 4776 | I40: 12970 | M40: NDIJ
A41: 40 | B41: 42 | C41: =VLOOKUP('For Hire 2013-14'!B41,'For Hire 2012-13'!$A$2:$C$101,3) -> KLLM Transport Services | D41: 863000 | G41: 3800 | I41: 5500 | M41: KLMI
A42: 41 | B42: 38 | C42: =VLOOKUP('For Hire 2013-14'!B42,'For Hire 2012-13'!$A$2:$C$101,3) -> Ruan Transportation Management Systems | D42: 848759 | F42: 5595 | G42: 3754 | H42: 48 | I42: 8395 | K42: 302 | L42: 248 | M42: RLCF
A43: 42 | B43: 44 | C43: =VLOOKUP('For Hire 2013-14'!B43,'For Hire 2012-13'!$A$2:$C$101,3) -> Celadon Group1 | D43: 806400 | E43: 35579 | F43: 4582 | G43: =2639+648+744 -> 4031 | I43: 11180 | K43: 185 | L43: 64 | M43: CDNK
A44: 43 | B44: 37 | C44: =VLOOKUP('For Hire 2013-14'!B44,'For Hire 2012-13'!$A$2:$C$101,3) -> Jack Cooper Transport Co. | D44: 790000 | G44: 3500 | M44: COOJ
A45: 44 | B45: 39 | C45: =VLOOKUP('For Hire 2013-14'!B45,'For Hire 2012-13'!$A$2:$C$101,3) -> Day & Ross Transportation1 Group | D45: 771988 | F45: 1602 | G45: =243+1309 -> 1552 | H45: 359 | I45: 3103 | L45: 45 | M45: DAYR
A46: 45 | B46: 40 | C46: =VLOOKUP('For Hire 2013-14'!B46,'For Hire 2012-13'!$A$2:$C$101,3) -> Trimac Group | D46: 737725 | F46: 3262 | G46: =1474+693 -> 2167 | I46: 4679 | M46: TSUH
A47: 46 | B47: 43 | C47: =VLOOKUP('For Hire 2013-14'!B47,'For Hire 2012-13'!$A$2:$C$101,3) -> Covenant Transportation | D47: 718980 | E47: 17808 | F47: 4400 | G47: =2470+195 -> 2665 | I47: 6722 | M47: CVTH
A48: 47 | B48: 47 | C48: =VLOOKUP('For Hire 2013-14'!B48,'For Hire 2012-13'!$A$2:$C$101,3) -> Stevens Transport | D48: 673160 | E48: 91310 | F48: 2835 | G48: =1945+830 -> 2775 | I48: 3782 | M48: STVV
A49: 48 | B49: 45 | C49: =VLOOKUP('For Hire 2013-14'!B49,'For Hire 2012-13'!$A$2:$C$101,3) -> Marten Transport | D49: 672929 | E49: 29834 | F49: 3240 | G49: =2368+52 -> 2420 | I49: 4265 | M49: MTEN
A50: 49 | B50: 59 | C50: =VLOOKUP('For Hire 2013-14'!B50,'For Hire 2012-13'!$A$2:$C$101,3) -> Daseke Inc. | D50: 668000 | F50: 2500 | G50: =1875+257+478 -> 2610 | I50: 5515 | M50: Daseke
A51: 50 | B51: 50 | C51: =VLOOKUP('For Hire 2013-14'!B51,'For Hire 2012-13'!$A$2:$C$101,3) -> USA Truck | D51: 602477 | E51: 6033 | G51: =1987+196 -> 2183 | I51: 6216 | M51: USAT
A52: 51 | B52: 48 | C52: =VLOOKUP('For Hire 2013-14'!B52,'For Hire 2012-13'!$A$2:$C$101,3) -> AAA Cooper Transportation | D52: 580372 | F52: 4500 | G52: 2450 | I52: 6000 | M52: AACT
A53: 52 | B53: 60 | C53: =VLOOKUP('For Hire 2013-14'!B53,'For Hire 2012-13'!$A$2:$C$101,3) -> Pitt Ohio | D53: 551300 | F53: 3140 | G53: 812 | H53: =398+36 -> 434 | I53: 2037 | M53: PITD
A54: 53 | B54: 56 | C54: =VLOOKUP('For Hire 2013-14'!B54,'For Hire 2012-13'!$A$2:$C$101,3) -> Mercer Transportation | D54: 547269 | F54: 325 | G54: 2189 | I54: 2189 | M54: MCET
A55: 54 | B55: 57 | C55: =VLOOKUP('For Hire 2013-14'!B55,'For Hire 2012-13'!$A$2:$C$101,3) -> Western Express | D55: 540104 | F55: 3107 | G55: =2402+2 -> 2404 | I55: 5700 | M55: WESD
A56: 55 | B56: 74 | C56: =VLOOKUP('For Hire 2013-14'!B56,'For Hire 2012-13'!$A$2:$C$101,3) -> United Road Services | D56: 532000 | F56: 1700 | G56: =1300+472 -> 1772 | M56: URDS
A57: 56 | B57: 51 | C57: =VLOOKUP('For Hire 2013-14'!B57,'For Hire 2012-13'!$A$2:$C$101,3) -> Canada catage system | D57: 516976 | G57: =1952+591 -> 2543 | H57: 368 | I57: 2417 | M57: CACG
A58: 57 | B58: 52 | C58: =VLOOKUP('For Hire 2013-14'!B58,'For Hire 2012-13'!$A$2:$C$101,3) -> Mullen Group | D58: 516878 | F58: 2092 | G58: =831+543 -> 1374 | H58: =90+198 -> 288 | I58: 3529 | K58: 563+169 | M58: MULM
A59: 58 | B59: 54 | C59: =VLOOKUP('For Hire 2013-14'!B59,'For Hire 2012-13'!$A$2:$C$101,3) -> The Suddath Cos | D59: 500000 | F59: 2000 | G59: 384 | H59: 287 | I59: 754 | M59: SGLN
A60: 59 | B60: 55 | C60: =VLOOKUP('For Hire 2013-14'!B60,'For Hire 2012-13'!$A$2:$C$101,3) -> Bison Transport | D60: 489568 | F60: 2321 | G60: =1088+39+375 -> 1502 | I60: 3857 | K60: 182 | L60: 80 | M60: BIOS
A61: 60 | B61: 70 | C61: =VLOOKUP('For Hire 2013-14'!B61,'For Hire 2012-13'!$A$2:$C$101,3) -> Acme Truck Line Inc. | D61: 487208 | F61: 3000 | G61: 2007 | H61: 724 | I61: 2257 | M61: ATEQ
A62: 61 | B62: 53 | C62: =VLOOKUP('For Hire 2013-14'!B62,'For Hire 2012-13'!$A$2:$C$101,3) -> TransX Group | D62: 482571 | F62: 2560 | G62: =655+850 -> 1505 | I62: 4240 | K62: 915 | L62: 470 | M62: DKXP
A63: 62 | B63: 58 | C63: =VLOOKUP('For Hire 2013-14'!B63,'For Hire 2012-13'!$A$2:$C$101,3) -> Shevell Group | D63: 461000 | F63: 3559 | G63: =1885+35 -> 1920 | H63: 125 | I63: 4600 | L63: 20 | M63: Shevell
A64: 63 | B64: 76 | C64: =VLOOKUP('For Hire 2013-14'!B64,'For Hire 2012-13'!$A$2:$C$101,3) -> Bennett International Group | D64: 436024 | F64: 772 | G64: =66+110+1232 -> 1408 | H64: 388 | I64: 1418 | L64: 4 | M64: BGME
A65: 64 | B65: 65 | C65: =VLOOKUP('For Hire 2013-14'!B65,'For Hire 2012-13'!$A$2:$C$101,3) -> Dayton Freight Lines | D65: 436000 | F65: 3610 | G65: 1228 | I65: 3109 | M65: DAFG
A66: 65 | B66: 61 | C66: =VLOOKUP('For Hire 2013-14'!B66,'For Hire 2012-13'!$A$2:$C$101,3) -> Dart Transit Co. | D66: 425503 | E66: 3854 | F66: 1365 | G66: =575+1300 -> 1875 | I66: 5789 | K66: 94 | M66: ADTS
A67: 66 | B67: 67 | C67: =VLOOKUP('For Hire 2013-14'!B67,'For Hire 2012-13'!$A$2:$C$101,3) -> Cowan Systems | D67: 421515 | F67: 1700 | G67: =1125+623 -> 1748 | I67: 3795 | M67: CWAS
A68: 67 | B68: 63 | C68: =VLOOKUP('For Hire 2013-14'!B68,'For Hire 2012-13'!$A$2:$C$101,3) -> P.A.M. Transportation services | D68: 410937 | E68: 13491 | F68: 2911 | G68: =1436+325 -> 1761 | I68: 4919 | M68: PAMT
A69: 68 | B69: 81 | C69: =VLOOKUP('For Hire 2013-14'!B69,'For Hire 2012-13'!$A$2:$C$101,3) -> Evans Network of Cos | D69: 400000 | F69: 275 | G69: =50+250+2850 -> 3150 | I69: 525 | M69: EVTW
A70: 69 | B70: 66 | C70: =VLOOKUP('For Hire 2013-14'!B70,'For Hire 2012-13'!$A$2:$C$101,3) -> Roehl Transport | D70: 395971 | F70: 2500 | G70: =2050+85+120 -> 2255 | H70: 8 | I70: 4090 | M70: ROEV
A71: 70 | B71: 73 | C71: =VLOOKUP('For Hire 2013-14'!B71,'For Hire 2012-13'!$A$2:$C$101,3) -> Interstate Distributor Co | D71: 385955 | F71: 2048 | G71: =1365+317 -> 1682 | I71: 5046 | M71: IPNS
A72: 71 | B72: 68 | C72: =VLOOKUP('For Hire 2013-14'!B72,'For Hire 2012-13'!$A$2:$C$101,3) -> Mesilla Valley Transportation | D72: 372000 | F72: 1700 | G72: 1300 | I72: 4800 | M72: MSLV
A73: 72 | B73: 79 | C73: =VLOOKUP('For Hire 2013-14'!B73,'For Hire 2012-13'!$A$2:$C$101,3) -> California Cartage Co. | D73: 368700 | G73: 1200 | M73: CCXP
A74: 73 | B74: 78 | C74: =VLOOKUP('For Hire 2013-14'!B74,'For Hire 2012-13'!$A$2:$C$101,3) -> Epes Carriers | D74: 341494 | E74: 24001 | F74: 1359 | G74: =944+177 -> 1121 | I74: 5500 | M74: EPES
A75: 74 | B75: 83 | C75: =VLOOKUP('For Hire 2013-14'!B75,'For Hire 2012-13'!$A$2:$C$101,3) -> Cassens Transport | D75: 328649 | F75: 1445 | G75: 1371 | M75: CASF
A76: 75 | B76: 882 | C76: =VLOOKUP('For Hire 2013-14'!B76,'For Hire 2012-13'!$A$2:$C$101,3) -> McCoy Group | D76: 318811 | F76: 2500 | G76: =756+66 -> 822 | H76: 22 | I76: 1900 | M76: mccoy
A77: 76 | B77: 80 | C77: =VLOOKUP('For Hire 2013-14'!B77,'For Hire 2012-13'!$A$2:$C$101,3) -> Maverick USA | D77: 316018 | E77: 21044 | F77: 1813 | G77: =1281+80+15 -> 1376 | I77: 1983 | M77: MAVK
A78: 77 | B78: 72 | C78: =VLOOKUP('For Hire 2013-14'!B78,'For Hire 2012-13'!$A$2:$C$101,3) -> Comcar Industries | D78: 315972 | F78: 2409 | G78: =1559+378 -> 1937 | I78: 4226 | M78: Comcar
A79: 78 | B79: 77 | C79: =VLOOKUP('For Hire 2013-14'!B79,'For Hire 2012-13'!$A$2:$C$101,3) -> Challenger Group1 | D79: 300130 | F79: 1900 | G79: =1500+140 -> 1640 | I79: 3300 | L79: 420 | M79: CGFR
A80: 79 | B80: 84 | C80: =VLOOKUP('For Hire 2013-14'!B80,'For Hire 2012-13'!$A$2:$C$101,3) -> Koch Companies | D80: 285000 | F80: 980 | G80: =747+59+33 -> 839 | H80: 418 | I80: 4584 | K80: 60 | L80: 418 | M80: KLOG
A81: 80 | B81: 87 | C81: =VLOOKUP('For Hire 2013-14'!B81,'For Hire 2012-13'!$A$2:$C$101,3) -> The Dependable Cos. | D81: 282000 | F81: 1777 | G81: =322+174 -> 496 | H81: 1 | I81: 1130 | L81: 324 | M81: DPXI
A82: 81 | B82: 88 | C82: =VLOOKUP('For Hire 2013-14'!B82,'For Hire 2012-13'!$A$2:$C$101,3) -> John Christner Trucking LLC | D82: 271104 | E82: 15033 | F82: 213 | G82: =15+690+28 -> 733 | I82: 1184 | M82: CJHT
A83: 82 | B83: 69 | C83: =VLOOKUP('For Hire 2013-14'!B83,'For Hire 2012-13'!$A$2:$C$101,3) -> Graebel Cos. | D83: 270000 | F83: 2000 | G83: =140+280 -> 420 | H83: 192 | I83: 800 | M83: Graebel
A84: 83 | B84: 90 | C84: =VLOOKUP('For Hire 2013-14'!B84,'For Hire 2012-13'!$A$2:$C$101,3) -> Trans-System Inc. | D84: 262627 | F84: 965 | G84: =715+209 -> 924 | I84: 1463 | M84: Transsystem
A85: 84 | B85: 94 | C85: =VLOOKUP('For Hire 2013-14'!B85,'For Hire 2012-13'!$A$2:$C$101,3) -> Paschall Truck Lines | D85: 261211 | G85: =950+200 -> 1150 | I85: 3000 | M85: PASC
A86: 85 | B86: 89 | C86: =VLOOKUP('For Hire 2013-14'!B86,'For Hire 2012-13'!$A$2:$C$101,3) -> Superior Bulk Logistics | D86: 260200 | E86: 7600 | F86: 1416 | G86: =953+236 -> 1189 | I86: 2099 | M86: SUAH
A87: 86 | B87: 100 | C87: =VLOOKUP('For Hire 2013-14'!B87,'For Hire 2012-13'!$A$2:$C$101,3) -> McCoy Group | D87: 249244 | F87: 1083 | G87: =857+224 -> 1081 | I87: 2096 | M87: mccoy
A88: 87 | B88: 91 | C88: =VLOOKUP('For Hire 2013-14'!B88,'For Hire 2012-13'!$A$2:$C$101,3) -> Groendyke Transport Inc. | D88: 241313 | F88: 1423 | G88: 975 | I88: 1500 | M88: Groendyke
A89: 88 | B89: NA | C89: Black Horse Carriers | D89: 238000 | F89: 1665 | G89: 950 | H89: 160 | I89: 2800 | M89: N/A
A90: 89 | B90: NA | C90: Transport Investments Inc. | D90: 237068 | F90: 115 | G90: =11+26+718 -> 755 | I90: 1101 | M90: Transportinvest
A91: 90 | B91: NA | C91: Melton Truck Lines | D91: 236000 | F91: 1378 | G91: 1107 | I91: 1837 | M91: MTLA
A92: 90 | B92: NA | C92: IMC Cos. | D92: 236000 | F92: 1522 | G92: =238+171+628 -> 1037 | I92: 88 | L92: 1619 | M92: IMCCos
A93: 92 | B93: NA | C93: Dicom Transportation Group | D93: 230874 | F93: 1200 | G93: =162+650 -> 812 | I93: 450 | M93: GOGI
A94: 93 | B94: 97 | C94: =VLOOKUP('For Hire 2013-14'!B94,'For Hire 2012-13'!$A$2:$C$101,3) -> Brown Integrated Logistics | D94: 224655 | F94: 1104 | G94: =515+67+465 -> 1047 | H94: 12 | I94: 5100 | M94: BRWH
A95: 94 | B95: 85 | C95: =VLOOKUP('For Hire 2013-14'!B95,'For Hire 2012-13'!$A$2:$C$101,3) -> Fastfrate Holdings | D95: 222960 | F95: 710 | G95: =333+171 -> 504 | H95: 24 | I95: 1371 | L95: 650 | M95: Consolidated
A96: 95 | B96: 96 | C96: =VLOOKUP('For Hire 2013-14'!B96,'For Hire 2012-13'!$A$2:$C$101,3) -> A&R Logistics | D96: 222000 | F96: 1100 | G96: =650+100 -> 750 | I96: 1400 | K96: 750 | M96: ANRI
A97: 95 | B97: NA | C97: Martin Transportation Systems | D97: 222000 | F97: 1551 | G97: =850+80 -> 930 | I97: 1800 | M97: MRLC
A98: 97 | B98: 93 | C98: =VLOOKUP('For Hire 2013-14'!B98,'For Hire 2012-13'!$A$2:$C$101,3) -> Calyx Transportation Group | D98: 218198 | G98: =175+325 -> 500 | H98: 30 | I98: 750 | K98: 240 | L98: 164 | M98: Calyx
A99: 98 | B99: NA | C99: Navajo Express | D99: 218000 | F99: 1300 | G99: =900+100 -> 1000 | I99: 1800 | M99: NAVE
A100: 99 | B100: NA | C100: Central Freight Lines Inc. | D100: 214000 | G100: =1198+250 -> 1448 | H100: 85 | I100: 6648 | M100: CENT
...

Sheet For Hire 2015-16
A1: Rank 2016 | B1: Rank 2015 | C1: Company | D1: Revenue (millions) | E1: Net Income (millions) | F1: Employees | G1: SCAC
A2: 1 | B2: 1 | C2: UPS Supply Chain Solutions | D2: 3,108 est | E2: 5900 | F2: 12700 | G2: UPSF | H2: UPS Supply Chain Solutions: Freight Forwarding
A3: 2 | B3: 12 | C3: XPO Logistics Inc. | D3: 2,841 est | E3: 5,536 est | G3: XPOL | H3: XPO Logistics LLC
A4: 3 | B4: 2 | C4: J.B. Hunt Transport Services | D4: 2,660 est | E4: 5816 | F4: - | G4: QPMT | H4: J.B. Hunt Transport Services
A5: 4 | B5: 4 | C5: C.H. Robinson Worldwide | D5: 2268 | E5: 13476 | F5: 13159 | G5: N/A
A6: 5 | B6: 5 | C6: Expeditors International of Washington | D6: 2188 | E6: 6617 | F6: 15397 | G6: EXDO | H6: Expeditors International of Washington, Inc.
A7: 6 | B7: 3 | C7: Ryder Supply Chain Solutions | D7: 1,925 est | E7: 2,443 est | F7: - | G7: Ryder | H7: Ryder Supply Chain Solutions
A8: 7 | B8: 6 | C8: DHL Supply Chain | D8: 1815 | E8: 3300 | F8: - | G8: DMAL | H8: DHL Global Forwarding
A9: 8 | B9: 10 | C9: FedEx Corp. | D9: 1,625 est | E9: 3178 | F9: - | G9: FDTB | H9: FedEx Corp
A10: 9 | B10: 7 | C10: Ceva Logistics | D10: 1,570 est | E10: 2452 | F10: - | G10: COUT | H10: CEVA Logistics, U.S.: cout
A11: 10 | B11: 8 | C11: Americold Logistics | D11: 1,555 est | E11: - | F11: - | G11: AEID | H11: Americold Transportation Services: US
A12: 11 | B12: 9 | C12: UTi Worldwide | D12: 1,330 est | E12: 3,696 est | F12: - | G12: N/A | H12: UTi Distribution, Inc.
A13: 12 | B13: 11 | C13: Schneider | D13: 1,275 est | E13: 3,480 est | F13: - | G13: N/A | H13: Schneider: Schneider Logistics Division
A14: 13 | B14: 13 | C14: Kuehne + Nagel Inc. | D14: 1197 | E14: 5230 | F14: - | G14: KHNN | H14: Kuehne + Nagel Inc.
A15: 14 | B15: 15 | C15: Penske Logistics | D15: 1,150 est | E15: 1,430 est | F15: 13750 | G15: PSKL | H15: Penske Logistics
A16: 15 | B16: 16 | C16: NFI | D16: 1130 | E16: 1200 | F16: 8101 | G16: NFIL,NFAV,NFBR,NFCV,NFIA,NFIH,NFIV,NFTG,NAFT,NAFQ,NFIV | H16: NFI: NFI Transportation
A17: 16 | B17: 14 | C17: Swift Transportation | D17: 1,065 est | E17: 1,418 est | F17: 120 | G17: SWFT | H17: Swift Transportation
A18: 17 | B18: 20 | C18: DB Schenker USA | D18: 898 | E18: 2687 | F18: - | G18: N/A
A19: 18 | B19: 19 | C19: Neovia Logistics | D19: 860 | E19: - | F19: - | G19: N/A
A20: 19 | B20: 17 | C20: Werner Global Logistics | D20: 826 | E20: 1052 | F20: 4933 | G20: N/A
A21: 20 | B21: 18 | C21: Ruan | D21: 816 | E21: 869 | F21: 5558 | G21: RLCF,RUAN | H21: Ruan Transportation Management Systems, Inc.: Ruan Transport Corporation
A22: 21 | B22: - | C22: Lineage Logistics | D22: 800 | E22: - | F22: - | G22: N/A
A23: 22 | B23: 24 | C23: OHL | D23: 732 est | E23: 1470 | F23: 8000 | G23: OHSQ | H23: OHL: Logistics
A24: 23 | B24: 22 | C24: Cardinal Logistics Holdings | D24: 681 est | E24: - | F24: - | G24: N/A
A25: 24 | B25: 23 | C25: APL Logistics | D25: 660 est | E25: 1030 | F25: 6000 | G25: APDD | H25: APL Logistics: AUTO
A26: 25 | B26: 27 | C26: Kenco Group | D26: 535 | E26: 582 | F26: 3800 | G26: KLSV | H26: Kenco Transportation Services
A27: 26 | B27: 26 | C27: Panalpina Inc. | D27: 459 | E27: 2784 | F27: - | G27: PALA | H27: Panalpina, Inc.
A28: 27 | B28: 33 | C28: Total Quality Logistics | D28: 446 | E28: 2240 | F28: 3791 | G28: TQYL | H28: Total Quality Logistics: Total Quality Logistics
A29: 28 | B29: 30 | C29: Universal Logistics Holdings Inc. | D29: 444 | E29: - | F29: - | G29: ULSV | H29: Universal Logistics Services, Inc: Freight Brokerage
A30: 29 | B30: 31 | C30: Hub Group | D30: 413 | E30: 3526 | F30: 2633 | G30: HUBG,HHWY | H30: Hub Group: Highway
A31: 30 | B31: 34 | C31: DSC Logistics | D31: 405 | E31: - | F31: - | G31: DRSC | H31: DSC Logistics: DSC Logistics
A32: 31 | B32: 32 | C32: Saddle Creek Logistics Services | D32: 390 | E32: - | F32: 2587 | G32: SDLC | H32: Saddle Creek Transportation Inc.
A33: 32 | B33: 28 | C33: U.S. Xpress Inc. | D33: 351 | E33: 508 | F33: - | G33: USXI | H33: U.S. Xpress
A34: 33 | B34: 40 | C34: BDP International | D34: 297 | E34: 1900 | F34: - | G34: N/A
A35: 34 | B35: 36 | C35: Landstar System | D35: 292 est | E35: 1,760 est | F35: 1223 | G35: LRGR | H35: Landstar System
A36: 35 | B36: 45 | C36: Echo Global Logistics | D36: 290 | E36: 1512 | F36: 2335 | G36: ECHS | H36: Echo Global Logistics
A37: 36 | B37: 35 | C37: Toll Global Forwarding | D37: 285 | E37: 1448 | F37: - | G37: N/A
A38: 37 | B38: 37 | C38: Performance Team | D38: 278 | E38: 279 | F38: 4300 | G38: PFYM | H38: Performance Team
A39: 38 | B39: 38 | C39: Burris Logistics | D39: 275 | E39: 3524 | F39: - | G39: N/A
A40: 39 | B40: 42 | C40: Preferred Freezer Services | D40: 265 est | E40: 324 | F40: 1525 | G40: PFBE | H40: Preferred Freezer Logistics
A41: 40 | B41: - | C41: Apex Logistics International | D41: 255 est | E41: 613 | F41: - | G41: N/A
A42: 41 | B42: 41 | C42: Cowan Logistics | D42: 252 | E42: 347 | F42: 1258 | G42: N/A
A43: 42 | B43: 29 | C43: Fidelitone | D43: 235 | E43: 245 | F43: 690 | G43: N/A
A44: 43 | B44: - | C44: Estenson Logistics | D44: 226 | E44: 226 | F44: - | G44: ESNL | H44: Estenson Logistics
A45: 44 | B45: 47 | C45: Crane Worldwide Logistics | D45: 217 | E45: 654 | F45: - | G45: CNCQ | H45: Crane Worldwide Logistics
A46: 45 | B46: 44 | C46: Averitt Express Inc. | D46: 204 | E46: 396 | F46: - | G46: AVRT | H46: Averitt Express
A47: 46 | B47: - | C47: Worldwide Express | D47: 200 est | E47: 750 | F47: - | G47: WISW | H47: WorldWide Logistics
A48: 47 | B48: - | C48: Port Logistics Group | D48: 190 | E48: 200 | F48: 2500 | G48: PLGM | H48: Port Logistics Group
A49: 48 | B49: - | C49: Radiant Logistics | D49: 189 | E49: 872 | F49: - | G49: RLGN | H49: Radiant Global Logistics, dba Adcom, Airgroup &DBA
A50: 49 | B50: 43 | C50: SCI Group | D50: 187 | E50: 189 | F50: - | G50: N/A
A51: 50 | B51: 50 | C51: Agility Logistics | D51: 180 est | E51: 774 est | F51: - | G51: N/A
A52: 50 | B52: 48 | C52: Odyssey Logistics & Technology | D52: 180 est | E52: 590 est | F52: - | G52: N/A | H52: Odyssey Logistics & Technology

Sheet For Hire 2016-17
A1: Rank 2017 | B1: Rank 2016 | C1: Company | D1: Revenue(000) | E1: Net income(000) | F1: Employees | G1: Tractors | H1: Trailers | I1: SCAC
A2: 1 | B2: 1 | C2: UPS Inc. | D2: 60906000 | E2: 3431000 | F2: 434000 | G2: - | H2: - | I2: =VLOOKUP(C2,Sheet1!A1:B3381,2) -> UPSF
A3: 2 | B3: 2 | C3: FedEx Corp. | D3: 57570000 | E3: 1907000 | F3: 400000 | G3: 29733 | H3: 108041 | I3: =VLOOKUP(C3,Sheet1!A2:B3382,2) -> N/A
A4: 3 | B4: 3 | C4: XPO Logistics | D4: 14619400 | E4: 63100 | F4: 89000 | G4: 15396 | H4: 27606 | I4: =VLOOKUP(C4,Sheet1!A3:B3383,2) -> URBS
A5: 4 | B5: 4 | C5: J.B. Hunt Transport Services Inc. | D5: 6555459 | E5: 432090 | F5: 22172 | G5: 14805 | H5: 30330 | I5: =VLOOKUP(C5,Sheet1!A4:B3384,2) -> JEZT
A6: 5 | B6: 5 | C6: YRC Worldwide | D6: 4697500 | E6: 21500 | F6: 32000 | G6: 14300 | H6: 44500 | I6: =VLOOKUP(C6,Sheet1!A5:B3385,2) -> YARB
A7: 6 | B7: 7 | C7: Schneider | D7: 4045736 | E7: 156851 | F7: 19300 | G7: 10459 | H7: 37910 | I7: =VLOOKUP(C7,Sheet1!A6:B3386,2) -> SSIV
A8: 7 | B8: 6 | C8: Swift Transportation | D8: 4031517 | E8: 149267 | F8: 21900 | G8: 18366 | H8: 64066 | I8: =VLOOKUP(C8,Sheet1!A7:B3387,2) -> SDPO
A9: 8 | B9: 8 | C9: Hub Group | D9: 3572790 | E9: 74805 | F9: 2755 | G9: 2705 | H9: 436 | I9: =VLOOKUP(C9,Sheet1!A8:B3388,2) -> N/A
A10: 9 | B10: 9 | C10: Landstar System | D10: 3167634 | E10: 137350 | F10: 1197 | G10: 9186 | H10: 15170 | I10: =VLOOKUP(C10,Sheet1!A9:B3389,2) -> JEAC
A11: 10 | B11: 10 | C11: TFI International | D11: 3037205 | E11: 482592 | F11: 17685 | G11: 18535 | H11: 25310 | I11: =VLOOKUP(C11,Sheet1!A10:B3390,2) -> TRXP
A12: 11 | B12: 11 | C12: Old Dominion Freight Line Inc. | D12: 2991517 | E12: 295765 | F12: 19040 | G12: 7994 | H12: 32525 | I12: =VLOOKUP(C12,Sheet1!A11:B3391,2) -> OIXI
A13: 12 | B13: 12 | C13: ArcBest | D13: 2700219 | E13: 18652 | F13: 13000 | G13: 4387 | H13: 21361 | I13: =VLOOKUP(C13,Sheet1!A12:B3392,2) -> ACTC
A14: 13 | B14: 13 | C14: Ryder Supply Chain Solutions | D14: 2658745 | E14: 169172 | F14: - | G14: 67900 | H14: 42800 | I14: =VLOOKUP(C14,Sheet1!A13:B3393,2) -> N/A
A15: 14 | B15: 14 | C15: Estes Express Lines | D15: 2400000 | E15: - | F15: 16570 | G15: 7009 | H15: 26718 | I15: =VLOOKUP(C15,Sheet1!A14:B3394,2) -> ESNL
A16: 15 | B16: 16 | C16: Roadrunner Transportation Systems Inc. | D16: 2044000 | E16: - | F16: 4645 | G16: 4332 | H16: 6508 | I16: =VLOOKUP(C16,Sheet1!A15:B3395,2) -> RRIS
A17: 16 | B17: 15 | C17: Werner Enterprises Inc. | D17: 2008991 | E17: 79129 | F17: 11738 | G17: 7100 | H17: 24350 | I17: =VLOOKUP(C17,Sheet1!A16:B3396,2) -> WENG
A18: 17 | B18: 17 | C18: UniGroup Inc. | D18: 1700000 | E18: - | F18: - | G18: - | H18: - | I18: =VLOOKUP(C18,Sheet1!A17:B3397,2) -> UNMC
A19: 18 | B19: 18 | C19: Prime Inc. | D19: 1683834 | E19: 194247 | F19: 3661 | G19: 6246 | H19: 12309 | I19: =VLOOKUP(C19,Sheet1!A18:B3398,2) -> PMYT
A20: 19 | B20: 24 | C20: CRST International | D20: 1546000 | E20: - | F20: 7849 | G20: 6682 | H20: 13811 | I20: =VLOOKUP(C20,Sheet1!A19:B3399,2) -> CRPS
A21: 20 | B21: 26 | C21: Purolator Holdings Ltd. | D21: 1526207 | E21: - | F21: 10000 | G21: 463 | H21: 1280 | I21: =VLOOKUP(C21,Sheet1!A20:B3400,2) -> PTAM
A22: 21 | B22: 23 | C22: Penske Logistics | D22: 1500000 | E22: - | F22: 14180 | G22: 2704 | H22: 8785 | I22: =VLOOKUP(C22,Sheet1!A21:B3401,2) -> PENM
A23: 21 | B23: 20 | C23: Sirva Inc. | D23: 1400000 | E23: - | F23: - | G23: - | H23: - | I23: =VLOOKUP(C23,Sheet1!A22:B3402,2) -> SGHE
A24: 21 | B24: 19 | C24: U.S. Xpress Enterprises | D24: 1500000 | E24: - | F24: 10135 | G24: 7000 | H24: 15500 | I24: =VLOOKUP(C24,Sheet1!A23:B3403,2) -> USDI
A25: 24 | B25: - | C25: R+L Carriers | D25: 1452000 | E25: - | F25: 10000 | G25: 5958 | H25: 12604 | I25: =VLOOKUP(C25,Sheet1!A24:B3404,2) -> HRSD
A26: 25 | B26: 21 | C26: Kenan Advantage Group Inc. | D26: 1421975 | E26: - | F26: 7561 | G26: 6869 | H26: 10404 | I26: =VLOOKUP(C26,Sheet1!A25:B3405,2) -> GRHA
A27: 26 | B27: 23 | C27: C.R. England Inc. | D27: 1304898 | E27: - | F27: 7883 | G27: 4165 | H27: 5990 | I27: =VLOOKUP(C27,Sheet1!A26:B3406,2) -> CORV
A28: 27 | B28: 27 | C28: NFI | D28: 1250000 | E28: - | F28: 8300 | G28: 2793 | H28: 8300 | I28: =VLOOKUP(C28,Sheet1!A27:B3407,2) -> NSLC
A29: 28 | B29: 25 | C29: Saia Inc. | D29: 1218481 | E29: 48024 | F29: 9000 | G29: 4000 | H29: 13000 | I29: =VLOOKUP(C29,Sheet1!A28:B3408,2) -> SAGE
A30: 29 | B30: 28 | C30: Southeastern Freight Lines | D30: 1192296 | E30: - | F30: 8458 | G30: 3734 | H30: 11943 | I30: =VLOOKUP(C30,Sheet1!A29:B3409,2) -> SXSQ
A31: 30 | B31: 29 | C31: Knight-Swift Transportation Holdings | D31: 1118034 | E31: 93863 | F31: 5500 | G31: 4705 | H31: 9915 | I31: =VLOOKUP(C31,Sheet1!A30:B3410,2) -> KNIG,KTMW,KNBK,KNIB,KNIM,KTPS
A32: 31 | B32: 32 | C32: Averitt Express | D32: 1091475 | E32: - | F32: - | G32: 4500 | H32: 14623 | I32: =VLOOKUP(C32,Sheet1!A31:B3411,2) -> AVOG
A33: 32 | B33: 30 | C33: Universal Logistics Holdings | D33: 1072751 | E33: 24244 | F33: 6275 | G33: 3801 | H33: 4154 | I33: =VLOOKUP(C33,Sheet1!A32:B3412,2) -> UFER
A34: 33 | B34: 32 | C34: Celadon Group Inc. | D34: 1050000 | E34: 2700 | F34: 6000 | G34: 7050 | H34: 15000 | I34: =VLOOKUP(C34,Sheet1!A33:B3413,2) -> CEJT
A35: 34 | B35: 37 | C35: Anderson Trucking Service | D35: 1032144 | E35: - | F35: 1410 | G35: 2372 | H35: 6300 | I35: =VLOOKUP(C35,Sheet1!A34:B3414,2) -> #N/A
A36: 35 | B36: 33 | C36: Crete Carrier Corp. | D36: 1030000 | E36: - | F36: 5500 | G36: 5130 | H36: 12883 | I36: =VLOOKUP(C36,Sheet1!A35:B3415,2) -> CRAW
A37: 36 | B37: - | C37: Cardinal Logistics Holdings | D37: 1000600 | E37: - | F37: 4642 | G37: 3020 | H37: 9725 | I37: =VLOOKUP(C37,Sheet1!A36:B3416,2) -> N/A
A38: 37 | B38: 35 | C38: Forward Air Corp. | D38: 982530 | E38: 27670 | F38: 3689 | G38: 935 | H38: 4868 | I38: =VLOOKUP(C38,Sheet1!A37:B3417,2) -> FTNA
A39: 38 | B39: 36 | C39: KLLM Transport Services | D39: 937000 | E39: - | F39: - | G39: 3815 | H39: 5300 | I39: =VLOOKUP(C39,Sheet1!A38:B3418,2) -> KLMI
A40: 39 | B40: 34 | C40: Lynden Inc. | D40: 925000 | E40: - | F40: 2800 | G40: 768 | H40: 2889 | I40: =VLOOKUP(C40,Sheet1!A39:B3419,2) -> LNWT
A41: 40 | B41: 38 | C41: Ruan | D41: 872184 | E41: - | F41: 5546 | G41: 3425 | H41: 8165 | I41: =VLOOKUP(C41,Sheet1!A40:B3420,2) -> RTTE
A42: 41 | B42: 39 | C42: Atlas World Group | D42: 795239 | E42: - | F42: - | G42: 2159 | H42: - | I42: =VLOOKUP(C42,Sheet1!A41:B3421,2) -> APEN
A43: 42 | B43: 46 | C43: Daseke Inc. | D43: 770000 | E43: -8700 | F43: 3400 | G43: 3500 | H43: 7300 | I43: =VLOOKUP(C43,Sheet1!A42:B3422,2) -> THDY
A44: 43 | B44: 42 | C44: Quality Distribution Inc. | D44: 758000 | E44: - | F44: - | G44: - | H44: - | I44: =VLOOKUP(C44,Sheet1!A43:B3423,2) -> USML
A45: 44 | B45: 113 | C45: Central Transport International | D45: 703000 | E45: - | F45: - | G45: 3180 | H45: 6543 | I45: =VLOOKUP(C45,Sheet1!A44:B3424,2) -> CSTS
A46: 45 | B46: 42 | C46: Trimac Transportation | D46: 700000 | E46: - | F46: 3400 | G46: 1800 | H46: 2400 | I46: =VLOOKUP(C46,Sheet1!A45:B3425,2) -> TLKV
A47: 46 | B47: 47 | C47: Marten Transport Ltd. | D47: 671144 | E47: 33464 | F47: 3622 | G47: 2848 | H47: 4854 | I47: =VLOOKUP(C47,Sheet1!A46:B3426,2) -> MKSW
A48: 47 | B48: 43 | C48: Covenant Transport Services | D48: 670651 | E48: 16835 | F48: 4400 | G48: 2535 | H48: 7389 | I48: =VLOOKUP(C48,Sheet1!A47:B3427,2) -> CVEN
A49: 48 | B49: 44 | C49: Jack Cooper Holdings Corp. | D49: 667849 | E49: - | F49: - | G49: 2119 | H49: 2126 | I49: =VLOOKUP(C49,Sheet1!A48:B3428,2) -> N/A
A50: 49 | B50: 46 | C50: Stevens Transport | D50: 662450 | E50: 77990 | F50: 2703 | G50: 2690 | H50: 3795 | I50: =VLOOKUP(C50,Sheet1!A49:B3429,2) -> SCII
A51: 50 | B51: 52 | C51: Pitt Ohio Transportation Group | D51: 649972 | E51: - | F51: 3178 | G51: 866 | H51: 2072 | I51: =VLOOKUP(C51,Sheet1!A50:B3430,2) -> PITD
A52: 51 | B52: 45 | C52: Day & Ross Transportation | D52: 640515 | E52: - | F52: 1829 | G52: 1531 | H52: 4010 | I52: =VLOOKUP(C52,Sheet1!A51:B3431,2) -> DVLC
A53: 52 | B53: 41 | C53: Heartland Express Inc. | D53: 612937 | E53: 56386 | F53: 3600 | G53: 5049 | H53: 15218 | I53: =VLOOKUP(C53,Sheet1!A52:B3432,2) -> NDIJ
A54: 53 | B54: 54 | C54: AAA Cooper Transportation Inc. | D54: 605538 | E54: - | F54: 4600 | G54: 2400 | H54: 6000 | I54: =VLOOKUP(C54,Sheet1!A53:B3433,2) -> #N/A
A55: 54 | B55: 49 | C55: Suddath | D55: 550000 | E55: - | F55: - | G55: - | H55: - | I55: =VLOOKUP(C55,Sheet1!A54:B3434,2) -> SZTI
A56: 55 | B56: 52 | C56: Western Express Inc. | D56: 527909 | E56: 38334 | F56: 3000 | G56: 2582 | H56: 7366 | I56: =VLOOKUP(C56,Sheet1!A55:B3435,2) -> WESD
A57: 56 | B57: 54 | C57: United Road Services Inc. | D57: 525000 | E57: - | F57: 1700 | G57: 1835 | H57: 1200 | I57: =VLOOKUP(C57,Sheet1!A56:B3436,2) -> N/A
A58: 56 | B58: - | C58: OnTrac Inc. | D58: 525000 | E58: - | F58: 3000 | G58: 55 | H58: 571 | I58: =VLOOKUP(C58,Sheet1!A57:B3437,2) -> EMSY
A59: 58 | B59: 51 | C59: Mullen Group Ltd. | D59: 520272 | E59: - | F59: 3267 | G59: 1821 | H59: 4998 | I59: =VLOOKUP(C59,Sheet1!A58:B3438,2) -> N/A
A60: 59 | B60: 59 | C60: Evans Network of Cos. | D60: 505000 | E60: - | F60: 320 | G60: 3865 | H60: 650 | I60: =VLOOKUP(C60,Sheet1!A59:B3439,2) -> ADEN
A61: 60 | B61: 58 | C61: Dayton Freight Lines Inc. | D61: 498370 | E61: - | F61: 4010 | G61: 1387 | H61: 3664 | I61: =VLOOKUP(C61,Sheet1!A60:B3440,2) -> DBKE
A62: 61 | B62: 58 | C62: PS Logistics | D62: 495300 | E62: - | F62: 2600 | G62: 2247 | H62: 2359 | I62: =VLOOKUP(C62,Sheet1!A61:B3441,2) -> RAYG
A63: 62 | B63: 57 | C63: Canada Cartage | D63: 452728 | E63: - | F63: 3110 | G63: 2429 | H63: 2736 | I63: =VLOOKUP(C63,Sheet1!A62:B3442,2) -> CAWD
A64: 63 | B64: 55 | C64: Mercer Transportation Co. | D64: 449337 | E64: - | F64: 295 | G64: 2228 | H64: 2400 | I64: =VLOOKUP(C64,Sheet1!A63:B3443,2) -> MTLA
A65: 64 | B65: 69 | C65: Dart Holding Co. | D65: 441845 | E65: - | F65: 1273 | G65: 2187 | H65: 6963 | I65: =VLOOKUP(C65,Sheet1!A64:B3444,2) -> DRIN
A66: 65 | B66: 63 | C66: California Cartage Co. | D66: 440000 | E66: - | F66: 1500 | G66: - | H66: - | I66: =VLOOKUP(C66,Sheet1!A65:B3445,2) -> CLXE
A67: 66 | B67: 60 | C67: Shevell Group | D67: 436000 | E67: - | F67: 3895 | G67: 1550 | H67: 3902 | I67: =VLOOKUP(C67,Sheet1!A66:B3446,2) -> N/A
A68: 67 | B68: 62 | C68: Cowan Systems | D68: 434018 | E68: - | F68: 1915 | G68: 2059 | H68: 5111 | I68: =VLOOKUP(C68,Sheet1!A67:B3447,2) -> CUXC
A69: 68 | B69: 66 | C69: P.A.M. Transport | D69: 432852 | E69: 11101 | F69: 2463 | G69: - | H69: 5699 | I69: =VLOOKUP(C69,Sheet1!A68:B3448,2) -> PLXB
A70: 69 | B70: 68 | C70: Bennett International Group | D70: 429616 | E70: - | F70: 998 | G70: 1338 | H70: 1892 | I70: =VLOOKUP(C70,Sheet1!A69:B3449,2) -> BMGI
A71: 70 | B71: 53 | C71: USA Truck | D71: 429099 | E71: -7699 | F71: 2000 | G71: 1415 | H71: 5605 | I71: =VLOOKUP(C71,Sheet1!A70:B3450,2) -> USKE
A72: 71 | B72: 61 | C72: TransX Group of Companies | D72: 423678 | E72: - | F72: 2617 | G72: 1560 | H72: 4410 | I72: =VLOOKUP(C72,Sheet1!A71:B3451,2) -> TWXC
A73: 72 | B73: 66 | C73: Mesilla Valley Transportation | D73: 402940 | E73: - | F73: 1900 | G73: 1400 | H73: 5100 | I73: =VLOOKUP(C73,Sheet1!A72:B3452,2) -> MSLV
A74: 73 | B74: - | C74: TMC Transportation | D74: 394000 | E74: - | F74: - | G74: - | H74: - | I74: =VLOOKUP(C74,Sheet1!A73:B3453,2) -> TDED
A75: 74 | B75: 65 | C75: Bison Transport Inc. | D75: 432084 | E75: - | F75: 2559 | G75: 1439 | H75: 4475 | I75: =VLOOKUP(C75,Sheet1!A74:B3454,2) -> BDLO
A76: 75 | B76: 70 | C76: Interstate Distributor Co. | D76: 370168 | E76: - | F76: 2000 | G76: 1805 | H76: 3900 | I76: =VLOOKUP(C76,Sheet1!A75:B3455,2) -> ITLO
A77: 76 | B77: 70 | C77: Roehl Transport Inc. | D77: 355323 | E77: - | F77: 2485 | G77: 1995 | H77: 4898 | I77: =VLOOKUP(C77,Sheet1!A76:B3456,2) -> RFS
A78: 77 | B78: 96 | C78: Central Freight Lines | D78: 347800 | E78: - | F78: - | G78: 1127 | H78: 7852 | I78: =VLOOKUP(C78,Sheet1!A77:B3457,2) -> CQNP
A79: 78 | B79: 79 | C79: A. Duie Pyle Inc. | D79: 346000 | E79: - | F79: 2800 | G79: 945 | H79: 2225 | I79: =VLOOKUP(C79,Sheet1!A78:B3458,2) -> #N/A
A80: 79 | B80: 78 | C80: Black Horse Carriers | D80: 337500 | E80: - | F80: 2625 | G80: 1520 | H80: 3000 | I80: =VLOOKUP(C80,Sheet1!A79:B3459,2) -> #N/A
A81: 80 | B81: 74 | C81: Maverick USA Inc. | D81: 334953 | E81: - | F81: 2119 | G81: 1675 | H81: 2453 | I81: =VLOOKUP(C81,Sheet1!A80:B3460,2) -> MAVK
A82: 81 | B82: 71 | C82: Epes Carriers Inc. | D82: 332073 | E82: 24333 | F82: 1535 | G82: 1202 | H82: - | I82: =VLOOKUP(C82,Sheet1!A81:B3461,2) -> ENVS
A83: 82 | B83: 75 | C83: Dicom Transportation Group | D83: 320700 | E83: - | F83: - | G83: - | H83: - | I83: =VLOOKUP(C83,Sheet1!A82:B3462,2) -> N/A
A84: 83 | B84: 74 | C84: Cassens Transport | D84: 317557 | E84: - | F84: 1419 | G84: 1364 | H84: 1364 | I84: =VLOOKUP(C84,Sheet1!A83:B3463,2) -> CPDF
A85: 84 | B85: 80 | C85: IMC Cos. | D85: 293000 | E85: - | F85: 1875 | G85: 1515 | H85: 91 | I85: =VLOOKUP(C85,Sheet1!A84:B3464,2) -> IHLE
A86: 85 | B86: 76 | C86: Koch Companies Inc. | D86: 280000 | E86: - | F86: 1150 | G86: 1001 | H86: 5250 | I86: =VLOOKUP(C86,Sheet1!A85:B3465,2) -> KUDT
A87: 86 | B87: - | C87: Dependable Supply Chain Services | D87: 278000 | E87: - | F87: - | G87: 321 | H87: 1220 | I87: =VLOOKUP(C87,Sheet1!A86:B3466,2) -> DPHE
A88: 87 | B88: 91 | C88: Transport Investments Inc. | D88: 276000 | E88: - | F88: 200 | G88: 1150 | H88: 2100 | I88: =VLOOKUP(C88,Sheet1!A87:B3467,2) -> TAGB
A89: 88 | B89: - | C89: TransAm Trucking Inc. | D89: 270000 | E89: - | F89: - | G89: 1144 | H89: 1818 | I89: =VLOOKUP(C89,Sheet1!A88:B3468,2) -> TCVG
A90: 89 | B90: 82 | C90: Challenger Group | D90: 258006 | E90: - | F90: - | G90: - | H90: - | I90: =VLOOKUP(C90,Sheet1!A89:B3469,2) -> CGFR
A91: 90 | B91: 83 | C91: Trans-System Inc. | D91: 252500 | E91: - | F91: 1100 | G91: 1021 | H91: 1600 | I91: =VLOOKUP(C91,Sheet1!A90:B3470,2) -> TNUE
A92: 91 | B92: 84 | C92: Foodliner/Quest Liner | D92: 252275 | E92: - | F92: 1261 | G92: 1173 | H92: 2185 | I92: =VLOOKUP(C92,Sheet1!A91:B3471,2) -> FOLW
A93: 92 | B93: - | C93: Hirschbach Motor Lines | D93: 251697 | E93: - | F93: 646 | G93: 1010 | H93: - | I93: =VLOOKUP(C93,Sheet1!A92:B3472,2) -> HIRS
A94: 93 | B94: - | C94: United Vision Logistics | D94: 245000 | E94: - | F94: - | G94: 1003 | H94: 1347 | I94: =VLOOKUP(C94,Sheet1!A93:B3473,2) -> URDS
A95: 94 | B95: - | C95: Salmon Cos. | D95: 241796 | E95: - | F95: - | G95: 713 | H95: 1092 | I95: =VLOOKUP(C95,Sheet1!A94:B3474,2) -> N/A
A96: 95 | B96: 79 | C96: Comcar Industries | D96: 240054 | E96: - | F96: - | G96: 1592 | H96: 4660 | I96: =VLOOKUP(C96,Sheet1!A95:B3475,2) -> CMBD
A97: 96 | B97: 86 | C97: John Christner Trucking | D97: 239015 | E97: 14998 | F97: 232 | G97: 844 | H97: 1060 | I97: =VLOOKUP(C97,Sheet1!A96:B3476,2) -> BUHJ
A98: 97 | B98: 89 | C98: Martin Transportation Systems | D98: 237500 | E98: - | F98: 1637 | G98: 1130 | H98: 2200 | I98: =VLOOKUP(C98,Sheet1!A97:B3477,2) -> MKSW
A99: 98 | B99: 81 | C99: Paschall Truck Lines Inc. | D99: 237311 | E99: - | F99: 1872 | G99: 1303 | H99: 3101 | I99: =VLOOKUP(C99,Sheet1!A98:B3478,2) -> PDSN,PDSB
A100: 99 | B100: 87 | C100: Superior Bulk Logistics Inc. | D100: 233900 | E100: 5200 | F100: 1392 | G100: 1300 | H100: 2100 | I100: =VLOOKUP(C100,Sheet1!A99:B3479,2) -> SRIR
...

Sheet For Hire 2017-18
A1: Rank 2018 | B1: Rank 2017 | C1: Company | D1: Revenue(000) | E1: Net income(000) | F1: Employees | G1: Tractors | H1: Trailers | I1: SCAC
A2: 1 | B2: 1 | C2: UPS Inc. | D2: 65872000 | E2: 4910000 | F2: 454000 | G2: 18683 | H2: 97746 | I2: UPSF | J2: UPS Inc
A3: 2 | B3: 2 | C3: FedEx Corp. | D3: 63864000 | E3: 4465000 | F3: 425000 | G3: 29873 | H3: 113218 | I3: FDTB | J3: FedEx Corp
A4: 3 | B4: 3 | C4: XPO Logistics | D4: 15380800 | E4: 312400 | F4: 95000 | G4: 16287 | H4: 27591 | I4: XPOL | J4: XPO Logistics
A5: 4 | B5: 4 | C5: J.B. Hunt Transport Services Inc. | D5: 7189568 | E5: 385308 | F5: 27670 | G5: 14392 | H5: 32931 | I5: QPMT | J5: J.B. Hunt Transport Services
A6: 5 | B6: 30 | C6: Knight-Swift Transportation Holdings | D6: 5136261 | E6: 529922 | F6: 25400 | G6: 23069 | H6: 74949 | I6: N/A
A7: 6 | B7: 5 | C7: YRC Worldwide | D7: 4891000 | E7: -10800 | F7: 32000 | G7: 14100 | H7: 44600 | I7: RDWY | J7: YRC Worldwide
A8: 7 | B8: 6 | C8: Schneider | D8: 4383600 | E8: 389900 | F8: 19600 | G8: 11859 | H8: 37637 | I8: N/A | J8: Schneider: Schneider Logistics Division
A9: 8 | B9: 9 | C9: Hub Group | D9: 4034897 | E9: 135153 | F9: 4377 | G9: 3520 | H9: 5850 | I9: HUBG,HHWY | J9: Hub Group: Highway
A10: 9 | B10: 10 | C10: TFI International | D10: 3906575 | E10: 130181 | F10: 17044 | G10: 16132 | H10: 24617 | I10: N/A
A11: 10 | B11: 9 | C11: Landstar System | D11: 3646364 | E11: 177088 | F11: 1273 | G11: 9438 | H11: 15534 | I11: LRGR | J11: Landstar System
A12: 11 | B12: 11 | C12: Old Dominion Freight Line Inc. | D12: 3358112 | E12: 463774 | F12: 20944 | G12: 8316 | H12: 32890 | I12: ODFL | J12: Old Dominion Freight Line, Inc.
A13: 12 | B13: 13 | C13: Ryder Supply Chain Solutions | D13: 3065500 | E13: 158400 | F13: - | G13: - | H13: - | I13: Ryder | J13: Ryder Supply Chain Solutions
A14: 13 | B14: 12 | C14: ArcBest | D14: 2826457 | E14: 59726 | F14: 13000 | G14: 4436 | H14: 22275 | I14: KNIG,KTMW,KNBK,KNIB,KNIM,KTPS | J14: ArcBest
A15: 14 | B15: 14 | C15: Estes Express Lines | D15: 2740000 | E15: - | F15: 17397 | G15: 6695 | H15: 27443 | I15: EXLA | J15: Estes Express Lines
A16: 15 | B16: 16 | C16: Werner Enterprises Inc. | D16: 2116737 | E16: 92000 | F16: 12154 | G16: 7480 | H16: 24500 | I16: WENP,WEND,WENL,WGLL,WENF,WMMD,WEDV,WERN,WVAS,WMMI,WVAD,WRBH | J16: Werner Enterprises
A17: 16 | B17: 15 | C17: Roadrunner Transportation Systems Inc. | D17: 2091300 | E17: -91200 | F17: 4600 | G17: 3625 | H17: 6920 | I17: RDFS | J17: Roadrunner Transportation Services, Inc.
A18: 17 | B18: 27 | C18: NFI | D18: 1910000 | E18: - | F18: 10000 | G18: 4000 | H18: 8900 | I18: NFIL,NFAV,NFBR,NFCV,NFIA,NFIH,NFIV,NFTG,NAFT,NAFQ,NFIV | J18: NFI: NFI Transportation
A19: 18 | B19: 18 | C19: Prime Inc. | D19: 1875031 | E19: 208184 | F19: 4300 | G19: 6296 | H19: 12753 | I19: PDSI | J19: Prime Inc
A20: 19 | B20: 21 | C20: Penske Logistics | D20: 1700000 | E20: - | F20: 18011 | G20: 2935 | H20: 9108 | I20: PSKL | J20: Penske Logistics
A21: 19 | B21: 17 | C21: UniGroup Inc. | D21: 1700000 | E21: - | F21: - | G21: - | H21: - | I21: AERM | J21: UniGroup Inc.
A22: 21 | B22: 21 | C22: U.S. Xpress Enterprises | D22: 1600000 | E22: - | F22: 9522 | G22: 6600 | H22: 16800 | I22: USXI | J22: U.S. Xpress Enterprises
A23: 22 | B23: 24 | C23: R+L Carriers | D23: 1580000 | E23: - | F23: - | G23: 5084 | H23: 15675 | I23: N/A
A24: 23 | B24: 19 | C24: CRST International | D24: 1555000 | E24: - | F24: 7538 | G24: 5774 | H24: 12145 | I24: CRFR | J24: CRST International
A25: 24 | B25: 25 | C25: Kenan Advantage Group Inc. | D25: 1441440 | E25: - | F25: 9000 | G25: 6686 | H25: 10744 | I25: AVTK,BLKE,KAGW,KNTC,NOCP,POCN,DTCH,TRAP,CRYI,KEJB | J25: Kenan Advantage
A26: 25 | B26: 26 | C26: C.R. England Inc. | D26: 1405411 | E26: - | F26: 7975 | G26: 4213 | H26: 6116 | I26: ENGI | J26: C.R. England Inc.
A27: 26 | B27: 21 | C27: Sirva Inc. | D27: 1400000 | E27: - | F27: - | G27: - | H27: - | I27: Sirva | J27: Sirva Inc.
A28: 27 | B28: 28 | C28: Saia Inc. | D28: 1378510 | E28: 91156 | F28: 9800 | G28: 4259 | H28: 13901 | I28: SAIA | J28: Saia Inc.
A29: 28 | B29: 20 | C29: Purolator Holdings Ltd. | D29: 1343111 | E29: - | F29: 10000 | G29: 465 | H29: 1329 | I29: N/A
A30: 29 | B30: 42 | C30: Daseke Inc. | D30: 1300000 | E30: 26996 | F30: 4700 | G30: 5200 | H30: 11500 | I30: Daseke | J30: Daseke Inc.
A31: 30 | B31: 29 | C31: Southeastern Freight Lines | D31: 1260050 | E31: - | F31: 8792 | G31: 3635 | H31: 11697 | I31: SEFL | J31: Southeastern Freight Lines
A32: 31 | B32: 32 | C32: Universal Logistics Holdings | D32: 1216665 | E32: 28153 | F32: 8231 | G32: 3784 | H32: 5765 | I32: ULSV | J32: Universal Logistics Services, Inc: Freight Brokerage
A33: 32 | B33: 31 | C33: Averitt Express | D33: 1146970 | E33: 98967 | F33: 8500 | G33: 4513 | H33: 14585 | I33: AVRT | J33: Averitt Express
A34: 33 | B34: 37 | C34: Forward Air Corp. | D34: 1100816 | E34: 87321 | F34: 4898 | G34: 964 | H34: 6464 | I34: FAFN | J34: Forward Air Corp
A35: 34 | B35: 35 | C35: Crete Carrier Corp. | D35: 1100000 | E35: - | F35: 6000 | G35: 5400 | H35: 14000 | I35: CRCR | J35: Crete Carrier Corp
A36: 35 | B36: 33 | C36: Celadon Group Inc. | D36: 1065356 | E36: - | F36: 5200 | G36: 3850 | H36: 10000 | I36: CDNK,CNGV,CELU,CDER,CELZ,CDFK,OSTP | J36: Celadon Group, Inc.: Celadon Trucking
A37: 36 | B37: 34 | C37: Anderson Trucking Service | D37: 1004301 | E37: - | F37: 1996 | G37: 2652 | H37: 6958 | I37: ANNN | J37: Anderson Trucking Service
A38: 37 | B38: 38 | C38: KLLM Transport Services | D38: 959000 | E38: - | F38: - | G38: 3800 | H38: 5700 | I38: KLMI | J38: KLLM Transport Services
A39: 38 | B39: 39 | C39: Lynden Inc. | D39: 950000 | E39: - | F39: 2600 | G39: 768 | H39: 2889 | I39: LTIA | J39: Lynden Inc.
A40: 39 | B40: 59 | C40: Evans Network of Cos. | D40: 898000 | E40: - | F40: 376 | G40: 5014 | H40: 550 | I40: EVTW | J40: Evans Network of Cos
A41: 40 | B41: 41 | C41: Atlas World Group | D41: 842100 | E41: 4800 | F41: 671 | G41: 1271 | H41: 4076 | I41: ALQK | J41: Atlas World Group
A42: 41 | B42: 40 | C42: Ruan | D42: 836298 | E42: - | F42: 5500 | G42: 2900 | H42: 8710 | I42: RLCF,RUAN | J42: Ruan Transportation Management Systems, Inc.: Ruan Transport Corporation
A43: 42 | B43: 43 | C43: Quality Distribution Inc. | D43: 786000 | E43: - | F43: - | G43: 2541 | H43: 5204 | I43: QTKI | J43: Quality Distribution Inc
A44: 43 | B44: 44 | C44: Central Transport International | D44: 754000 | E44: - | F44: - | G44: 3180 | H44: 6543 | I44: CQNP | J44: Central Coast Transport Inc.
A45: 44 | B45: 36 | C45: Cardinal Logistics Holdings | D45: 720000 | E45: - | F45: 4245 | G45: 2905 | H45: 7940 | I45: CHWK | J45: Cardinal Health 200, LLC
A46: 45 | B46: 51 | C46: Day & Ross Transportation | D46: 718941 | E46: - | F46: 2240 | G46: 1800 | H46: 5714 | I46: N/A
A47: 46 | B47: 50 | C47: Pitt Ohio Transportation Group | D47: 715827 | E47: - | F47: 5381 | G47: 1856 | H47: 5372 | I47: PITD | J47: Pitt Ohio
A48: 47 | B48: 47 | C48: Covenant Transport Services | D48: 705007 | E48: 55439 | F48: 4297 | G48: 2700 | H48: 7389 | I48: CVEN | J48: Covenant Transport
A49: 48 | B49: 46 | C49: Marten Transport Ltd. | D49: 698120 | E49: 90284 | F49: 3492 | G49: 2738 | H49: 4909 | I49: MTEN | J49: Marten Transport LTD
A50: 49 | B50: 49 | C50: Stevens Transport | D50: 694980 | E50: 83845 | F50: 2925 | G50: 2810 | H50: 4010 | I50: STVV | J50: Stevens Transport
A51: 50 | B51: 53 | C51: AAA Cooper Transportation Inc. | D51: 665000 | E51: - | F51: 5000 | G51: 3000 | H51: 6500 | I51: AACT | J51: AAA Cooper Transportation
A52: 51 | B52: 56 | C52: United Road Services Inc. | D52: 645000 | E52: - | F52: 1700 | G52: 1850 | H52: 1150 | I52: URDS | J52: United Road Services Inc.
A53: 52 | B53: 58 | C53: Mullen Group Ltd. | D53: 627372 | E53: - | F53: 3535 | G53: 1919 | H53: 5065 | I53: N/A
A54: 53 | B54: 52 | C54: Heartland Express Inc. | D54: 607336 | E54: 75173 | F54: 3800 | G54: 6719 | H54: 19975 | I54: HAEI | J54: Heartland Express, Inc. of Iowa
A55: 54 | B55: 48 | C55: Jack Cooper Holdings Corp. | D55: 602825 | E55: 74839 | F55: 3753 | G55: 2637 | H55: - | I55: COOJ | J55: Jack Cooper Transport Co., Inc.
A56: 55 | B56: 61 | C56: PS Logistics | D56: 595780 | E56: - | F56: 3000 | G56: 2500 | H56: - | I56: N/A
A57: 56 | B57: 45 | C57: Trimac Transportation | D57: 576796 | E57: - | F57: 3200 | G57: 1720 | H57: 3800 | I57: TSUH,TTOS | J57: Trimac Transportation Inc.
A58: 57 | B58: 56 | C58: OnTrac Inc. | D58: 572856 | E58: - | F58: - | G58: 36 | H58: 950 | I58: EMSY | J58: OnTrac Inc.
A59: 58 | B59: 55 | C59: Western Express Inc. | D59: 566230 | E59: 41998 | F59: 2850 | G59: 2555 | H59: 7800 | I59: WSXI | J59: Western Express
A60: 59 | B60: 60 | C60: Dayton Freight Lines Inc. | D60: 562000 | E60: - | F60: 4501 | G60: 1561 | H60: 3803 | I60: DAFG | J60: Dayton Freight Lines Inc
A61: 60 | B61: 54 | C61: Suddath | D61: 550000 | E61: - | F61: - | G61: - | H61: - | I61: N/A
A62: 61 | B62: 62 | C62: Canada Cartage | D62: 546309 | E62: - | F62: 3137 | G62: 2548 | H62: 2817 | I62: CACG | J62: Canada Cartage System LP: CCSLP
A63: 62 | B63: 69 | C63: Bennett International Group | D63: 512874 | E63: - | F63: 1023 | G63: 1345 | H63: 2126 | I63: BGME | J63: Bennett International Group
A64: 63 | B64: 63 | C64: Mercer Transportation Co. | D64: 492509 | E64: - | F64: 293 | G64: 2299 | H64: 2299 | I64: MCET | J64: Mercer Transportation Company
A65: 64 | B65: - | C65: Two Men and a Truck Movers | D65: 487236 | E65: - | F65: 6136 | G65: - | H65: - | I65: N/A
A66: 65 | B66: 74 | C66: Bison Transport Inc. | D66: 472004 | E66: - | F66: 2944 | G66: 1704 | H66: 4732 | I66: BIOS | J66: Bison Transport Inc
A67: 66 | B67: 67 | C67: Cowan Systems | D67: 462544 | E67: - | F67: 1946 | G67: 2122 | H67: 5677 | I67: CWAS | J67: Cowan Systems
A68: 67 | B68: - | C68: Eagle Express Lines/Hoovestol Inc. | D68: 452429 | E68: - | F68: - | G68: 1935 | H68: 2421 | I68: N/A
A69: 68 | B69: 64 | C69: Dart Holding Co. | D69: 451925 | E69: - | F69: 2626 | G69: 2131 | H69: 7159 | I69: N/A
A70: 69 | B70: 70 | C70: USA Truck | D70: 446533 | E70: 7497 | F70: 2400 | G70: 1669 | H70: 5596 | I70: USAT | J70: USA Truck
A71: 70 | B71: 66 | C71: Shevell Group | D71: 439500 | E71: - | F71: 3745 | G71: 1550 | H71: 3950 | I71: Shevell | J71: Shevell Group
A72: 71 | B72: 68 | C72: P.A.M. Transport | D72: 437838 | E72: 38899 | F72: 2409 | G72: 2281 | H72: 5795 | I72: N/A
A73: 72 | B73: 72 | C73: Mesilla Valley Transportation | D73: 430261 | E73: - | F73: 1760 | G73: 1450 | H73: 6000 | I73: MSLV | J73: Mesilla Valley Transportation
A74: 73 | B74: 71 | C74: TransX Group of Companies | D74: 415541 | E74: - | F74: 2617 | G74: 1365 | H74: 4410 | I74: TNXL | J74: TransX: TNXL
A75: 74 | B75: 73 | C75: TMC Transportation | D75: 413000 | E75: - | F75: - | G75: 2613 | H75: 3404 | I75: TDED | J75: TMC Transportation
A76: 75 | B76: 79 | C76: Black Horse Carriers | D76: 412500 | E76: - | F76: 3150 | G76: 1670 | H76: 3500 | I76: N/A | J76: Black Horse Carriers
A77: 76 | B77: 81 | C77: Epes Carriers Inc. | D77: 400977 | E77: 26309 | F77: - | G77: 1272 | H77: 6065 | I77: EPES | J77: Epes Carriers Inc
A78: 77 | B78: - | C78: LaserShip Inc. | D78: 400000 | E78: - | F78: - | G78: 29 | H78: 27 | I78: N/A
A79: 78 | B79: 76 | C79: Roehl Transport Inc. | D79: 384473 | E79: - | F79: 2336 | G79: 1983 | H79: 4873 | I79: ROEV | J79: Roehl Transport, Inc.
A80: 79 | B80: 78 | C80: A. Duie Pyle Inc. | D80: 373000 | E80: - | F80: 2697 | G80: 946 | H80: 1936 | I80: PYLE | J80: A. Duie Pyle Inc.
A81: 80 | B81: 80 | C81: Maverick USA Inc. | D81: 352068 | E81: - | F81: 2122 | G81: 1648 | H81: 2480 | I81: N/A
A82: 81 | B82: 87 | C82: Transport Investments Inc. | D82: 339920 | E82: - | F82: 190 | G82: 1037 | H82: 1846 | I82: N/A
A83: 82 | B83: 84 | C83: IMC Cos. | D83: 332490 | E83: - | F83: 2300 | G83: 1658 | H83: 148 | I83: N/A
A84: 83 | B84: 82 | C84: Dicom Transportation Group | D84: 320700 | E84: - | F84: - | G84: - | H84: - | I84: GOGI | J84: Dicom Transportation Group
A85: 84 | B85: 94 | C85: Salmon Cos. | D85: 314303 | E85: - | F85: - | G85: 713 | H85: 1092 | I85: N/A
A86: 85 | B86: 83 | C86: Cassens Transport | D86: 302004 | E86: - | F86: 1265 | G86: 1231 | H86: 1231 | I86: CASF | J86: Cassens Transport
A87: 86 | B87: 88 | C87: TransAm Trucking Inc. | D87: 280000 | E87: - | F87: - | G87: 1135 | H87: 1823 | I87: TAMI | J87: TransAm Trucking
A88: 87 | B88: 92 | C88: Hirschbach Motor Lines | D88: 278494 | E88: - | F88: 800 | G88: 1250 | H88: 1965 | I88: HIRS | J88: Hirschbach Motor Lines
A89: 88 | B89: 91 | C89: Foodliner/Quest Liner | D89: 277471 | E89: - | F89: 1190 | G89: 1183 | H89: 2233 | I89: FOLW | J89: Foodliner
A90: 89 | B90: 85 | C90: Koch Companies Inc. | D90: 277000 | E90: - | F90: 1190 | G90: 1053 | H90: 5476 | I90: KLOG | J90: Koch Companies Inc.
A91: 90 | B91: 86 | C91: Dependable Supply Chain Services | D91: 274000 | E91: - | F91: - | G91: 344 | H91: 1220 | I91: DPXI | J91: Dependable Transportation, Inc. : Dependable Transportation, Inc.
A92: 91 | B92: 90 | C92: Trans-System Inc. | D92: 271000 | E92: - | F92: 1050 | G92: 1000 | H92: 1700 | I92: Transsystem | J92: Trans-System Inc.
A93: 92 | B93: - | C93: Melton Truck Lines Inc. | D93: 269785 | E93: - | F93: 1569 | G93: 1310 | H93: 2111 | I93: MTLA | J93: Melton Truck Lines, Inc
A94: 93 | B94: 77 | C94: Central Freight Lines | D94: 266000 | E94: - | F94: - | G94: 2001 | H94: 8012 | I94: CFMH | J94: Central Freight Lines
A95: 94 | B95: 97 | C95: Martin Transportation Systems | D95: 261403 | E95: - | F95: 1725 | G95: 1060 | H95: 2250 | I95: MRLC | J95: Martin Transportation Systems
A96: 95 | B96: 100 | C96: A&R Logistics | D96: 259370 | E96: - | F96: 1100 | G96: 858 | H96: 1132 | I96: ANRI | J96: A&R Logistics
A97: 96 | B97: 89 | C97: Challenger Group | D97: 258734 | E97: - | F97: 1850 | G97: 1469 | H97: 3300 | I97: CGFR | J97: Challenger Group
A98: 97 | B98: 93 | C98: United Vision Logistics | D98: 256000 | E98: - | F98: - | G98: 1003 | H98: 1347 | I98: DYNS | J98: United Vision Logistics
A99: 98 | B99: 99 | C99: Superior Bulk Logistics Inc. | D99: 252300 | E99: 14500 | F99: 1370 | G99: 1100 | H99: 2000 | I99: N/A
A100: 99 | B100: 96 | C100: John Christner Trucking | D100: 244696 | E100: 13138 | F100: 222 | G100: 809 | H100: 1112 | I100: CJHT | J100: John Christner Trucking, LLC
...

Sheet SCAC
A1: Performance Rankings | C1: ALL FLEETS
A2: Rankings are from 1-5, 1=Best (Top 20%)
A3: Click down arrows to filter data by column categories. Select one or more items in the dropdown checklists. | L3: =cou -> #NAME?
A4: To seach by name, SCAC or MCN, click CTRL + F to bring up the search dialogue box, then type in the 4 letter SCAC , the 8 digit MCN, or all or part of the company name.
A6: Note: g/tm=g/ton-mile | G6: Performance Rankings and Emission Factors
G7: Grams per Mile | M7: Grams per Ton-Mile
A8: CompanyDivisionName | B8: Mode | C8: SubMode | D8: Fleet Type | E8: SCAC | F8: MCN | G8: g/mile CO2 Rank | H8: g/mile CO2 | I8: g/mile NOx Rank | J8: g/mile NOx | K8: g/mile PM Rank | L8: g/mile PM | M8: g/tm CO2 Rank | N8: g/tm CO2 | O8: g/tm NOx Rank | P8: g/tm NOx | Q8: g/tm PM Rank | R8: g/tm PM | T8: SCAC_Self
A9: 1st Choice Logistics LLC | B9: Logistics | C9: Logistics | E9: FCOS | F9: MC833561 | G9: 5 | H9: 2460 | I9: 5 | J9: 28.5 | K9: 5 | L9: 1.275 | M9: 5 | N9: 492.5 | O9: 5 | P9: 3.35 | Q9: 5 | R9: 0.177 | T9: FCOS
A10: 3 Rivers Logistics, Inc | B10: Logistics | C10: Logistics | E10: TVQI | F10: MC376181 | G10: 5 | H10: 2460 | I10: 5 | J10: 28.5 | K10: 4 | L10: 1.025 | M10: 5 | N10: 492.5 | O10: 5 | P10: 3.35 | Q10: 4 | R10: 0.139 | T10: TVQI
A11: A & Z Trucking, Inc. | B11: Logistics | C11: Logistics | E11: AZTD | F11: MC510449 | G11: 5 | H11: 2460 | I11: 5 | J11: 28.5 | K11: 4 | L11: 1.025 | M11: 5 | N11: 492.5 | O11: 5 | P11: 3.35 | Q11: 4 | R11: 0.139 | T11: AZTD
A12: A&R Global Logistics | B12: Logistics | C12: Logistics | E12: AMLQ | F12: MC316077 | G12: 4 | H12: 2250 | I12: 3 | J12: 18.5 | K12: 3 | L12: 0.775 | M12: 2 | N12: 207.5 | O12: 2 | P12: 1.25 | Q12: 5 | R12: 0.177 | T12: AMLQ
A13: A.M.Transport Services, Inc. | B13: Logistics | C13: Logistics | E13: AMNO | F13: MC224875 | G13: 4 | H13: 2250 | I13: 5 | J13: 28.5 | K13: 4 | L13: 1.025 | M13: 4 | N13: 397.5 | O13: 4 | P13: 2.65 | Q13: 4 | R13: 0.139 | T13: AMNO
A14: Ace Logistics, Inc. | B14: Logistics | C14: Logistics | E14: ACEI | F14: MC411479 | G14: 4 | H14: 2250 | I14: 4 | J14: 23.5 | K14: 4 | L14: 1.025 | M14: 4 | N14: 397.5 | O14: 4 | P14: 2.65 | Q14: 4 | R14: 0.139 | T14: ACEI
A15: Adams Third Wave Logistics LLC: Freight Broker | B15: Logistics | C15: Logistics | E15: AHWE | F15: MC723939 | G15: 1 | H15: 1620 | I15: 1 | J15: 8.5 | K15: 1 | L15: 0.275 | M15: 1 | N15: 112.5 | O15: 1 | P15: 0.55 | Q15: 1 | R15: 0.025 | T15: AHWE
A16: Addison Transportation | B16: Logistics | C16: Logistics | E16: AFDN | F16: MC326834 | G16: 4 | H16: 2250 | I16: 4 | J16: 23.5 | K16: 4 | L16: 1.025 | M16: 4 | N16: 397.5 | O16: 4 | P16: 2.65 | Q16: 4 | R16: 0.139 | T16: AFDN
A17: ADM Logistics, Inc. | B17: Logistics | C17: Logistics | E17: ADOS | F17: MC274764 | G17: 1 | H17: 1620 | I17: 1 | J17: 8.5 | K17: 1 | L17: 0.275 | M17: 2 | N17: 207.5 | O17: 2 | P17: 1.25 | Q17: 2 | R17: 0.063 | T17: ADOS
A18: Advanced Transportation Services, Inc. | B18: Logistics | C18: Logistics | E18: AVDR | F18: MC191784 | G18: 4 | H18: 2250 | I18: 3 | J18: 18.5 | K18: 3 | L18: 0.775 | M18: 3 | N18: 302.5 | O18: 3 | P18: 1.95 | Q18: 3 | R18: 0.101 | T18: AVDR
A19: Aeronet Worldwide: supply chain solutions | B19: Logistics | C19: Logistics | E19: AERG,AERN | F19: MC0033994 | G19: 1 | H19: 1620 | I19: 1 | J19: 8.5 | K19: 1 | L19: 0.275 | M19: 1 | N19: 112.5 | O19: 1 | P19: 0.55 | Q19: 1 | R19: 0.025 | T19: AERG,AERN
A20: AFN, LLC | B20: Logistics | C20: Logistics | E20: AFNW | F20: MC446639 | G20: 3 | H20: 2040 | I20: 3 | J20: 18.5 | K20: 3 | L20: 0.775 | M20: 3 | N20: 302.5 | O20: 3 | P20: 1.95 | Q20: 3 | R20: 0.101 | T20: AFNW
... A595: Zipline Logistics, LLC | B595: Logistics | C595: Logistics | E595: N/A | F595: MC600879 | G595: 1 | H595: 1620 | I595: 1 | J595: 8.5 | K595: 1 | L595: 0.275 | M595: 1 | N595: 112.5 | O595: 1 | P595: 0.55 | Q595: 1 | R595: 0.025 | T595: N/A
A596: C.R. England: Intermodal | B596: Multi-modal | E596: ENGI | F596: MC124679 | H596: 1225 | J596: 18.5 | L596: 0.5 | N596: 30 | P596: 0.425 | R596: 0.014 | T596: ENGI
A597: Hub Group: Intermodal | B597: Multi-modal | E597: HUBG | F597: MC507885 | H597: 1225 | J597: 17.5 | L597: 0.48 | N597: 40 | P597: 0.475 | R597: 0.016 | T597: HUBG
A598: Independent Dispatch, Inc.: Intermodal | B598: Multi-modal | E598: INDD | F598: MC156480 | H598: 1075 | J598: 18.5 | L598: 0.5 | N598: 30 | P598: 0.425 | R598: 0.014 | T598: INDD
A599: Independent Dispatch, Inc.: Regional Trucking | B599: Multi-modal | E599: INDD | F599: MC156480 | H599: 1525 | J599: 15.5 | L599: 0.44 | N599: 60 | P599: 0.425 | R599: 0.016 | T599: INDD
A600: J.B. Hunt Transport, Inc.: Intermodal Division | B600: Multi-modal | E600: QPMT | F600: MC135797 | H600: 1075 | J600: 16.5 | L600: 0.44 | N600: 30 | P600: 0.375 | R600: 0.01 | T600: QPMT
A601: Kleysen Group LP: Intermodal Division | B601: Multi-modal | E601: KLET | F601: MCMB 0693372 | H601: 1375 | J601: 15.5 | L601: 0.46 | N601: 30 | P601: 0.425 | R601: 0.012 | T601: KLET
A602: Kleysen Group LP: Truckload Division | B602: Multi-modal | E602: KLET | F602: MCMB 0693372 | H602: 1675 | J602: 15.5 | L602: 0.44 | N602: 60 | P602: 0.375 | R602: 0.012 | T602: KLET
A603: Market Transport, Ltd.: Logistics | B603: Multi-modal | E603: MTLZ | F603: MC140827 | H603: 1525 | J603: 15.5 | L603: 0.52 | N603: 70 | P603: 0.575 | R603: 0.018 | T603: MTLZ
A604: Marten Transport LTD | B604: Multi-modal | E604: MTEN | F604: MC103798 | H604: 1675 | J604: 15.5 | L604: 0.44 | N604: 70 | P604: 0.375 | R604: 0.01 | T604: MTEN
A605: Schneider: Schneider Intermodal Division | B605: Multi-modal | E605: SCNN | F605: MC264184 | H605: 1075 | J605: 16.5 | L605: 0.46 | N605: 30 | P605: 0.425 | R605: 0.014 | T605: SCNN
A606: Triple Crown Services Company: rail operations | B606: Multi-modal | E606: TCSR | F606: MC263591 | H606: 1225 | J606: 17.5 | L606: 0.5 | N606: 40 | P606: 0.525 | R606: 0.016 | T606: TCSR
A607: UPS Small Package | B607: Multi-modal | E607: UPSN,UPSS | F607: MC115495 | H607: 1225 | J607: 15.5 | L607: 0.44 | N607: 70 | P607: 0.575 | R607: 0.018 | T607: UPSN,UPSS
... A609: YRC Worldwide Inc.: YRC Freight | B609: Multi-modal | E609: RDWY | F609: MC071821 | H609: 1675 | J609: 15.5 | L609: 0.46 | N609: 70 | P609: 0.575 | R609: 0.018 | T609: RDWY
A610: 101 Transport, Inc. | B610: Truck | C610: TL/Dry Van | D610: For-Hire | E610: OZOT | F610: MC625894 | G610: 2 | H610: 1560 | I610: 3 | J610: 5.9 | K610: 5 | L610: 0.086 | M610: 1 | N610: 74 | O610: 3 | P610: 0.375 | Q610: 5 | R610: 0.008 | T610: OZOT
A611: 1262380 Ontario Limited/dba FF Express | B611: Truck | C611: Expedited | D611: For-Hire | E611: FFXR | F611: MC343105 | G611: 2 | H611: 850 | I611: 2 | J611: 1.55 | K611: 2 | L611: 0.045 | M611: 4 | N611: 400 | O611: 3 | P611: 0.75 | Q611: 5 | R611: 0.0335 | T611: FFXR
A612: 1527530 Ontario Inc./M&M Carriers | B612: Truck | C612: TL/Dry Van | D612: For-Hire | E612: MNMR | F612: MCN/A | G612: 2 | H612: 1560 | I612: 2 | J612: 3.4 | K612: 2 | L612: 0.026 | M612: 2 | N612: 84 | O612: 2 | P612: 0.225 | Q612: 2 | R612: 0.002 | T612: MNMR
A613: 1541335 Ontario Inc./Road Link Xpress | B613: Truck | C613: TL/Dry Van | D613: For-Hire | E613: ROAD | F613: MCN/A | G613: 5 | H613: 1800 | I613: 3 | J613: 5.9 | K613: 5 | L613: 0.086 | M613: 2 | N613: 84 | O613: 2 | P613: 0.225 | Q613: 4 | R613: 0.006 | T613: ROAD
A614: 1579901 Ontario Inc./ASL Global Logistics | B614: Truck | C614: Refrigerated | D614: For-Hire | E614: AGBM | F614: MCN/A | G614: 2 | H614: 1640 | I614: 5 | J614: 7 | K614: 5 | L614: 0.175 | M614: 2 | N614: 82 | O614: 4 | P614: 0.425 | Q614: 5 | R614: 0.012 | T614: AGBM
A615: 1628939 Ontario LTD o/a P&D Freightlines | B615: Truck | C615: TL/Dry Van | D615: For-Hire | E615: PDGH | F615: MCN/A | G615: 3 | H615: 1640 | I615: 4 | J615: 8.4 | K615: 5 | L615: 0.086 | M615: 2 | N615: 84 | O615: 3 | P615: 0.375 | Q615: 5 | R615: 0.008 | T615: PDGH
A616: 1st Express Inc. | B616: Truck | C616: TL/Dry Van | D616: For-Hire | E616: FSEP | F616: MC181440 | G616: 2 | H616: 1560 | I616: 3 | J616: 5.9 | K616: 5 | L616: 0.086 | M616: 2 | N616: 84 | O616: 2 | P616: 0.225 | Q616: 4 | R616: 0.006 | T616: FSEP
A617: 2210310 Ontario Inc./Dynamic Freight Haulers | B617: Truck | C617: TL/Dry Van | D617: For-Hire | E617: DFHR | F617: MC691346 | G617: 4 | H617: 1720 | I617: 4 | J617: 8.4 | K617: 5 | L617: 0.086 | M617: 5 | N617: 114 | O617: 4 | P617: 0.525 | Q617: 5 | R617: 0.008 | T617: DFHR
A618: 2322819 Ontario Inc./Right Service Right Choice | B618: Truck | C618: TL/Dry Van | D618: For-Hire | E618: TTWT | F618: MCN/A | G618: 2 | H618: 1560 | I618: 3 | J618: 5.9 | K618: 5 | L618: 0.086 | M618: 3 | N618: 94 | O618: 3 | P618: 0.375 | Q618: 4 | R618: 0.006 | T618: TTWT
A619: 24/7 Express Logistics, Inc.: Truckload Denver | B619: Truck | C619: LTL/Dry Van | D619: For-Hire | E619: TFCD | F619: MC426943 | G619: 3 | H619: 1550 | I619: 1 | J619: 1.4 | K619: 1 | L619: 0.01 | M619: 4 | N619: 146 | O619: 1 | P619: 0.06 | Q619: 1 | R619: 0.00085 | T619: TFCD
A620: 24/7 Express Logistics, Inc.: Truckload KC | B620: Truck | C620: Mixed | D620: For-Hire | E620: TFCY | F620: MC426943 | G620: 4 | H620: 1800 | I620: 1 | J620: 1.55 | K620: 1 | L620: 0.015 | M620: 5 | N620: 113 | O620: 1 | P620: 0.075 | Q620: 1 | R620: 0.00085 | T620: TFCY
A621: 24/7 Express Logistics, Inc: Truckload | B621: Truck | C621: Mixed | E621: TFCY | F621: MC426943 | G621: 5 | H621: 1900 | I621: 5 | J621: 11.55 | K621: 5 | L621: 0.415 | M621: 5 | N621: 113 | O621: 5 | P621: 0.675 | Q621: 5 | R621: 0.0262 | T621: TFCY
A622: 24:7 Expedite, Inc.: Freight | B622: Truck | C622: Mixed | D622: For-Hire | E622: TWFJ | F622: MC690675 | G622: 4 | H622: 1800 | I622: 3 | J622: 6.55 | K622: 1 | L622: 0.015 | M622: 5 | N622: 113 | O622: 4 | P622: 0.525 | Q622: 2 | R622: 0.0052 | T622: TWFJ
A623: 3398722 Canada Inc: JB Transport | B623: Truck | C623: Refrigerated | D623: For-Hire | E623: 74Y6 | F623: MC516915 | G623: 5 | H623: 1940 | I623: 5 | J623: 7 | K623: 5 | L623: 0.175 | M623: 3 | N623: 88 | O623: 4 | P623: 0.425 | Q623: 5 | R623: 0.012 | T623: 74Y6
A624: 3NT, LLC. | B624: Truck | C624: TL/Dry Van | D624: For-Hire | E624: THLL | F624: MC716290 | G624: 2 | H624: 1560 | I624: 1 | J624: 0.9 | K624: 1 | L624: 0.006 | M624: 1 | N624: 74 | O624: 1 | P624: 0.075 | Q624: 1 | R624: 0.0005 | T624: THLL
A625: 5/D Express, Inc.: 5/D Express,Inc | B625: Truck | C625: TL/Dry Van | D625: For-Hire | E625: FDRP | F625: MC488737 | G625: 3 | H625: 1640 | I625: 3 | J625: 5.9 | K625: 5 | L625: 0.086 | M625: 1 | N625: 74 | O625: 2 | P625: 0.225 | Q625: 3 | R625: 0.004 | T625: FDRP
A626: 6233317 Canada Inc. DBA Rockwell Truck Line | B626: Truck | C626: TL/Dry Van | D626: For-Hire | E626: RKWT | F626: MC797845 | G626: 1 | H626: 1480 | I626: 5 | J626: 10.9 | K626: 5 | L626: 0.086 | M626: 1 | N626: 74 | O626: 4 | P626: 0.525 | Q626: 5 | R626: 0.008 | T626: RKWT
A627: 8198004 Canada Inc.: A AND R Transport & Logistics | B627: Truck | C627: Mixed | D627: For-Hire | E627: ARTQ | F627: MC823220 | G627: 5 | H627: 1900 | I627: 5 | J627: 11.55 | K627: 5 | L627: 0.415 | M627: 4 | N627: 103 | O627: 4 | P627: 0.525 | Q627: 5 | R627: 0.0262 | T627: ARTQ
A628: A & A Express, LLC | B628: Truck | C628: Refrigerated | D628: For-Hire | E628: AAXB | F628: MC108419 | G628: 4 | H628: 1840 | I628: 2 | J628: 3.4 | K628: 3 | L628: 0.115 | M628: 3 | N628: 88 | O628: 2 | P628: 0.205 | Q628: 2 | R628: 0.00425 | T628: AAXB
A629: A & C Transport LLC | B629: Truck | C629: Refrigerated | D629: For-Hire | E629: ACBB | F629: MCN/A | G629: 4 | H629: 1840 | I629: 3 | J629: 4.6 | K629: 2 | L629: 0.085 | M629: 5 | N629: 100 | O629: 2 | P629: 0.205 | Q629: 2 | R629: 0.00425 | T629: ACBB
A630: A & H Cartage, Inc. | B630: Truck | C630: LTL/Dry Van | D630: For-Hire | E630: AHCG | F630: MC196753 | G630: 3 | H630: 1550 | I630: 5 | J630: 8.6 | K630: 5 | L630: 0.3 | M630: 4 | N630: 146 | O630: 5 | P630: 0.86 | Q630: 4 | R630: 0.0242 | T630: AHCG
A631: A & T Trucking Company | B631: Truck | C631: Mixed | D631: For-Hire | E631: ATNG | F631: MC292766 | G631: 5 | H631: 1900 | I631: 1 | J631: 1.55 | K631: 1 | L631: 0.015 | M631: 5 | N631: 113 | O631: 1 | P631: 0.075 | Q631: 1 | R631: 0.00085 | T631: ATNG
A632: A Plus Expediting & Logistics Inc | B632: Truck | C632: Expedited | D632: For-Hire | E632: APEP | F632: MC641074 | G632: 5 | H632: 1450 | I632: 1 | J632: 0.35 | K632: 1 | L632: 0.004 | M632: 3 | N632: 300 | O632: 1 | P632: 0.15 | Q632: 1 | R632: 0.00175 | T632: APEP
A633: A&I Express Inc. | B633: Truck | C633: Refrigerated | D633: For-Hire | E633: AIEP | F633: MC629066 | G633: 1 | H633: 1540 | I633: 3 | J633: 4.6 | K633: 5 | L633: 0.175 | M633: 1 | N633: 76 | O633: 2 | P633: 0.205 | Q633: 4 | R633: 0.00925 | T633: AIEP
... A637: A&M Transport, Inc.: Flatbed Fleet | B637: Truck | C637: Flatbed | D637: For-Hire | E637: ALKM,AFLJ | F637: MC217072 | G637: 4 | H637: 1870 | I637: 4 | J637: 11 | K637: 2 | L637: 0.0965 | M637: 2 | N637: 74 | O637: 3 | P637: 0.375 | Q637: 2 | R637: 0.0045 | T637: ALKM,AFLJ
A638: A&M Transport, Inc.: Tautliner Fleet | B638: Truck | C638: Specialized | D638: For-Hire | E638: ALKM | F638: MC217072 | G638: 2 | H638: 1712.5 | I638: 3 | J638: 5.55 | K638: 2 | L638: 0.041 | M638: 2 | N638: 65 | P638: 0 | Q638: 2 | R638: 0.0032 | T638: ALKM
A639: A&R Logistics, Inc. | B639: Truck | C639: Heavy/Bulk | D639: For-Hire | E639: ANRI | F639: MC140820 | G639: 4 | H639: 2125 | I639: 2 | J639: 5.75 | K639: 4 | L639: 0.22 | M639: 5 | N639: 89.5 | O639: 4 | P639: 0.35 | Q639: 5 | R639: 0.0085 | T639: ANRI
A640: A&S Services Group, LLC | B640: Truck | C640: TL/Dry Van | D640: For-Hire | E640: ANSW | F640: MC164166 | G640: 2 | H640: 1560 | I640: 2 | J640: 3.4 | K640: 2 | L640: 0.026 | M640: 4 | N640: 104 | O640: 2 | P640: 0.225 | Q640: 2 | R640: 0.002 | T640: ANSW
A641: A. Blair Enterprises Inc | B641: Truck | C641: Specialized | D641: For-Hire | E641: BAEN | F641: MC218608 | G641: 1 | H641: 1537.5 | I641: 1 | J641: 0.95 | K641: 1 | L641: 0.008 | M641: 5 | N641: 89 | P641: 0 | Q641: 3 | R641: 0.0082 | T641: BAEN
A642: A. Duie Pyle Inc. | B642: Truck | C642: LTL/Dry Van | D642: For-Hire | E642: PYLE | F642: MC031941 | G642: 4 | H642: 1650 | I642: 3 | J642: 5 | K642: 3 | L642: 0.14 | M642: 3 | N642: 126 | O642: 3 | P642: 0.46 | Q642: 3 | R642: 0.0152 | T642: PYLE
A643: A. L. Smith Trucking, Inc. | B643: Truck | C643: Refrigerated | D643: For-Hire | E643: SALJ | F643: MC147232 | G643: 4 | H643: 1840 | I643: 4 | J643: 5.8 | K643: 5 | L643: 0.175 | M643: 4 | N643: 94 | O643: 3 | P643: 0.315 | Q643: 4 | R643: 0.00925 | T643: SALJ
A644: A. Smith Trucking Co. Inc. | B644: Truck | C644: Flatbed | D644: For-Hire | E644: SMGD | F644: MC297422 | G644: 1 | H644: 1570 | I644: 5 | J644: 14 | K644: 5 | L644: 0.5375 | M644: 1 | N644: 66 | O644: 4 | P644: 0.525 | Q644: 4 | R644: 0.0185 | T644: SMGD
A645: A.C. Trucking, Inc.: 12073707 | B645: Truck | C645: TL/Dry Van | D645: For-Hire | E645: AKGM | F645: MC196190 | G645: 3 | H645: 1640 | I645: 3 | J645: 5.9 | K645: 2 | L645: 0.026 | M645: 1 | N645: 74 | O645: 3 | P645: 0.375 | Q645: 2 | R645: 0.002 | T645: AKGM
A646: A.D. Transport Express, Inc. | B646: Truck | C646: TL/Dry Van | D646: For-Hire | E646: ADXR | F646: MC195625 | G646: 1 | H646: 1480 | I646: 2 | J646: 3.4 | K646: 2 | L646: 0.026 | M646: 5 | N646: 114 | O646: 3 | P646: 0.375 | Q646: 2 | R646: 0.002 | T646: ADXR
A647: A.N. Webber, Inc. | B647: Truck | C647: TL/Dry Van | D647: For-Hire | E647: WANQ | F647: MC147008 | G647: 3 | H647: 1640 | I647: 2 | J647: 3.4 | K647: 2 | L647: 0.026 | M647: 3 | N647: 94 | O647: 2 | P647: 0.225 | Q647: 2 | R647: 0.002 | T647: WANQ
A648: A.O. Knabb Inc. - Northern Berks Transport Brokera | B648: Truck | C648: Refrigerated | D648: For-Hire | E648: NBTN | F648: MC677982 | G648: 5 | H648: 1940 | I648: 5 | J648: 7 | K648: 5 | L648: 0.175 | M648: 5 | N648: 100 | O648: 5 | P648: 0.535 | Q648: 5 | R648: 0.012 | T648: NBTN
A649: A/T Transportation, LLC. | B649: Truck | C649: TL/Dry Van | D649: For-Hire | E649: AUCR | F649: MCN/A | G649: 4 | H649: 1720 | I649: 2 | J649: 3.4 | K649: 3 | L649: 0.046 | M649: 2 | N649: 84 | O649: 2 | P649: 0.225 | Q649: 2 | R649: 0.002 | T649: AUCR
A650: AAA Cooper Transportation | B650: Truck | C650: LTL/Dry Van | D650: Private | E650: AACT | F650: MC55889 | G650: 3 | H650: 1550 | I650: 4 | J650: 6.8 | K650: 5 | L650: 0.3 | M650: 3 | N650: 126 | O650: 3 | P650: 0.46 | Q650: 4 | R650: 0.0242 | T650: AACT
A651: Abbyland Trucking, Inc. | B651: Truck | C651: Refrigerated | D651: For-Hire | E651: ABYL | F651: MC226145 | G651: 3 | H651: 1740 | I651: 5 | J651: 7 | K651: 5 | L651: 0.175 | M651: 3 | N651: 88 | O651: 3 | P651: 0.315 | Q651: 5 | R651: 0.012 | T651: ABYL
A652: Abco Transportation: ABTS | B652: Truck | C652: Refrigerated | D652: For-Hire | E652: ABTS | F652: MC269456 | G652: 5 | H652: 1940 | I652: 3 | J652: 4.6 | K652: 5 | L652: 0.175 | M652: 5 | N652: 100 | O652: 3 | P652: 0.315 | Q652: 4 | R652: 0.00925 | T652: ABTS
A653: ABEX Transportation, LLC | B653: Truck | C653: Dray | D653: For-Hire | E653: ABED | F653: MC647183 | G653: 2 | H653: 1655 | I653: 2 | J653: 7.5 | K653: 3 | L653: 0.33 | M653: 2 | N653: 80 | O653: 2 | P653: 0.35 | Q653: 3 | R653: 0.0149 | T653: ABED
A654: ABF Freight System, Inc. | B654: Truck | C654: LTL/Dry Van | E654: ABFS | F654: MC029910 | G654: 3 | H654: 1550 | I654: 3 | J654: 5 | K654: 4 | L654: 0.22 | M654: 3 | N654: 126 | O654: 3 | P654: 0.46 | Q654: 3 | R654: 0.0152 | T654: ABFS
A655: Abilene Motor Express | B655: Truck | C655: TL/Dry Van | D655: For-Hire | E655: AEQC | F655: MC194957 | G655: 3 | H655: 1640 | I655: 3 | J655: 5.9 | K655: 4 | L655: 0.066 | M655: 3 | N655: 94 | O655: 2 | P655: 0.225 | Q655: 3 | R655: 0.004 | T655: AEQC
A656: Above All Transport LLC | B656: Truck | C656: Refrigerated | D656: Dedicated | E656: ABVC | F656: MC0383031 | G656: 5 | H656: 1940 | I656: 5 | J656: 7 | K656: 5 | L656: 0.175 | M656: 5 | N656: 100 | O656: 5 | P656: 0.535 | Q656: 5 | R656: 0.012 | T656: ABVC
A657: Absolute Intermodal LLC | B657: Truck | C657: Dray | D657: For-Hire | E657: ASUL | F657: MC603063 | G657: 2 | H657: 1655 | I657: 2 | J657: 7.5 | K657: 2 | L657: 0.13 | M657: 2 | N657: 80 | O657: 2 | P657: 0.35 | Q657: 2 | R657: 0.0059 | T657: ASUL
A658: ABT Freight Lines Inc | B658: Truck | C658: Refrigerated | D658: For-Hire | E658: ABTL | F658: MC713583 | G658: 5 | H658: 1940 | I658: 5 | J658: 7 | K658: 5 | L658: 0.175 | M658: 4 | N658: 94 | O658: 4 | P658: 0.425 | Q658: 5 | R658: 0.012 | T658: ABTL
A659: AC Leasing Company Inc. | B659: Truck | C659: TL/Dry Van | D659: For-Hire | E659: ACWH | F659: MC156691 | G659: 3 | H659: 1640 | I659: 4 | J659: 8.4 | K659: 5 | L659: 0.086 | M659: 1 | N659: 74 | O659: 3 | P659: 0.375 | Q659: 5 | R659: 0.008 | T659: ACWH
A660: AC Transport | B660: Truck | C660: Mixed | D660: For-Hire | E660: OFTO | F660: MC465753 | G660: 3 | H660: 1700 | I660: 5 | J660: 11.55 | K660: 4 | L660: 0.305 | M660: 2 | N660: 83 | O660: 4 | P660: 0.525 | Q660: 3 | R660: 0.0122 | T660: OFTO
A661: Accelerated Courier, Inc. | B661: Truck | C661: Mixed | D661: For-Hire | E661: ACUI | F661: MC171052 | G661: 2 | H661: 1600 | I661: 1 | J661: 1.55 | K661: 1 | L661: 0.015 | M661: 5 | N661: 113 | O661: 1 | P661: 0.075 | Q661: 1 | R661: 0.00085 | T661: ACUI
A662: Accelerated Services LLC | B662: Truck | C662: Auto Carrier | D662: For-Hire | E662: ACVY | F662: MC382853 | G662: 5 | H662: 2182.5 | I662: 1 | J662: 3.65 | K662: 2 | L662: 0.09 | M662: 4 | N662: 129.5 | O662: 2 | P662: 0.33 | Q662: 2 | R662: 0.0048 | T662: ACVY
A663: Accord Transportation Ltd.: Highway | B663: Truck | C663: TL/Dry Van | D663: For-Hire | E663: ACTL | F663: MCN/A | G663: 2 | H663: 1560 | I663: 2 | J663: 3.4 | K663: 4 | L663: 0.066 | M663: 1 | N663: 74 | O663: 1 | P663: 0.075 | Q663: 2 | R663: 0.002 | T663: ACTL
A664: Ace Doran Hauling & Rigging Co | B664: Truck | C664: Flatbed | D664: For-Hire | E664: ACEH | F664: MC112304 | G664: 1 | H664: 1570 | I664: 5 | J664: 14 | K664: 5 | L664: 0.5375 | M664: 3 | N664: 82 | O664: 5 | P664: 0.675 | Q664: 5 | R664: 0.0255 | T664: ACEH
A665: Ace Forwarding, Inc | B665: Truck | C665: Mixed | D665: For-Hire | E665: AFWO,AFWP | F665: MC307158 | G665: 1 | H665: 1500 | I665: 1 | J665: 1.55 | K665: 1 | L665: 0.015 | M665: 5 | N665: 113 | O665: 2 | P665: 0.225 | Q665: 2 | R665: 0.0052 | T665: AFWO,AFWP
A666: Ace Hardware Corporation: ACHW | B666: Truck | C666: LTL/Dry Van | D666: Private | E666: ACHW | F666: MC186924 | G666: 3 | H666: 1550 | I666: 1 | J666: 1.4 | K666: 1 | L666: 0.01 | M666: 3 | N666: 126 | O666: 2 | P666: 0.26 | Q666: 1 | R666: 0.00085 | T666: ACHW
... A678: Aerodyne Transportation, LLC | B678: Truck | C678: TL/Dry Van | D678: For-Hire | E678: LDWY | F678: MC161864 | G678: 1 | H678: 1480 | I678: 1 | J678: 0.9 | K678: 2 | L678: 0.026 | M678: 1 | N678: 74 | O678: 1 | P678: 0.075 | Q678: 1 | R678: 0.0005 | T678: LDWY
A679: Aeropres Corporation | B679: Truck | C679: Tanker | D679: Private | E679: ACOH | G679: 3 | H679: 1650 | I679: 2 | J679: 3.9 | K679: 2 | L679: 0.055 | M679: 5 | N679: 75 | O679: 3 | P679: 0.23 | Q679: 2 | R679: 0.0023 | T679: ACOH
A680: Aetna Freight Lines, Inc. | B680: Truck | C680: Flatbed | D680: For-Hire | E680: AGFC | F680: MC200014 | G680: 3 | H680: 1770 | I680: 5 | J680: 14 | K680: 5 | L680: 0.5375 | M680: 3 | N680: 82 | O680: 5 | P680: 0.675 | Q680: 5 | R680: 0.0255 | T680: AGFC
A681: Afton Trucking: AFTT | B681: Truck | C681: Dray | D681: For-Hire | E681: AFTT | F681: MC164738 | G681: 5 | H681: 1925 | I681: 1 | J681: 4.5 | K681: 2 | L681: 0.13 | M681: 3 | N681: 86 | O681: 1 | P681: 0.15 | Q681: 2 | R681: 0.0059 | T681: AFTT
A682: Ag Trucking, Inc. | B682: Truck | C682: Tanker | D682: For-Hire | E682: AGTG | F682: MC13367 | G682: 3 | H682: 1650 | I682: 1 | J682: 2.3 | K682: 2 | L682: 0.055 | M682: 3 | N682: 67 | O682: 2 | P682: 0.15 | Q682: 2 | R682: 0.0023 | T682: AGTG
A683: Agri-Tel Transportation Inc. | B683: Truck | C683: Refrigerated | D683: For-Hire | E683: AGTJ | F683: MCN/A | G683: 1 | H683: 1540 | I683: 1 | J683: 2.2 | K683: 1 | L683: 0.055 | M683: 1 | N683: 76 | O683: 1 | P683: 0.095 | Q683: 1 | R683: 0.0015 | T683: AGTJ
A684: Agricultural Express Inc | B684: Truck | C684: Refrigerated | D684: For-Hire | E684: AGIE | F684: MC195889 | G684: 4 | H684: 1840 | I684: 4 | J684: 5.8 | K684: 4 | L684: 0.145 | M684: 3 | N684: 88 | O684: 3 | P684: 0.315 | Q684: 3 | R684: 0.00675 | T684: AGIE
A685: Agricultural Transport | B685: Truck | C685: Refrigerated | D685: For-Hire | E685: AGUN | F685: MC245850 | G685: 3 | H685: 1740 | I685: 3 | J685: 4.6 | K685: 2 | L685: 0.085 | M685: 1 | N685: 76 | O685: 2 | P685: 0.205 | Q685: 2 | R685: 0.00425 | T685: AGUN
A686: Aim Integrated Logistics | B686: Truck | C686: Mixed | D686: Dedicated | E686: AIDD | F686: MC244504 | G686: 5 | H686: 1900 | I686: 2 | J686: 4.05 | K686: 2 | L686: 0.085 | M686: 5 | N686: 113 | O686: 2 | P686: 0.225 | Q686: 2 | R686: 0.0052 | T686: AIDD
A687: Aim Transport, Inc. | B687: Truck | C687: Mixed | D687: For-Hire | E687: AIMP | F687: MC240419 | G687: 2 | H687: 1600 | I687: 2 | J687: 4.05 | K687: 2 | L687: 0.085 | M687: 1 | N687: 73 | O687: 2 | P687: 0.225 | Q687: 1 | R687: 0.00085 | T687: AIMP
A688: Air Capitol Delivery & Warehouse LLC | B688: Truck | C688: TL/Dry Van | D688: For-Hire | E688: AQIR | F688: MC389874 | G688: 2 | H688: 1560 | I688: 2 | J688: 3.4 | K688: 5 | L688: 0.086 | M688: 3 | N688: 94 | O688: 2 | P688: 0.225 | Q688: 5 | R688: 0.008 | T688: AQIR
A689: Air Ground Xpress, Inc. | B689: Truck | C689: Mixed | D689: For-Hire | E689: AGXP | F689: MC268342 | G689: 1 | H689: 1500 | I689: 1 | J689: 1.55 | K689: 1 | L689: 0.015 | M689: 5 | N689: 113 | O689: 2 | P689: 0.225 | Q689: 1 | R689: 0.00085 | T689: AGXP
A690: Air Ocean Transport, Inc. | B690: Truck | C690: Mixed | D690: Private | E690: AIRT | F690: MC57133 | G690: 1 | H690: 1500 | I690: 5 | J690: 11.55 | K690: 5 | L690: 0.415 | M690: 4 | N690: 103 | O690: 5 | P690: 0.675 | Q690: 5 | R690: 0.0262 | T690: AIRT
...

Sheet All Fleet
A1: Performance Rankings | C1: ALL FLEETS
A2: Rankings are from 1-5, 1=Best (Top 20%)
A3: Click down arrows to filter data by column categories. Select one or more items in the dropdown checklists.
A4: To seach by name, SCAC or MCN, click CTRL + F to bring up the search dialogue box, then type in the 4 letter SCAC , the 8 digit MCN, or all or part of the company name.
A6: Note: g/tm=g/ton-mile | G6: Performance Rankings and Emission Factors
G7: Grams per Mile | M7: Grams per Ton-Mile
A8: CompanyDivisionName | B8: Mode | C8: SubMode | D8: Fleet Type | E8: SCAC | F8: MCN | G8: g/mile CO2 Rank | H8: g/mile CO2 | I8: g/mile NOx Rank | J8: g/mile NOx | K8: g/mile PM Rank | L8: g/mile PM | M8: g/tm CO2 Rank | N8: g/tm CO2 | O8: g/tm NOx Rank | P8: g/tm NOx | Q8: g/tm PM Rank | R8: g/tm PM | T8: SCAC_Self
A9: 1st Choice Logistics LLC | B9: Logistics | C9: Logistics | E9: FCOS | F9: MC833561 | G9: 5 | H9: 2460 | I9: 5 | J9: 28.5 | K9: 5 | L9: 1.275 | M9: 5 | N9: 492.5 | O9: 5 | P9: 3.35 | Q9: 5 | R9: 0.177 | T9: FCOS
A10: 3 Rivers Logistics, Inc | B10: Logistics | C10: Logistics | E10: TVQI | F10: MC376181 | G10: 5 | H10: 2460 | I10: 5 | J10: 28.5 | K10: 4 | L10: 1.025 | M10: 5 | N10: 492.5 | O10: 5 | P10: 3.35 | Q10: 4 | R10: 0.139 | T10: TVQI
A11: A & Z Trucking, Inc. | B11: Logistics | C11: Logistics | E11: AZTD | F11: MC510449 | G11: 5 | H11: 2460 | I11: 5 | J11: 28.5 | K11: 4 | L11: 1.025 | M11: 5 | N11: 492.5 | O11: 5 | P11: 3.35 | Q11: 4 | R11: 0.139 | T11: AZTD
A12: A&R Global Logistics | B12: Logistics | C12: Logistics | E12: AMLQ | F12: MC316077 | G12: 4 | H12: 2250 | I12: 3 | J12: 18.5 | K12: 3 | L12: 0.775 | M12: 2 | N12: 207.5 | O12: 2 | P12: 1.25 | Q12: 5 | R12: 0.177 | T12: AMLQ
A13: A.M.Transport Services, Inc. | B13: Logistics | C13: Logistics | E13: AMNO | F13: MC224875 | G13: 4 | H13: 2250 | I13: 5 | J13: 28.5 | K13: 4 | L13: 1.025 | M13: 4 | N13: 397.5 | O13: 4 | P13: 2.65 | Q13: 4 | R13: 0.139 | T13: AMNO
A14: Ace Logistics, Inc. | B14: Logistics | C14: Logistics | E14: ACEI | F14: MC411479 | G14: 4 | H14: 2250 | I14: 4 | J14: 23.5 | K14: 4 | L14: 1.025 | M14: 4 | N14: 397.5 | O14: 4 | P14: 2.65 | Q14: 4 | R14: 0.139 | T14: ACEI
A15: Adams Third Wave Logistics LLC: Freight Broker | B15: Logistics | C15: Logistics | E15: AHWE | F15: MC723939 | G15: 1 | H15: 1620 | I15: 1 | J15: 8.5 | K15: 1 | L15: 0.275 | M15: 1 | N15: 112.5 | O15: 1 | P15: 0.55 | Q15: 1 | R15: 0.025 | T15: AHWE
A16: Addison Transportation | B16: Logistics | C16: Logistics | E16: AFDN | F16: MC326834 | G16: 4 | H16: 2250 | I16: 4 | J16: 23.5 | K16: 4 | L16: 1.025 | M16: 4 | N16: 397.5 | O16: 4 | P16: 2.65 | Q16: 4 | R16: 0.139 | T16: AFDN
A17: ADM Logistics, Inc. | B17: Logistics | C17: Logistics | E17: ADOS | F17: MC274764 | G17: 1 | H17: 1620 | I17: 1 | J17: 8.5 | K17: 1 | L17: 0.275 | M17: 2 | N17: 207.5 | O17: 2 | P17: 1.25 | Q17: 2 | R17: 0.063 | T17: ADOS
A18: Advanced Transportation Services, Inc. | B18: Logistics | C18: Logistics | E18: AVDR | F18: MC191784 | G18: 4 | H18: 2250 | I18: 3 | J18: 18.5 | K18: 3 | L18: 0.775 | M18: 3 | N18: 302.5 | O18: 3 | P18: 1.95 | Q18: 3 | R18: 0.101 | T18: AVDR
A19: Aeronet Worldwide: supply chain solutions | B19: Logistics | C19: Logistics | E19: AERG,AERN | F19: MC0033994 | G19: 1 | H19: 1620 | I19: 1 | J19: 8.5 | K19: 1 | L19: 0.275 | M19: 1 | N19: 112.5 | O19: 1 | P19: 0.55 | Q19: 1 | R19: 0.025 | T19: AERG,AERN
A20: AFN, LLC | B20: Logistics | C20: Logistics | E20: AFNW | F20: MC446639 | G20: 3 | H20: 2040 | I20: 3 | J20: 18.5 | K20: 3 | L20: 0.775 | M20: 3 | N20: 302.5 | O20: 3 | P20: 1.95 | Q20: 3 | R20: 0.101 | T20: AFNW
... A595: Zipline Logistics, LLC | B595: Logistics | C595: Logistics | E595: N/A | F595: MC600879 | G595: 1 | H595: 1620 | I595: 1 | J595: 8.5 | K595: 1 | L595: 0.275 | M595: 1 | N595: 112.5 | O595: 1 | P595: 0.55 | Q595: 1 | R595: 0.025 | T595: N/A
A596: C.R. England: Intermodal | B596: Multi-modal | E596: ENGI | F596: MC124679 | H596: 1225 | J596: 18.5 | L596: 0.5 | N596: 30 | P596: 0.425 | R596: 0.014 | T596: ENGI
A597: Hub Group: Intermodal | B597: Multi-modal | E597: HUBG | F597: MC507885 | H597: 1225 | J597: 17.5 | L597: 0.48 | N597: 40 | P597: 0.475 | R597: 0.016 | T597: HUBG
A598: Independent Dispatch, Inc.: Intermodal | B598: Multi-modal | E598: INDD | F598: MC156480 | H598: 1075 | J598: 18.5 | L598: 0.5 | N598: 30 | P598: 0.425 | R598: 0.014 | T598: INDD
A599: Independent Dispatch, Inc.: Regional Trucking | B599: Multi-modal | E599: INDD | F599: MC156480 | H599: 1525 | J599: 15.5 | L599: 0.44 | N599: 60 | P599: 0.425 | R599: 0.016 | T599: INDD
A600: J.B. Hunt Transport, Inc.: Intermodal Division | B600: Multi-modal | E600: QPMT | F600: MC135797 | H600: 1075 | J600: 16.5 | L600: 0.44 | N600: 30 | P600: 0.375 | R600: 0.01 | T600: QPMT
A601: Kleysen Group LP: Intermodal Division | B601: Multi-modal | E601: KLET | F601: MCMB 0693372 | H601: 1375 | J601: 15.5 | L601: 0.46 | N601: 30 | P601: 0.425 | R601: 0.012 | T601: KLET
A602: Kleysen Group LP: Truckload Division | B602: Multi-modal | E602: KLET | F602: MCMB 0693372 | H602: 1675 | J602: 15.5 | L602: 0.44 | N602: 60 | P602: 0.375 | R602: 0.012 | T602: KLET
A603: Market Transport, Ltd.: Logistics | B603: Multi-modal | E603: MTLZ | F603: MC140827 | H603: 1525 | J603: 15.5 | L603: 0.52 | N603: 70 | P603: 0.575 | R603: 0.018 | T603: MTLZ
A604: Marten Transport LTD | B604: Multi-modal | E604: MTEN | F604: MC103798 | H604: 1675 | J604: 15.5 | L604: 0.44 | N604: 70 | P604: 0.375 | R604: 0.01 | T604: MTEN
A605: Schneider: Schneider Intermodal Division | B605: Multi-modal | E605: SCNN | F605: MC264184 | H605: 1075 | J605: 16.5 | L605: 0.46 | N605: 30 | P605: 0.425 | R605: 0.014 | T605: SCNN
A606: Triple Crown Services Company: rail operations | B606: Multi-modal | E606: TCSR | F606: MC263591 | H606: 1225 | J606: 17.5 | L606: 0.5 | N606: 40 | P606: 0.525 | R606: 0.016 | T606: TCSR
A607: UPS Small Package | B607: Multi-modal | E607: UPSN,UPSS | F607: MC115495 | H607: 1225 | J607: 15.5 | L607: 0.44 | N607: 70 | P607: 0.575 | R607: 0.018 | T607: UPSN,UPSS
... A609: YRC Worldwide Inc.: YRC Freight | B609: Multi-modal | E609: RDWY | F609: MC071821 | H609: 1675 | J609: 15.5 | L609: 0.46 | N609: 70 | P609: 0.575 | R609: 0.018 | T609: RDWY
A610: 101 Transport, Inc. | B610: Truck | C610: TL/Dry Van | D610: For-Hire | E610: OZOT | F610: MC625894 | G610: 2 | H610: 1560 | I610: 3 | J610: 5.9 | K610: 5 | L610: 0.086 | M610: 1 | N610: 74 | O610: 3 | P610: 0.375 | Q610: 5 | R610: 0.008 | T610: OZOT
A611: 1262380 Ontario Limited/dba FF Express | B611: Truck | C611: Expedited | D611: For-Hire | E611: FFXR | F611: MC343105 | G611: 2 | H611: 850 | I611: 2 | J611: 1.55 | K611: 2 | L611: 0.045 | M611: 4 | N611: 400 | O611: 3 | P611: 0.75 | Q611: 5 | R611: 0.0335 | T611: FFXR
A612: 1527530 Ontario Inc./M&M Carriers | B612: Truck | C612: TL/Dry Van | D612: For-Hire | E612: MNMR | F612: MCN/A | G612: 2 | H612: 1560 | I612: 2 | J612: 3.4 | K612: 2 | L612: 0.026 | M612: 2 | N612: 84 | O612: 2 | P612: 0.225 | Q612: 2 | R612: 0.002 | T612: MNMR
A613: 1541335 Ontario Inc./Road Link Xpress | B613: Truck | C613: TL/Dry Van | D613: For-Hire | E613: ROAD | F613: MCN/A | G613: 5 | H613: 1800 | I613: 3 | J613: 5.9 | K613: 5 | L613: 0.086 | M613: 2 | N613: 84 | O613: 2 | P613: 0.225 | Q613: 4 | R613: 0.006 | T613: ROAD
A614: 1579901 Ontario Inc./ASL Global Logistics | B614: Truck | C614: Refrigerated | D614: For-Hire | E614: AGBM | F614: MCN/A | G614: 2 | H614: 1640 | I614: 5 | J614: 7 | K614: 5 | L614: 0.175 | M614: 2 | N614: 82 | O614: 4 | P614: 0.425 | Q614: 5 | R614: 0.012 | T614: AGBM
A615: 1628939 Ontario LTD o/a P&D Freightlines | B615: Truck | C615: TL/Dry Van | D615: For-Hire | E615: PDGH | F615: MCN/A | G615: 3 | H615: 1640 | I615: 4 | J615: 8.4 | K615: 5 | L615: 0.086 | M615: 2 | N615: 84 | O615: 3 | P615: 0.375 | Q615: 5 | R615: 0.008 | T615: PDGH
A616: 1st Express Inc. | B616: Truck | C616: TL/Dry Van | D616: For-Hire | E616: FSEP | F616: MC181440 | G616: 2 | H616: 1560 | I616: 3 | J616: 5.9 | K616: 5 | L616: 0.086 | M616: 2 | N616: 84 | O616: 2 | P616: 0.225 | Q616: 4 | R616: 0.006 | T616: FSEP
A617: 2210310 Ontario Inc./Dynamic Freight Haulers | B617: Truck | C617: TL/Dry Van | D617: For-Hire | E617: DFHR | F617: MC691346 | G617: 4 | H617: 1720 | I617: 4 | J617: 8.4 | K617: 5 | L617: 0.086 | M617: 5 | N617: 114 | O617: 4 | P617: 0.525 | Q617: 5 | R617: 0.008 | T617: DFHR
A618: 2322819 Ontario Inc./Right Service Right Choice | B618: Truck | C618: TL/Dry Van | D618: For-Hire | E618: TTWT | F618: MCN/A | G618: 2 | H618: 1560 | I618: 3 | J618: 5.9 | K618: 5 | L618: 0.086 | M618: 3 | N618: 94 | O618: 3 | P618: 0.375 | Q618: 4 | R618: 0.006 | T618: TTWT
A619: 24/7 Express Logistics, Inc.: Truckload Denver | B619: Truck | C619: LTL/Dry Van | D619: For-Hire | E619: TFCD | F619: MC426943 | G619: 3 | H619: 1550 | I619: 1 | J619: 1.4 | K619: 1 | L619: 0.01 | M619: 4 | N619: 146 | O619: 1 | P619: 0.06 | Q619: 1 | R619: 0.00085 | T619: TFCD
A620: 24/7 Express Logistics, Inc.: Truckload KC | B620: Truck | C620: Mixed | D620: For-Hire | E620: TFCY | F620: MC426943 | G620: 4 | H620: 1800 | I620: 1 | J620: 1.55 | K620: 1 | L620: 0.015 | M620: 5 | N620: 113 | O620: 1 | P620: 0.075 | Q620: 1 | R620: 0.00085 | T620: TFCY
A621: 24/7 Express Logistics, Inc: Truckload | B621: Truck | C621: Mixed | E621: TFCY | F621: MC426943 | G621: 5 | H621: 1900 | I621: 5 | J621: 11.55 | K621: 5 | L621: 0.415 | M621: 5 | N621: 113 | O621: 5 | P621: 0.675 | Q621: 5 | R621: 0.0262 | T621: TFCY
A622: 24:7 Expedite, Inc.: Freight | B622: Truck | C622: Mixed | D622: For-Hire | E622: TWFJ | F622: MC690675 | G622: 4 | H622: 1800 | I622: 3 | J622: 6.55 | K622: 1 | L622: 0.015 | M622: 5 | N622: 113 | O622: 4 | P622: 0.525 | Q622: 2 | R622: 0.0052 | T622: TWFJ
A623: 3398722 Canada Inc: JB Transport | B623: Truck | C623: Refrigerated | D623: For-Hire | E623: 74Y6 | F623: MC516915 | G623: 5 | H623: 1940 | I623: 5 | J623: 7 | K623: 5 | L623: 0.175 | M623: 3 | N623: 88 | O623: 4 | P623: 0.425 | Q623: 5 | R623: 0.012 | T623: 74Y6
A624: 3NT, LLC. | B624: Truck | C624: TL/Dry Van | D624: For-Hire | E624: THLL | F624: MC716290 | G624: 2 | H624: 1560 | I624: 1 | J624: 0.9 | K624: 1 | L624: 0.006 | M624: 1 | N624: 74 | O624: 1 | P624: 0.075 | Q624: 1 | R624: 0.0005 | T624: THLL
A625: 5/D Express, Inc.: 5/D Express,Inc | B625: Truck | C625: TL/Dry Van | D625: For-Hire | E625: FDRP | F625: MC488737 | G625: 3 | H625: 1640 | I625: 3 | J625: 5.9 | K625: 5 | L625: 0.086 | M625: 1 | N625: 74 | O625: 2 | P625: 0.225 | Q625: 3 | R625: 0.004 | T625: FDRP
A626: 6233317 Canada Inc. DBA Rockwell Truck Line | B626: Truck | C626: TL/Dry Van | D626: For-Hire | E626: RKWT | F626: MC797845 | G626: 1 | H626: 1480 | I626: 5 | J626: 10.9 | K626: 5 | L626: 0.086 | M626: 1 | N626: 74 | O626: 4 | P626: 0.525 | Q626: 5 | R626: 0.008 | T626: RKWT
A627: 8198004 Canada Inc.: A AND R Transport & Logistics | B627: Truck | C627: Mixed | D627: For-Hire | E627: ARTQ | F627: MC823220 | G627: 5 | H627: 1900 | I627: 5 | J627: 11.55 | K627: 5 | L627: 0.415 | M627: 4 | N627: 103 | O627: 4 | P627: 0.525 | Q627: 5 | R627: 0.0262 | T627: ARTQ
A628: A & A Express, LLC | B628: Truck | C628: Refrigerated | D628: For-Hire | E628: AAXB | F628: MC108419 | G628: 4 | H628: 1840 | I628: 2 | J628: 3.4 | K628: 3 | L628: 0.115 | M628: 3 | N628: 88 | O628: 2 | P628: 0.205 | Q628: 2 | R628: 0.00425 | T628: AAXB
A629: A & C Transport LLC | B629: Truck | C629: Refrigerated | D629: For-Hire | E629: ACBB | F629: MCN/A | G629: 4 | H629: 1840 | I629: 3 | J629: 4.6 | K629: 2 | L629: 0.085 | M629: 5 | N629: 100 | O629: 2 | P629: 0.205 | Q629: 2 | R629: 0.00425 | T629: ACBB
A630: A & H Cartage, Inc. | B630: Truck | C630: LTL/Dry Van | D630: For-Hire | E630: AHCG | F630: MC196753 | G630: 3 | H630: 1550 | I630: 5 | J630: 8.6 | K630: 5 | L630: 0.3 | M630: 4 | N630: 146 | O630: 5 | P630: 0.86 | Q630: 4 | R630: 0.0242 | T630: AHCG
A631: A & T Trucking Company | B631: Truck | C631: Mixed | D631: For-Hire | E631: ATNG | F631: MC292766 | G631: 5 | H631: 1900 | I631: 1 | J631: 1.55 | K631: 1 | L631: 0.015 | M631: 5 | N631: 113 | O631: 1 | P631: 0.075 | Q631: 1 | R631: 0.00085 | T631: ATNG
A632: A Plus Expediting & Logistics Inc | B632: Truck | C632: Expedited | D632: For-Hire | E632: APEP | F632: MC641074 | G632: 5 | H632: 1450 | I632: 1 | J632: 0.35 | K632: 1 | L632: 0.004 | M632: 3 | N632: 300 | O632: 1 | P632: 0.15 | Q632: 1 | R632: 0.00175 | T632: APEP
A633: A&I Express Inc. | B633: Truck | C633: Refrigerated | D633: For-Hire | E633: AIEP | F633: MC629066 | G633: 1 | H633: 1540 | I633: 3 | J633: 4.6 | K633: 5 | L633: 0.175 | M633: 1 | N633: 76 | O633: 2 | P633: 0.205 | Q633: 4 | R633: 0.00925 | T633: AIEP
... A637: A&M Transport, Inc.: Flatbed Fleet | B637: Truck | C637: Flatbed | D637: For-Hire | E637: ALKM,AFLJ | F637: MC217072 | G637: 4 | H637: 1870 | I637: 4 | J637: 11 | K637: 2 | L637: 0.0965 | M637: 2 | N637: 74 | O637: 3 | P637: 0.375 | Q637: 2 | R637: 0.0045 | T637: ALKM,AFLJ
A638: A&M Transport, Inc.: Tautliner Fleet | B638: Truck | C638: Specialized | D638: For-Hire | E638: ALKM | F638: MC217072 | G638: 2 | H638: 1712.5 | I638: 3 | J638: 5.55 | K638: 2 | L638: 0.041 | M638: 2 | N638: 65 | P638: 0 | Q638: 2 | R638: 0.0032 | T638: ALKM
A639: A&R Logistics, Inc. | B639: Truck | C639: Heavy/Bulk | D639: For-Hire | E639: ANRI | F639: MC140820 | G639: 4 | H639: 2125 | I639: 2 | J639: 5.75 | K639: 4 | L639: 0.22 | M639: 5 | N639: 89.5 | O639: 4 | P639: 0.35 | Q639: 5 | R639: 0.0085 | T639: ANRI
A640: A&S Services Group, LLC | B640: Truck | C640: TL/Dry Van | D640: For-Hire | E640: ANSW | F640: MC164166 | G640: 2 | H640: 1560 | I640: 2 | J640: 3.4 | K640: 2 | L640: 0.026 | M640: 4 | N640: 104 | O640: 2 | P640: 0.225 | Q640: 2 | R640: 0.002 | T640: ANSW
A641: A. Blair Enterprises Inc | B641: Truck | C641: Specialized | D641: For-Hire | E641: BAEN | F641: MC218608 | G641: 1 | H641: 1537.5 | I641: 1 | J641: 0.95 | K641: 1 | L641: 0.008 | M641: 5 | N641: 89 | P641: 0 | Q641: 3 | R641: 0.0082 | T641: BAEN
A642: A. Duie Pyle Inc. | B642: Truck | C642: LTL/Dry Van | D642: For-Hire | E642: PYLE | F642: MC031941 | G642: 4 | H642: 1650 | I642: 3 | J642: 5 | K642: 3 | L642: 0.14 | M642: 3 | N642: 126 | O642: 3 | P642: 0.46 | Q642: 3 | R642: 0.0152 | T642: PYLE
A643: A. L. Smith Trucking, Inc. | B643: Truck | C643: Refrigerated | D643: For-Hire | E643: SALJ | F643: MC147232 | G643: 4 | H643: 1840 | I643: 4 | J643: 5.8 | K643: 5 | L643: 0.175 | M643: 4 | N643: 94 | O643: 3 | P643: 0.315 | Q643: 4 | R643: 0.00925 | T643: SALJ
A644: A. Smith Trucking Co. Inc. | B644: Truck | C644: Flatbed | D644: For-Hire | E644: SMGD | F644: MC297422 | G644: 1 | H644: 1570 | I644: 5 | J644: 14 | K644: 5 | L644: 0.5375 | M644: 1 | N644: 66 | O644: 4 | P644: 0.525 | Q644: 4 | R644: 0.0185 | T644: SMGD
A645: A.C. Trucking, Inc.: 12073707 | B645: Truck | C645: TL/Dry Van | D645: For-Hire | E645: AKGM | F645: MC196190 | G645: 3 | H645: 1640 | I645: 3 | J645: 5.9 | K645: 2 | L645: 0.026 | M645: 1 | N645: 74 | O645: 3 | P645: 0.375 | Q645: 2 | R645: 0.002 | T645: AKGM
A646: A.D. Transport Express, Inc. | B646: Truck | C646: TL/Dry Van | D646: For-Hire | E646: ADXR | F646: MC195625 | G646: 1 | H646: 1480 | I646: 2 | J646: 3.4 | K646: 2 | L646: 0.026 | M646: 5 | N646: 114 | O646: 3 | P646: 0.375 | Q646: 2 | R646: 0.002 | T646: ADXR
A647: A.N. Webber, Inc. | B647: Truck | C647: TL/Dry Van | D647: For-Hire | E647: WANQ | F647: MC147008 | G647: 3 | H647: 1640 | I647: 2 | J647: 3.4 | K647: 2 | L647: 0.026 | M647: 3 | N647: 94 | O647: 2 | P647: 0.225 | Q647: 2 | R647: 0.002 | T647: WANQ
A648: A.O. Knabb Inc. - Northern Berks Transport Brokera | B648: Truck | C648: Refrigerated | D648: For-Hire | E648: NBTN | F648: MC677982 | G648: 5 | H648: 1940 | I648: 5 | J648: 7 | K648: 5 | L648: 0.175 | M648: 5 | N648: 100 | O648: 5 | P648: 0.535 | Q648: 5 | R648: 0.012 | T648: NBTN
A649: A/T Transportation, LLC. | B649: Truck | C649: TL/Dry Van | D649: For-Hire | E649: AUCR | F649: MCN/A | G649: 4 | H649: 1720 | I649: 2 | J649: 3.4 | K649: 3 | L649: 0.046 | M649: 2 | N649: 84 | O649: 2 | P649: 0.225 | Q649: 2 | R649: 0.002 | T649: AUCR
A650: AAA Cooper Transportation | B650: Truck | C650: LTL/Dry Van | D650: Private | E650: AACT | F650: MC55889 | G650: 3 | H650: 1550 | I650: 4 | J650: 6.8 | K650: 5 | L650: 0.3 | M650: 3 | N650: 126 | O650: 3 | P650: 0.46 | Q650: 4 | R650: 0.0242 | T650: AACT
A651: Abbyland Trucking, Inc. | B651: Truck | C651: Refrigerated | D651: For-Hire | E651: ABYL | F651: MC226145 | G651: 3 | H651: 1740 | I651: 5 | J651: 7 | K651: 5 | L651: 0.175 | M651: 3 | N651: 88 | O651: 3 | P651: 0.315 | Q651: 5 | R651: 0.012 | T651: ABYL
A652: Abco Transportation: ABTS | B652: Truck | C652: Refrigerated | D652: For-Hire | E652: ABTS | F652: MC269456 | G652: 5 | H652: 1940 | I652: 3 | J652: 4.6 | K652: 5 | L652: 0.175 | M652: 5 | N652: 100 | O652: 3 | P652: 0.315 | Q652: 4 | R652: 0.00925 | T652: ABTS
A653: ABEX Transportation, LLC | B653: Truck | C653: Dray | D653: For-Hire | E653: ABED | F653: MC647183 | G653: 2 | H653: 1655 | I653: 2 | J653: 7.5 | K653: 3 | L653: 0.33 | M653: 2 | N653: 80 | O653: 2 | P653: 0.35 | Q653: 3 | R653: 0.0149 | T653: ABED
A654: ABF Freight System, Inc. | B654: Truck | C654: LTL/Dry Van | E654: ABFS | F654: MC029910 | G654: 3 | H654: 1550 | I654: 3 | J654: 5 | K654: 4 | L654: 0.22 | M654: 3 | N654: 126 | O654: 3 | P654: 0.46 | Q654: 3 | R654: 0.0152 | T654: ABFS
A655: Abilene Motor Express | B655: Truck | C655: TL/Dry Van | D655: For-Hire | E655: AEQC | F655: MC194957 | G655: 3 | H655: 1640 | I655: 3 | J655: 5.9 | K655: 4 | L655: 0.066 | M655: 3 | N655: 94 | O655: 2 | P655: 0.225 | Q655: 3 | R655: 0.004 | T655: AEQC
A656: Above All Transport LLC | B656: Truck | C656: Refrigerated | D656: Dedicated | E656: ABVC | F656: MC0383031 | G656: 5 | H656: 1940 | I656: 5 | J656: 7 | K656: 5 | L656: 0.175 | M656: 5 | N656: 100 | O656: 5 | P656: 0.535 | Q656: 5 | R656: 0.012 | T656: ABVC
A657: Absolute Intermodal LLC | B657: Truck | C657: Dray | D657: For-Hire | E657: ASUL | F657: MC603063 | G657: 2 | H657: 1655 | I657: 2 | J657: 7.5 | K657: 2 | L657: 0.13 | M657: 2 | N657: 80 | O657: 2 | P657: 0.35 | Q657: 2 | R657: 0.0059 | T657: ASUL
A658: ABT Freight Lines Inc | B658: Truck | C658: Refrigerated | D658: For-Hire | E658: ABTL | F658: MC713583 | G658: 5 | H658: 1940 | I658: 5 | J658: 7 | K658: 5 | L658: 0.175 | M658: 4 | N658: 94 | O658: 4 | P658: 0.425 | Q658: 5 | R658: 0.012 | T658: ABTL
A659: AC Leasing Company Inc. | B659: Truck | C659: TL/Dry Van | D659: For-Hire | E659: ACWH | F659: MC156691 | G659: 3 | H659: 1640 | I659: 4 | J659: 8.4 | K659: 5 | L659: 0.086 | M659: 1 | N659: 74 | O659: 3 | P659: 0.375 | Q659: 5 | R659: 0.008 | T659: ACWH
A660: AC Transport | B660: Truck | C660: Mixed | D660: For-Hire | E660: OFTO | F660: MC465753 | G660: 3 | H660: 1700 | I660: 5 | J660: 11.55 | K660: 4 | L660: 0.305 | M660: 2 | N660: 83 | O660: 4 | P660: 0.525 | Q660: 3 | R660: 0.0122 | T660: OFTO
A661: Accelerated Courier, Inc. | B661: Truck | C661: Mixed | D661: For-Hire | E661: ACUI | F661: MC171052 | G661: 2 | H661: 1600 | I661: 1 | J661: 1.55 | K661: 1 | L661: 0.015 | M661: 5 | N661: 113 | O661: 1 | P661: 0.075 | Q661: 1 | R661: 0.00085 | T661: ACUI
A662: Accelerated Services LLC | B662: Truck | C662: Auto Carrier | D662: For-Hire | E662: ACVY | F662: MC382853 | G662: 5 | H662: 2182.5 | I662: 1 | J662: 3.65 | K662: 2 | L662: 0.09 | M662: 4 | N662: 129.5 | O662: 2 | P662: 0.33 | Q662: 2 | R662: 0.0048 | T662: ACVY
A663: Accord Transportation Ltd.: Highway | B663: Truck | C663: TL/Dry Van | D663: For-Hire | E663: ACTL | F663: MCN/A | G663: 2 | H663: 1560 | I663: 2 | J663: 3.4 | K663: 4 | L663: 0.066 | M663: 1 | N663: 74 | O663: 1 | P663: 0.075 | Q663: 2 | R663: 0.002 | T663: ACTL
A664: Ace Doran Hauling & Rigging Co | B664: Truck | C664: Flatbed | D664: For-Hire | E664: ACEH | F664: MC112304 | G664: 1 | H664: 1570 | I664: 5 | J664: 14 | K664: 5 | L664: 0.5375 | M664: 3 | N664: 82 | O664: 5 | P664: 0.675 | Q664: 5 | R664: 0.0255 | T664: ACEH
A665: Ace Forwarding, Inc | B665: Truck | C665: Mixed | D665: For-Hire | E665: AFWO,AFWP | F665: MC307158 | G665: 1 | H665: 1500 | I665: 1 | J665: 1.55 | K665: 1 | L665: 0.015 | M665: 5 | N665: 113 | O665: 2 | P665: 0.225 | Q665: 2 | R665: 0.0052 | T665: AFWO,AFWP
A666: Ace Hardware Corporation: ACHW | B666: Truck | C666: LTL/Dry Van | D666: Private | E666: ACHW | F666: MC186924 | G666: 3 | H666: 1550 | I666: 1 | J666: 1.4 | K666: 1 | L666: 0.01 | M666: 3 | N666: 126 | O666: 2 | P666: 0.26 | Q666: 1 | R666: 0.00085 | T666: ACHW
... A678: Aerodyne Transportation, LLC | B678: Truck | C678: TL/Dry Van | D678: For-Hire | E678: LDWY | F678: MC161864 | G678: 1 | H678: 1480 | I678: 1 | J678: 0.9 | K678: 2 | L678: 0.026 | M678: 1 | N678: 74 | O678: 1 | P678: 0.075 | Q678: 1 | R678: 0.0005 | T678: LDWY
A679: Aeropres Corporation | B679: Truck | C679: Tanker | D679: Private | E679: ACOH | G679: 3 | H679: 1650 | I679: 2 | J679: 3.9 | K679: 2 | L679: 0.055 | M679: 5 | N679: 75 | O679: 3 | P679: 0.23 | Q679: 2 | R679: 0.0023 | T679: ACOH
A680: Aetna Freight Lines, Inc. | B680: Truck | C680: Flatbed | D680: For-Hire | E680: AGFC | F680: MC200014 | G680: 3 | H680: 1770 | I680: 5 | J680: 14 | K680: 5 | L680: 0.5375 | M680: 3 | N680: 82 | O680: 5 | P680: 0.675 | Q680: 5 | R680: 0.0255 | T680: AGFC
A681: Afton Trucking: AFTT | B681: Truck | C681: Dray | D681: For-Hire | E681: AFTT | F681: MC164738 | G681: 5 | H681: 1925 | I681: 1 | J681: 4.5 | K681: 2 | L681: 0.13 | M681: 3 | N681: 86 | O681: 1 | P681: 0.15 | Q681: 2 | R681: 0.0059 | T681: AFTT
A682: Ag Trucking, Inc. | B682: Truck | C682: Tanker | D682: For-Hire | E682: AGTG | F682: MC13367 | G682: 3 | H682: 1650 | I682: 1 | J682: 2.3 | K682: 2 | L682: 0.055 | M682: 3 | N682: 67 | O682: 2 | P682: 0.15 | Q682: 2 | R682: 0.0023 | T682: AGTG
A683: Agri-Tel Transportation Inc. | B683: Truck | C683: Refrigerated | D683: For-Hire | E683: AGTJ | F683: MCN/A | G683: 1 | H683: 1540 | I683: 1 | J683: 2.2 | K683: 1 | L683: 0.055 | M683: 1 | N683: 76 | O683: 1 | P683: 0.095 | Q683: 1 | R683: 0.0015 | T683: AGTJ
A684: Agricultural Express Inc | B684: Truck | C684: Refrigerated | D684: For-Hire | E684: AGIE | F684: MC195889 | G684: 4 | H684: 1840 | I684: 4 | J684: 5.8 | K684: 4 | L684: 0.145 | M684: 3 | N684: 88 | O684: 3 | P684: 0.315 | Q684: 3 | R684: 0.00675 | T684: AGIE
A685: Agricultural Transport | B685: Truck | C685: Refrigerated | D685: For-Hire | E685: AGUN | F685: MC245850 | G685: 3 | H685: 1740 | I685: 3 | J685: 4.6 | K685: 2 | L685: 0.085 | M685: 1 | N685: 76 | O685: 2 | P685: 0.205 | Q685: 2 | R685: 0.00425 | T685: AGUN
A686: Aim Integrated Logistics | B686: Truck | C686: Mixed | D686: Dedicated | E686: AIDD | F686: MC244504 | G686: 5 | H686: 1900 | I686: 2 | J686: 4.05 | K686: 2 | L686: 0.085 | M686: 5 | N686: 113 | O686: 2 | P686: 0.225 | Q686: 2 | R686: 0.0052 | T686: AIDD
A687: Aim Transport, Inc. | B687: Truck | C687: Mixed | D687: For-Hire | E687: AIMP | F687: MC240419 | G687: 2 | H687: 1600 | I687: 2 | J687: 4.05 | K687: 2 | L687: 0.085 | M687: 1 | N687: 73 | O687: 2 | P687: 0.225 | Q687: 1 | R687: 0.00085 | T687: AIMP
A688: Air Capitol Delivery & Warehouse LLC | B688: Truck | C688: TL/Dry Van | D688: For-Hire | E688: AQIR | F688: MC389874 | G688: 2 | H688: 1560 | I688: 2 | J688: 3.4 | K688: 5 | L688: 0.086 | M688: 3 | N688: 94 | O688: 2 | P688: 0.225 | Q688: 5 | R688: 0.008 | T688: AQIR
A689: Air Ground Xpress, Inc. | B689: Truck | C689: Mixed | D689: For-Hire | E689: AGXP | F689: MC268342 | G689: 1 | H689: 1500 | I689: 1 | J689: 1.55 | K689: 1 | L689: 0.015 | M689: 5 | N689: 113 | O689: 2 | P689: 0.225 | Q689: 1 | R689: 0.00085 | T689: AGXP
A690: Air Ocean Transport, Inc. | B690: Truck | C690: Mixed | D690: Private | E690: AIRT | F690: MC57133 | G690: 1 | H690: 1500 | I690: 5 | J690: 11.55 | K690: 5 | L690: 0.415 | M690: 4 | N690: 103 | O690: 5 | P690: 0.675 | Q690: 5 | R690: 0.0262 | T690: AIRT
...

Sheet Sheet1
A1: CompanyDivisionName2 | B1: SCAC_Self
A2: 1st Choice Logistics LLC | B2: FCOS
A3: 3 Rivers Logistics, Inc | B3: TVQI
A4: A & Z Trucking, Inc. | B4: AZTD
A5: A&R Global Logistics | B5: AMLQ
A6: A.M.Transport Services, Inc. | B6: AMNO
A7: Ace Logistics, Inc. | B7: ACEI
A8: Adams Third Wave Logistics LLC: Freight Broker | B8: AHWE
A9: Addison Transportation | B9: AFDN
A10: ADM Logistics, Inc. | B10: ADOS
A11: Advanced Transportation Services, Inc. | B11: AVDR
A12: Aeronet Worldwide: supply chain solutions | B12: AERG,AERN
... A3381: ZNG Freight, Inc.: 1 | B3381: ZNGF
